Workbook
Name açucar: 'COMPOSIÇÃO NUTRICIONAL'!$C$4:$C$32
Name Alimentos: #REF!
Name alimentos: 'COMPOSIÇÃO NUTRICIONAL'!$C$4:$C$569
Name AlimentosTabela: #REF!
Name AntropometriaPeso: [1]Antropometria!$H$8
Name arrozmassa: 'COMPOSIÇÃO NUTRICIONAL'!$C$493:$C$497
Name barras: 'COMPOSIÇÃO NUTRICIONAL'!$C$451:$C$463
Name bebidas: 'COMPOSIÇÃO NUTRICIONAL'!$C$40:$C$49
Name Cacau: 'COMPOSIÇÃO NUTRICIONAL'!$C$552:$C$569
Name Carnepeixe: 'COMPOSIÇÃO NUTRICIONAL'!$C$488:$C$492
Name cereais: 'COMPOSIÇÃO NUTRICIONAL'!$C$50:$C$180
Name fruta: 'COMPOSIÇÃO NUTRICIONAL'!$C$181:$C$241
Name frutossecos: 'COMPOSIÇÃO NUTRICIONAL'!$C$242:$C$255
Name gelados: 'COMPOSIÇÃO NUTRICIONAL'!$C$256:$C$257
Name gelatina: 'COMPOSIÇÃO NUTRICIONAL'!$C$435:$C$439
Name gordura: 'COMPOSIÇÃO NUTRICIONAL'!$C$33:$C$39
Name leguminosas: 'COMPOSIÇÃO NUTRICIONAL'!$C$508:$C$518
Name LeiteIogurte: 'COMPOSIÇÃO NUTRICIONAL'!$C$258:$C$393
Name manteiga: 'COMPOSIÇÃO NUTRICIONAL'!$C$464:$C$487
Name ovo: 'COMPOSIÇÃO NUTRICIONAL'!$C$432:$C$434
Name pão: 'COMPOSIÇÃO NUTRICIONAL'!$C$120:$C$140
Name porçãofruta: 'COMPOSIÇÃO NUTRICIONAL'!$C$507
Name Queijofiambre: 'COMPOSIÇÃO NUTRICIONAL'!$C$396:$C$431
Name sementes: 'COMPOSIÇÃO NUTRICIONAL'!$C$447:$C$450
Name sopas: 'COMPOSIÇÃO NUTRICIONAL'!$C$519:$C$528

Sheet FICHA CLIENTE
C3: CONSULTA DE NUTRIÇÃO - FICHA DE CLIENTE
C4: NOME
C6: DATA NASCIMENTO
A9: PROFISSÃO
A10: CONTACTO TELEFÓNICO
A11: E-MAIL
A12: MOTIVO DA CONSULTA
A13: ALERGIAS/INTOLERÂNCIAS ALIMENTARES
A14: PATOLOGIAS
A15: MEDICAÇÃO
A18: DATA DA CONSULTA | C18: OBSERVAÇÕES/ ALTERAÇÕES AO PLANO ALIMENTAR IMPLEMENTADO

Sheet ANAMNESE
C2: NOME | D2: EDUARDA CARVALHO | I2: OBSERVAÇÕES
C3: DATA NASCIMENTO | D3: 32118 | E3: IDADE | F3: =DATEDIF(D3,TODAY(),"Y") -> 38 | I3: ALIMENTOS QUE NÃO GOSTA, TRANSITO INTESTINAL, CICLO MESNTRUAL,ETC…
C4: SEXO | D4: 1
C5: ETNIA | D5: 0
C6: PROFISSÃO
C7: CONTACTO TELEFÓNICO
C8: E-MAIL
C9: MOTIVO DA CONSULTA
C10: SEGUIMENTO EM NUTRIÇÃO?
C11: ALERGIAS/INTOLERÂNCIAS ALIMENTARES
C12: DESPORTO
C15: HISTÓRIA ALIMENTAR | K15: HISTÓRIA ALIMENTAR | S15: HISTÓRIA ALIMENTAR
C17: 1ªCONSULTA | G17: 44684 | K17: 2ª CONSULTA | S17: 3ª CONSULTA
B18: HORAS/LOCAL | C18: PEQUENO-ALMOÇO | J18: HORAS/LOCAL | K18: PEQUENO-ALMOÇO | R18: HORAS/LOCAL | S18: PEQUENO-ALMOÇO
B25: HORAS/LOCAL | C25: MERENDA DA MANHÃ | J25: HORAS/LOCAL | K25: MERENDA DA MANHÃ | R25: HORAS/LOCAL | S25: MERENDA DA MANHÃ
B31: HORAS/LOCAL | C31: ALMOÇO | J31: HORAS/LOCAL | K31: ALMOÇO | R31: HORAS/LOCAL | S31: ALMOÇO
B41: HORAS/LOCAL | C41: MERENDA DA TARDE | J41: HORAS/LOCAL | K41: MERENDA DA TARDE | R41: HORAS/LOCAL | S41: MERENDA DA TARDE
B48: HORAS/LOCAL | C48: JANTAR | J48: HORAS/LOCAL | K48: JANTAR | R48: HORAS/LOCAL | S48: JANTAR
B58: HORAS/LOCAL | C58: CEIA | J58: HORAS/LOCAL | K58: CEIA | R58: HORAS/LOCAL | S58: CEIA
B64: OBSERVAÇÕES AO ACONSELHAMENTO | J64: OBSERVAÇÕES AO ACONSELHAMENTO | R64: OBSERVAÇÕES AO ACONSELHAMENTO
B65: HIDRATAÇÃO | J65: HIDRATAÇÃO | R65: HIDRATAÇÃO

Sheet ANTROPOMETRIA
B1: AVALIAÇÃO DA COMPOSIÇÃO CORPORAL
B3: Data de Nascimento: | C3: =ANAMNESE!D3 -> 32118 | H3: Classificação de IMC (Segundo OMS)
B4: Idade: | C4: =DATEDIF(C3,TODAY(),"Y") -> 38 | H4: Baixo Peso | I4: <18,5
H5: Normoponderal | I5: 19 - 24,5
H6: Excesso de Peso | I6: 25-30
C7: 1ª CONSULTA | H7: Obesidade | I7: >30
B8: Avaliação Antropométrica
B9: Peso (kg) | H9: Classificação IMC- Percentis pediatria
B10: Altura (cm) | H10: Baixo Peso | I10: <1 sd - 3rd
B11: Altura (m) | C11: =C10/100 -> 0 | H11: Normoponderal | I11: 3rd e 15th/ 15th e 25th / 25th e 50th | J11: 50th e 75th /75th e 85th
B12: IMC | C12: =C9/(C11*C11) -> #DIV/0! | H12: Excesso de Peso | I12: 85th - 95th | J12: 95th e 97th
B13: Perímetros - SOMA | C13: =SUM(C14:C18) -> 0 | H13: Obesidade | I13: 97th e 99th | J13: >= 99th
B14: Perímetro da Cintura (cm)
B15: Perímetro do Braço (cm)
B16: Perímetro da Anca (cm) | H16: Classificação IMC Lipschitz Idosos
B17: Perímetro da Coxa (cm) | H17: Baixo Peso | I17: <22
B18: Perímetro Geminal (cm) | H18: Normoponderal | I18: 22 - 27
B19: Pregas | H19: Excesso de Peso / Obesidade | I19: >27
B20: Prega Tricipital (mm)
B21: Prega Subescapular (mm)
B22: Prega Bicipital (mm)
B23: Prega Iliocristal (mm) | H23: PESO IDEAL MULHERES: | I23: =(C10-100-((C10-150)/2)+((C4-20)/4)) -> -20.5
B24: Prega Supraespinal (mm) | H24: PESO IDEAL HOMENS | I24: =(C10-100-((C10-150)/4)+((C4-20)/4)) -> -58
B25: Prega Abdominal (mm) | J25: Se Idade >45
B26: Prega Geminal (mm) | H26: PESO REFERÊNCIA MULHERES | I26: =(I27) - (0.05*I27) -> -90.155 | J26: =(J27) - (0.05*J27) -> -88.825
B27: Prega Crural (mm) | H27: PESO REFERÊNCIA HOMENS | I27: =((50+(0.75*(C10-150))+(0.8*(C10-100+C4/2)/2))) -> -94.9 | J27: =((50+(0.75*(C10-150))+(0.8*(C10-100+45/2)/2))) -> -93.5
B28: Prega Peitoral (mm)
B29: Soma das Pregas | C29: =SUM(C20:C28) -> 0 | H29: RECOMENDAÇÕES | I29: MULHERES | J29: HOMENS
A30: BIOIMPEDÂNCIA | B30: %MASSA GORDA | H30: % ÁGUA CORPORAL | I30: 45-60% | J30: 50-65%
B31: KG MASSA MAGRA | H31: GORDURA VISCERAL | I31: 1-12 SAUDÁVEL
B32: % Água Corporal | H32: MASSA GORDA | I32: 20-30% | J32: 8-20 %
B33: Gordura Visceral
A34: ANTROPOMETRIA | B34: %MASSA GORDA
B35: KG MASSA MUSCULAR
H36: Valores de Referência %MG- Não Atletas
H37: HOMENS | I37: Não recomendado | J37: Limite Inferior | K37: Médio | L37: Limite Superior | M37: Obesidade
H38: 18-40 Anos | I38: <8 | J38: 8 | K38: 13 | L38: 22 | M38: >22
H39: 40-60 Anos | I39: <10 | J39: 10 | K39: 18 | L39: 25 | M39: >25
B40: Adultos | H40: >60 Anos | I40: <10 | J40: 10 | K40: 16 | L40: 23 | M40: >23
B41: %Massa Gorda | H41: MULHERES | I41: Não recomendado | J41: Limite Inferior | K41: Médio | L41: Limite Superior | M41: Obesidade
B42: atletas | I42: 8-15 ATLETA
B43: Evans, et.al [Mulheres] | C43: =(8.997 )+ (0.24658 * (ANTROPOMETRIA!C27+ANTROPOMETRIA!C25+ANTROPOMETRIA!C20)) - (1.998 *ANAMNESE!D5) -> 8.997 | H43: 18-40 Anos | I43: <20 | J43: 20 | K43: 28 | L43: 35 | M43: >35
B44: Whiters, et.al | C44: =(4.95/(1.0988 - (0.0004*(C20+C21+C22+C24+C25+C26+C27)))-4.5)*100 -> 0.49144521 | H44: 40-60 Anos | I44: <20 | J44: 25 | K44: 32 | L44: 38 | M44: >38
B45: Carter, et.al | H45: >60 Anos | I45: <25 | J45: 25 | K45: 30 | L45: 35 | M45: >35
B46: Reilly, et.al [Homens Futebol] | C46: =5.174 + (0.124*C27) +( 0.147*C25)+(0.196*C20) + (0.13*C26) -> 5.174
B47: jackson et. al homens | C47: =((4.95/(1.112-(0.00043499*(C20+C21+C23+C24+C25+C27+C28))+(0.00000055*((C28+C27+C25+C24+C23+C20+C21)*(C20+C21+C23+C24+C25+C27+C28)))-(0.00028826*C4))-4.5)*100) -> -0.42755157
B48: jackson et. al mulheres | C48: =((5.01/(1.096095-(0.0006952*(C21+C25+C27+C23))+(0.0000011*((C21+C23+C25+C27)*(C27+C25+C23+C21)))-(0.0000714*C4)))-4.57)*100 -> 1.2113951
B49: Mulheres, Não atletas
B50: Peterson, et.al | C50: =22.18945 + (C4 * 0.06368) + (C12 * 0.604) - (C10*0.1452) + ((C20+C21+C23+C27)*0.30919) - (((C20+C21+C23+C27)*(C20+C21+C23+C27)) * 0.00099562) -> #DIV/0! | H50: Valores de Referência %MG- Atletas
B51: Jackson, et. al | C51: =((5.01/(1.089733-(0.0009245*(C20+C23+C25))+(0.0000025*((C23+C20+C25)*(C20+C23+C25)))-(0.0000979*C4)))-4.57)*100 -> 4.3205296 | H51: HOMENS | I51: Baixa | J51: Média | K51: Elevada
B52: Deurenberg, et al | C52: =(1.2*C12) + (0.23*C4) - 5.4 -> #DIV/0! | H52: 18-40 Anos | I52: 5 | J52: 10 | K52: 15
B53: Sun et. al | C53: =22.18945+(C4*0.06368)+C12*0.60404-C10*0.1452+(C27+C23+C21+C20)*0.30919-((C27+C23+C21+C20)*(C20+C21+C23+C27))*0.00099562 -> #DIV/0!
B54: Média | H54: 40-60 Anos | I54: 7 | J54: 11 | K54: 18
H55: >60 Anos | I55: 9 | J55: 12 | K55: 18
B56: Homens, Não atletas | H56: MULHERES | I56: Baixa | J56: Média | K56: Elevada
B57: Peterson, et. al | C57: =20.94878 + (C4 * 0.1166) - (C10 * 0.11666) + ( (C20+C21+C23+C27)*0.42696) - (( (C20+C21+C23+C27))*( (C20+C21+C23+C27)) *0.00159) -> 25.37958 | H57: 18-40 Anos | I57: 16 | J57: 23 | K57: 28
B58: Jackson, et.al | C58: =((4.95/(1.1125025-0.0013125*(C20+C28+C21)+0.0000055*(((C20+C21+C28)*(C20+C21+C28)))-0.000244*C4))-4.5)*100 -> -1.3176983 | H58: 40-60 Anos | I58: 20 | J58: 27 | K58: 33
B59: Deurenberg, et.al | C59: =(1.2 *C12) - 10.8 + (0.23*C4)-5.4 -> #DIV/0! | H59: >60 Anos | I59: 20 | J59: 27 | K59: 33
B60: SUN et.al | C60: =20.94878 + (C4*0.1166) - C10*0.11666 + (C20+C21+C23+C25)*0.42969 -((C20+C21+C23+C25)*(C20+C21+C23+C25))*0.00159 -> 25.37958
B61: Média
H62: Valores de Referência GRVIDEZ
B63: Kg de Massa Muscular | H63: Baixo Peso | I63: 12,5 Kg a 18Kg de aumento
B64: Lee, et. al [Mulheres] Peso | C64: =(0.244*C9)+(7.8*C11)-(0.098*C4)+(ANAMNESE!D5 - 3.3) -> -7.024 | H64: Normoponderal | I64: 11,5Kg a 16Kg
B65: Lee, et. al [Homens] Peso | C65: =(0.244 * C9) + (7.8*C11) - (0.098*C4) + (ANAMNESE!D5 - 3.3) + 6.6 -> -0.424 | H65: Excesso de Peso | I65: 7Kg a 11,5Kg
H66: Obesidade | I66: 5 a 9Kg
B67: Lee, et. al [homens] | C67: =C11*(0.00744*((C112))*(C112))+0.00088*((C113))*((C113))+0.00441*((C114))+((C114)) + 2.4 - (0.048*C4) +7.8 -> -1.5801
B68: Lee, et. al [mulheres] | C68: =C11*(0.00744*((C112))*(C112))+0.00088*((C113))*((C113))+0.00441*((C114))+((C114))- (0.048*$C$4) +7.8 -> -3.9801
B69: Jovens
B70: Kg de Massa Muscular
A71: Rapaz | B71: Poortmans, et.al 7-17 Anos | C71: =C11*((0.0064*(C15*C15))+(0.0032*(C17*C17))+(0.0015*(C18*C18)))+2.56+(0.136*C4) -> 7.728
A72: Rapariga | B72: Poortmans, et.al 7-17 Anos | C72: =C11*((0.0064*(C15*C15))+(0.0032*(C17*C17))+(0.0015*(C18*C18))) +(0.136*C4) -> 5.168
B74: %Massa Gorda
B75: Feminino
B76: Slaughter, et al | C76: =0.61 * (C20+C26) + 5.1 -> 5.1
B77: Slaughter, et al | C77: =0.546* (C20+C21) + 9.7 -> 9.7
B78: Brook, et al (1-11 Anos) | C78: =(4.95/(1.2063-0.0999*(LOG(C20+C21+C22+C23)))-4.5)*100 -> #NUM!
B79: Deurenberg, at al. (<15 Anos) | C79: =(1.51 *C12) - (0.7 * C4) + 1.4 -> #DIV/0!
B80: Masculino
B81: Slaughter, et al | C81: =0.735 * (C20+C26) + 1 -> 1
B82: Slaughter, et al | C82: =0.738* (C20+C21) + 1.7 -> 1.7
B83: Brook, et al (1-11 Anos) | C83: =(4.95/(1.169-(0.0788*((LOG(C20+C21+C22+C23)))))-4.5)*100 -> #NUM!
B84: Deurenberg, at al. (<15 Anos) | C84: =(1.51 *C12) - (0.7*C4) - 3.6 +1.4 -> #DIV/0!
A112: Perímetro Braço Corrigido | C112: =((C15-(3.14*C20/10)*(C15-(3.14*C20/10))/(4*3.14))-10) -> -10
A113: Perímetro da Coxa Corrigido | C113: =((C17-(3.14*C27/10)*(C17-(3.14*C27/10))/(4*3.14))-10) -> -10
A114: Perímetro do Gémeo Corrigido | C114: =((C18-(3.14*C26/10)*(C18-(3.14*C26/10))/(4*3.14))-10) -> -10

Sheet Fórmulas 
C2: Necessidades Energéticas
C4: Jovens 3-18Anos
C5: Schofield 3-10 Rapaz | D5: (19.59 x Peso) + (1,033 x Altura (cm)) + 414.9
C6: Schofield 3- 10 Rapariga | D6: (16.8 x Peso) + (1,618 x Altura (cm)) + 371.3
C7: Schofield 10-18 Rapaz | D7: (16.25 x Peso) + (1,373 x Altura (cm)) + 515.5
C8: Schofield 10-18 Rapariga | D8: (8.37 x Peso) + (4,65 x Altura (cm)) + 200
C9: FAO 3-10 Rapaz | D9: (22,7 x Peso) + 495
C10: FAO 3-10 Rapariga | D10: (22,5 x Peso) + 499
C11: FAO Rapaz 10-18 Anos | D11: 17,5*Peso +651
C12: FAO Rapariga 10-18 Anos | D12: 12,2*Peso + 746
C13: Jovens Obesidade 3-18 Anos
C14: Lazzer Rapaz | D14: ((892,68-(Idade*115,93)+(Peso*54,96)+((Altura (m))*1816,23)+1484,5))*0,2388458966275
C15: Lazzer Rapariga | D15: ((0*892,68)-(Idade*115,93)+(Peso*54,96)+(('Altura (m))*1816,23)+1484,5)*0,2388458966275
C17: Adultos
C18: FAO 18-29 Anos Homens | D18: 15.4Peso - 27H + 717)
C19: FAO 18-29 Anos Mulheres | D19: 13.3Peso + 334H + 35)
C20: FAO 30-65 Anos Homens | D20: 11.3Peso + 16H + 901
C21: FAO 30-65 Anos Mulheres | D21: 8.7Peso - 25H + 865)
C23: Cuningham, et al. | D23: 𝐺𝐸𝑅 = 21,6 × 𝑀𝐿𝐺 + 370
C24: Tem-haaf, et al. | D24: 11,936 * weight(kg)+ 587,728 *height(m)- { 8,129 * age(y)+ 191,027* sex(M~1,F~0) + 29,279
C25: Tem-haaf, et al. | D25: 22,771 *FFM + 484,264
C26: Ad Mifflin-St.Jeor, et al. | D26: 𝐺𝐸𝑅 = 19,7 × 𝑀𝐿𝐺 + 413
C28: Composição Corporal
C29: %Massa Gorda
C30: Evans, et.al (M) | D30: %BF= 8.997 6+ 0.24658*(3SKF) – 6.343*(gender) – 1.998*(race), considerando SKF: ABDOMINAL ; Crual ; TRICIPITAL; Sexo: 0F; 1M e Raça: 0 White e 1 Black
C31: Whiters, et.al | D31: BD = 1.0988 − (0.0004 ∗Σ[T, Sb, B, Sp, Ab, crural, geminal])
C32: Carter, et.al
C33: Reilly, et.al (Futebol H) | D33: BF% = 5.174 + (0.124 ∗ Crural) + (0.147 ∗ Ab) + (0.196 ∗ Tricipital) + (0.13 ∗ Geminal)
C34: Jackson homens atletas | D34: ((4,95/d)-4,50)*100. d= 1,112-0,00043499*(soma 7 pregas)+0,00000055*((soma)*(soma))-0,00028826*i
C35: jackson mulheres atletas | D35: ((5,01/d)-4,57)*100. d= 1,096095-0,0006952*(soma subescapular;abdominal;iliocristal;crural))+0,0000011*((soma)*(soma))-0,0000714*i
C37: Mulheres, Não atletas
C38: Peterson, et.al | D38: %BFnew = 22.18945 + (age 0.06368) + (BMI 0.60404)- (height 0.14520) + (sum4 0.30919)- (sum4(2) 0.00099562) [SUM4: tricipital;SB; SP; GEMINAL]
C39: Jackson, et. al | D39: ((5,01/D)-4,57)*100. D=1,089733-0,0009245*(SOMA TRICIPITAL,ABDOMINAL,ILIOCRISTAL)+0,0000025*((SOMA)*(SOMA))-0,0000979*I | E39: %=((4,95/Densidade)-4,50)*100 | F39: x=sum of triceps, chest, and subscapular skinfolds (in mm) for men, and the sum of triceps, suprailium, and abdominal skinfolds for women, and y =age in years
C40: Deurenberg, et al | D40: BF-=1,20*imc +0,23 *i -5,4
C41: Sun et. al | D41: 22,18945 + (i*0,06368) + imc*0,60404-A(cm) *0,14520+ (sum4pregas)*0,30919-((sum4p)*(sum4p))*,00099562. Pregas: tricipital;subescapular;iliocristal;crural
C42: Homens, Não atletas
C43: Peterson, et. al | D43: %BFnew = 20.94878 + (age 0.1166)- (height 0.11666) + (sum4 0.42696)- (sum4 (ao quadrado) *0.00159)
C44: Jackson, et.al | D44: 1.1125025-0.0013125(tricipital+subescapular+peitoral) + 0.0000055((tricipital;subescapular;peitoral)2 ) – 0.0002440(I) | E44: %=((4,95/Densidade)-4,50)*100 | F44: x=sum of triceps, chest, and subscapular skinfolds (in mm) for men, and the sum of triceps, suprailium, and abdominal skinfolds for women, and y =age in years
C45: Deurenberg, et.al | D45: BF-=1,20*imc-10,8*s +0,23 *i -5,4
C46: Durnin & Womersley, et. al
C47: Sun et. al | D47: 20,94878 + (I*0,1166) - A(cm) * 0,11666 + (sum 4Pregas) * 0,42696 - ((sum 4P) *(sum4p)) * 0,00159. Pregas tricipital;abdominal;subescapular;iliocristal
C49: %Massa Muscular
C50: Lee, et. al (M) | D50: 0,244.MCT + 7,8.Est (m)+ 6,6.S - 0,098.Id + Rb - 3,3
C51: Lee, et. al (H) | D51: 0,244.MCT + 7,8.Est (m)+ 6,6.S - 0,098.Id + Rb - 3,3
C54: Jovens
C55: Kg Massa Muscular
C56: Poortmans, et.al (H) 7-17 Anos | D56: SMM (kg) = Altura (m)* ( [(0.0064 * (PB)2) + (0.0032 * PCoxa (2))+ (0.0015 *PGeminal(2) + (2.56 *1 )+ (0.136 age))
C57: Poortmans, et.al (M) 7-17 Anos | D57: SMM (kg) = Altura (m)* ( [(0.0064 * (PB)2) + (0.0032 * PCoxa (2))+ (0.0015 *PGeminal(2) + (0.136 age))
C60: %Massa Gorda
C61: Feminino
C62: Slaughter, et al | D62: 0,610* (TR+Geminal)+5,1
C63: Slaughter, et al | D63: 0,546*(TR+SB)+9,7 | E63: %=((4,95/Densidade)-4,50)*100
C64: Brook, et al (1-11 Anos) | D64: BD= 1,2063-0,0999* LOG(SOMA4)
C65: Deurenberg, at al. (<15 Anos) | D65: 1,51*(imc)-0,70*Idade +1,4
C67: Masculino
C68: Slaughter, et al | D68: 0,735* (TR + Geminal)+1
C69: Slaughter, et al | D69: 0,738*(tr+SB) + 1,7
C70: Brook, et al (1-11 Anos) | D70: BD= 11690-0,0788*(log (soma4)) | E70: %=((4,95/Densidade)-4,50)*100
C71: Deurenberg, at al. (<15 Anos) | D71: 1,51*(imc)-0,70*Idade -3,6+1,4

Sheet RESULTADOS
C2: AVALIAÇÃO ANTROPOMÉTRICA
C3: Eduarda
C5: 44864
C7: PESO (Kg) | D7: =ANTROPOMETRIA!C9 -> 0 | E7: =ANTROPOMETRIA!D9 -> 0
C8: ALTURA (m) | D8: =ANTROPOMETRIA!C10/100 -> 0 | E8: =ANTROPOMETRIA!D10/100 -> 0
C9: IMC | D9: =ANTROPOMETRIA!C12 -> #DIV/0! | E9: =ANTROPOMETRIA!D12 -> 0
C10: Perímetro da Cintura (cm) | D10: =ANTROPOMETRIA!C14 -> 0 | E10: =ANTROPOMETRIA!D14 -> 0
C11: Perímetro do Braço (cm) | D11: =ANTROPOMETRIA!C15 -> 0 | E11: =ANTROPOMETRIA!D15 -> 0
C12: Perímetro da Anca (cm) | D12: =ANTROPOMETRIA!C16 -> 0 | E12: =ANTROPOMETRIA!D16 -> 0
C13: Perímetro da Coxa (cm) | D13: =ANTROPOMETRIA!C17 -> 0 | E13: =ANTROPOMETRIA!D17 -> 0
C14: Perímetro Geminal (cm) | D14: =ANTROPOMETRIA!C18 -> 0 | E14: =ANTROPOMETRIA!D18 -> 0
C15: SOMA DOS PERÍMETROS | D15: =ANTROPOMETRIA!C13 -> 0 | E15: =ANTROPOMETRIA!D13 -> 0
C16: Prega Tricipital (mm) | D16: =ANTROPOMETRIA!C20 -> 0 | E16: =ANTROPOMETRIA!D20 -> 0
C17: Prega Subescapular (mm) | D17: =ANTROPOMETRIA!C21 -> 0 | E17: =ANTROPOMETRIA!D21 -> 0
C18: Prega Bicipital (mm) | D18: =ANTROPOMETRIA!C22 -> 0 | E18: =ANTROPOMETRIA!D22 -> 0
C19: Prega Iliocristal (mm) | D19: =ANTROPOMETRIA!C23 -> 0 | E19: =ANTROPOMETRIA!D23 -> 0
C20: Prega Supraespinal (mm) | D20: =ANTROPOMETRIA!C24 -> 0 | E20: =ANTROPOMETRIA!D24 -> 0
C21: Prega Abdominal (mm) | D21: =ANTROPOMETRIA!C25 -> 0 | E21: =ANTROPOMETRIA!D25 -> 0
C22: Prega Geminal (mm) | D22: =ANTROPOMETRIA!C26 -> 0 | E22: =ANTROPOMETRIA!D26 -> 0
C23: Prega Crural (mm) | D23: =ANTROPOMETRIA!C27 -> 0 | E23: =ANTROPOMETRIA!D27 -> 0
C24: SOMA DAS PREGAS CUTÂNEAS | D24: =ANTROPOMETRIA!C28 -> 0 | E24: =ANTROPOMETRIA!D28 -> 0
C25: BIOIMPEDÂNCIA
C26: % MASSA GORDA | D26: =ANTROPOMETRIA!C30 -> 0 | E26: =ANTROPOMETRIA!D30 -> 0
C27: Kg MASSA MAGRA | D27: =ANTROPOMETRIA!C31 -> 0 | E27: =ANTROPOMETRIA!D31 -> 0
C28: % ÁGUA CORPORAL | D28: =ANTROPOMETRIA!C32 -> 0 | E28: =ANTROPOMETRIA!D32 -> 0
C29: NÍVEL GORDURA VISCERAL | D29: =ANTROPOMETRIA!C33 -> 0 | E29: =ANTROPOMETRIA!D33 -> 0
C30: ANTROPOMETRIA
C31: %MASSA GORDA | D31: =ANTROPOMETRIA!C34 -> 0 | E31: =ANTROPOMETRIA!D34 -> 0
C32: KG MASSA MUSCULAR | D32: =ANTROPOMETRIA!C35 -> 0 | E32: =ANTROPOMETRIA!D35 -> 0

Sheet NECESSIDADES ENERGÉTICAS
B2: Gasto Energético Basal
B5: Jovens 3-18Anos
B6: Schofield 3-10 Rapaz | C6: =(19.59*ANTROPOMETRIA!C9)+(1.033*ANTROPOMETRIA!C10)+414.9 -> 414.9
B7: Schofield 3- 10 Rapariga | C7: =(16.8*ANTROPOMETRIA!C9)+(1.618*ANTROPOMETRIA!C10)+371.3 -> 371.3
B8: Schofield 10-18 Rapaz | C8: =(16.25*ANTROPOMETRIA!C9)+(1.373*ANTROPOMETRIA!C10)+515.5 -> 515.5
B9: Schofield 10-18 Rapariga | C9: =(8.37*ANTROPOMETRIA!C9)+(4.65*ANTROPOMETRIA!C10)+200 -> 200
B10: FAO 3-10 Rapaz | C10: =(22.7*ANTROPOMETRIA!C9)+495 -> 495
B11: FAO 3-10 Rapariga | C11: =(22.5*ANTROPOMETRIA!C9)+499 -> 499
B12: FAO Rapaz 10-18 Anos | C12: =(17.5*ANTROPOMETRIA!C9) + 746 -> 746
B13: FAO Rapariga 10-18 Anos | C13: =(12.2*ANTROPOMETRIA!C9) +217 -> 217
B14: NE (Kcal)
B16: Jovens Obesidade 3-18Anos
B17: Lazzer Rapaz | C17: =((892.68-(ANTROPOMETRIA!C4*115.93)+(ANTROPOMETRIA!C9*54.96)+((ANTROPOMETRIA!C11)*1816.23)+1484.5))*0.2388458966275 -> -484.41769
B18: Lazzer Rapariga | C18: =((0*892.68)-(ANTROPOMETRIA!C4*115.93)+(ANTROPOMETRIA!C9*54.96)+((ANTROPOMETRIA!C11)*1816.23)+1484.5)*0.2388458966275 -> -697.63065
B19: NE (Kcal)
B21: Adultos
B22: Harris Benedict Homens | C22: =66.5+(13.75*ANTROPOMETRIA!C9)+(5*ANTROPOMETRIA!C10)-(6.78*ANTROPOMETRIA!C4) -> -191.14
B23: Harris Benedict Mulheres | C23: =655.0955+(1.8496*ANTROPOMETRIA!C10)+(9.5634*ANTROPOMETRIA!C9)-(4.6756*ANTROPOMETRIA!C4) -> 477.4227
B25: FAO 18-29 Anos Homens | C25: =(15.4*ANTROPOMETRIA!C9) -(27*(ANTROPOMETRIA!C10/100))+717 -> 717
B26: FAO 18-29 Anos Mulheres | C26: =(13.3*ANTROPOMETRIA!C9)+(334*(ANTROPOMETRIA!C10/100))+35 -> 35
B27: FAO 30-65 Anos Homens | C27: =(11.3*ANTROPOMETRIA!C9)+(16*(ANTROPOMETRIA!C10/100))+901 -> 901
B28: FAO 30-65 Anos Mulheres | C28: =(8.7*ANTROPOMETRIA!C9)-(25*(ANTROPOMETRIA!C10/100))+865 -> 865
B30: Cuningham, et al. | C30: =(21.6*(ANTROPOMETRIA!C9 - ANTROPOMETRIA!C36) )+ 370 -> 370
B32: Tem-haaf, et al. | C32: =(11.936*ANTROPOMETRIA!C9 )+ (587.728*ANTROPOMETRIA!C11) - (8.129*ANTROPOMETRIA!C4) + (191.027*ANAMNESE!D4) + 29.279 -> -88.596
B33: Tem-haaf, et al. | C33: =(22.771*(ANTROPOMETRIA!C9-ANTROPOMETRIA!C38))+ 484.264 -> 484.264
B35: Ad Mifflin-St.Jeor, et al. | C35: =(19.7*(ANTROPOMETRIA!C9-ANTROPOMETRIA!C38))+413 -> 413
B37: NE (Kcal)
B40: Gasto energético Total
B41: GET = NE X FA
C44: Objetivo do Plano
B45: GET =
B48: Fatores de Atividade
B49: PAL Adultos (FAO) | D49: PAL Crianças | E49: Leve | F49: Moderada | G49: Intensa
B50: <1,40 : Muito sedentário | D50: 1-5Anos | E50: 1.45 | F50: 1.6 | G50: -
B51: 1,40- 1,69 : Sedentário | D51: 6 - 13 Anos (H) | E51: 1.55 | F51: 1.75 | G51: 1.95
B52: 1,70- 1,99 : Moderada | D52: 6-13 Anos (M) | E52: 1.5 | F52: 1.7 | G52: 1.9
B53: 2- 2,40 : Vigorosa | D53: 14-18Anos (H) | E53: 1.6 | F53: 1.8 | G53: 2.05
B54: >2,40: Extrema | D54: 14-18 Anos (M) | E54: 1.45 | F54: 1.65 | G54: 1.85
A56: PPT BWIZER | B56: PAL ADULTOS
B57: 1,2 : Sedentário / Pouco ou nenhum exercício
B58: 1,375 : Aividade Leve / Exercício Leve 1-3x por semana | D58: Fatores de Stress
B59: 1,55 : Atividade Moderada / 6-7x por semana | D59: 1,2 : Lesão pequena/ cirurgia/ fratura
B60: 1,725 : Muito Ativo / Treinos bidiários ou HIIT todos os dias | D60: 1,5 : Infeçao/ Trauma com cirurgia
B61: 1,9 : Extremo / HIIT bidiário ou treinos pra competições endurance
D62: GRAVIDEZ | E62: =354-(6.91*ANTROPOMETRIA!C4)+ 1.2*((9.36*ANTROPOMETRIA!C9)+(701.6*ANTROPOMETRIA!C10)) -> 91.42 | G62: Kcal para IMC normal
B63: Fórmula de Bolso: 30 Kcal/MIG/Dia + Gasto da Atividade Física | E63: =448-(7.95*ANTROPOMETRIA!C4)+1.2*((11.4*ANTROPOMETRIA!C9)+(619*ANTROPOMETRIA!C10)) -> 145.9 | G63: Kcal para Obesidade
B64: HIDRATAÇÃO | E64: E63*semanas de gravidez + 180
B65: Fórmula de Bolso : (30ml *kg)/1000 | C65: =(30*ANTROPOMETRIA!C9)/1000 -> 0 | G65: ´+ 2 º e terceiro trimestre

Sheet DISTRIBUIÇÃO MACROS
B3: Objetivo do Plano (Kcal): | C3: ='NECESSIDADES ENERGÉTICAS'!C45 -> 0
B5: Distribuição de Macronutrientes | C5: % VET | D5: Kcal | E5: g | F5: g/kg
B6: Proteína | C6: 15 | D6: =(C6/100)*'NECESSIDADES ENERGÉTICAS'!C45 -> 0 | E6: =(D6/4) -> 0 | F6: =E6/ANTROPOMETRIA!C9 -> #DIV/0!
B7: Hidratos de Carbono | C7: 55 | D7: =(C7/100)*'NECESSIDADES ENERGÉTICAS'!C45 -> 0 | E7: =D7/4 -> 0 | F7: =E7/ANTROPOMETRIA!C9 -> #DIV/0!
B8: Lípidos | C8: 30 | D8: =(C8/100)*'NECESSIDADES ENERGÉTICAS'!C45 -> 0 | E8: =D8/9 -> 0 | F8: =E8/ANTROPOMETRIA!C9 -> #DIV/0!
C9: =SUM(C6:C8) -> 100
D11: RECOMENDAÇÕES
B12: DRI JOVENS
A13: HC | B13: 45-65% VET
B14: 3-8 g/Kg
A15: LIP | B15: 25-30%VET
A16: PRT | B16: 1,2-1,8 g/Kg
A19: HC | B19: – < 1 hora média diária de treino – ingestão hidratos carbono de 3 -5g/kg – 1 a 2 horas médias diárias de treino – ingestão hidratos carbono de 5-7g/kg – 2 a 3 horas médias diárias de treino – ingestão hidratos carbono de 6 -10g/kg – 4 a 5 horas médias diárias de treino – ingestão hidratos carbono de 8 -12g/kg
A23: DRI
A24: PT | B24: 0,6 -2,2g/kg/dia
A25: HC | B25: 3-5G/Lg/dia
A26: LP | B26: 05-1,5g/kg/dia
A28: 20g PT, a cada 3horas pós exercício para potenciar os ganhos de massa muscular (0,25 - 0,3g/kg/dia)

Sheet CÁLCULOS PLANO ALIMENTAR
C1: Objetivo | D1: Atual | E1: Diferença
B2: Kcal | C2: ='DISTRIBUIÇÃO MACROS'!C3 -> 0 | D2: =P11+P23+P33+P45+P66+P79+P55 -> #NAME? | E2: =C2-D2 -> #NAME?
B3: PROT (g) | C3: ='DISTRIBUIÇÃO MACROS'!E6 -> 0 | D3: =P12+P24+P34+P46+P67+P80+P56 -> #NAME? | E3: =C3-D3 -> #NAME?
B4: HC (g) | C4: ='DISTRIBUIÇÃO MACROS'!E7 -> 0 | D4: =P13+P25+P35+P47+P68+P81+P57 -> #NAME? | E4: =C4-D4 -> #NAME?
B5: LIP (g) | C5: ='DISTRIBUIÇÃO MACROS'!E8 -> 0 | D5: =P14+P26+P36+P48+P69+P82+P58 -> #NAME? | E5: =C5-D5 -> #NAME?
N8: Valor Nutricional
A9: Pequeno Almoço
A10: Horas | D10: (g/mL) | F10: Kcal | G10: Prot | H10: HC | I10: LP | J10: Observações | N10: Pequeno-Almoço
B11: 1 | C11: Tortita de Arroz | D11: =_xlfn.XLOOKUP(C11,cereais,'COMPOSIÇÃO NUTRICIONAL'!E50:E180,0,0,1)*'CÁLCULOS PLANO ALIMENTAR'!B11 -> #NAME? | F11: =_xlfn.XLOOKUP(C11,cereais,'COMPOSIÇÃO NUTRICIONAL'!F50:F180,0,0,1)*B11 -> #NAME? | G11: =_xlfn.XLOOKUP(C11,cereais,'COMPOSIÇÃO NUTRICIONAL'!G50:G180,0,0,1)*'CÁLCULOS PLANO ALIMENTAR'!B11 -> #NAME? | H11: =_xlfn.XLOOKUP(C11,cereais,'COMPOSIÇÃO NUTRICIONAL'!H50:H180,0,0,1)*'CÁLCULOS PLANO ALIMENTAR'!B11 -> #NAME? | I11: =_xlfn.XLOOKUP(C11,cereais,'COMPOSIÇÃO NUTRICIONAL'!I50:I180,0,0,1)*'CÁLCULOS PLANO ALIMENTAR'!B11 -> #NAME? | N11: Kcal | P11: =F11+F12+F13+F15+F14+F16+F17+F18+F19 -> #NAME?
C12: Fatia de Queijo Flamengo Light fatiado | D12: =_xlfn.XLOOKUP(C12,Queijofiambre,'COMPOSIÇÃO NUTRICIONAL'!E396:E431,0,0,1)*'CÁLCULOS PLANO ALIMENTAR'!B12 -> 0 | F12: =_xlfn.XLOOKUP(C12,Queijofiambre,'COMPOSIÇÃO NUTRICIONAL'!F396:F431,0,0,1)*'CÁLCULOS PLANO ALIMENTAR'!B12 -> 0 | G12: =_xlfn.XLOOKUP(C12,Queijofiambre,'COMPOSIÇÃO NUTRICIONAL'!G396:G431,0,0,1)*'CÁLCULOS PLANO ALIMENTAR'!B12 -> 0 | H12: =_xlfn.XLOOKUP(C12,Queijofiambre,'COMPOSIÇÃO NUTRICIONAL'!H396:H431,0,0,1)*'CÁLCULOS PLANO ALIMENTAR'!B12 -> 0 | I12: =_xlfn.XLOOKUP(C12,Queijofiambre,'COMPOSIÇÃO NUTRICIONAL'!I396:I431,0,0,1)*'CÁLCULOS PLANO ALIMENTAR'!B12 -> 0 | N12: PROT | P12: =G11+G12+G13+G14+G15+G16+G17+G18+G19 -> #NAME?
C13: Colher de Chá de Matinal Extra Light | D13: =_xlfn.XLOOKUP(C13,manteiga,'COMPOSIÇÃO NUTRICIONAL'!E464:E487,0,0,1)*'CÁLCULOS PLANO ALIMENTAR'!B13 -> 0 | F13: =_xlfn.XLOOKUP(C13,manteiga,'COMPOSIÇÃO NUTRICIONAL'!F464:F487,0,0,1)*'CÁLCULOS PLANO ALIMENTAR'!B13 -> 0 | G13: =_xlfn.XLOOKUP(C13,manteiga,'COMPOSIÇÃO NUTRICIONAL'!G464:G487,0,0,1)*'CÁLCULOS PLANO ALIMENTAR'!B13 -> 0 | H13: =_xlfn.XLOOKUP(C13,manteiga,'COMPOSIÇÃO NUTRICIONAL'!H464:H487,0,0,1)*'CÁLCULOS PLANO ALIMENTAR'!B13 -> 0 | I13: =_xlfn.XLOOKUP(C13,manteiga,'COMPOSIÇÃO NUTRICIONAL'!I464:I487,0,0,1)*'CÁLCULOS PLANO ALIMENTAR'!B13 -> 0 | N13: HC | P13: =H11+H12+H13+H14+H15+H17+H16+H18 -> #NAME?
C14: Iogurte Líquido Magro Mimosa, 0%Açúcar | D14: =_xlfn.XLOOKUP(C14,LeiteIogurte,'COMPOSIÇÃO NUTRICIONAL'!E258:E393,0,0,1)*'CÁLCULOS PLANO ALIMENTAR'!B14 -> 0 | F14: =_xlfn.XLOOKUP(C14,LeiteIogurte,'COMPOSIÇÃO NUTRICIONAL'!F258:F393,0,0,1)*'CÁLCULOS PLANO ALIMENTAR'!B14 -> 0 | G14: =_xlfn.XLOOKUP(C14,LeiteIogurte,'COMPOSIÇÃO NUTRICIONAL'!G258:G393,0,0,1)*'CÁLCULOS PLANO ALIMENTAR'!B14 -> 0 | H14: =_xlfn.XLOOKUP(C14,LeiteIogurte,'COMPOSIÇÃO NUTRICIONAL'!H258:H393,0,0,1)*'CÁLCULOS PLANO ALIMENTAR'!B14 -> 0 | I14: =_xlfn.XLOOKUP(C14,LeiteIogurte,'COMPOSIÇÃO NUTRICIONAL'!I258:I393,0,0,1)*'CÁLCULOS PLANO ALIMENTAR'!B14 -> 0 | N14: LIP | P14: =I11+I12+I14+I13+I15+I16+I17+I18 -> #NAME?
C15: Colher de chá de Doce de 4 frutos Casa Mateus, 0%açúcares | D15: =_xlfn.XLOOKUP(C15,açucar,'COMPOSIÇÃO NUTRICIONAL'!E4:E32,0,0,1)*'CÁLCULOS PLANO ALIMENTAR'!B15 -> 0 | F15: =_xlfn.XLOOKUP(C15,açucar,'COMPOSIÇÃO NUTRICIONAL'!F4:F32,0,0,1)*'CÁLCULOS PLANO ALIMENTAR'!B15 -> 0 | G15: =_xlfn.XLOOKUP(C15,açucar,'COMPOSIÇÃO NUTRICIONAL'!G4:G32,0,0,1)*'CÁLCULOS PLANO ALIMENTAR'!B15 -> 0 | H15: =_xlfn.XLOOKUP(C15,açucar,'COMPOSIÇÃO NUTRICIONAL'!H4:H32,0,0,1)*'CÁLCULOS PLANO ALIMENTAR'!B15 -> 0 | I15: =_xlfn.XLOOKUP(C15,açucar,'COMPOSIÇÃO NUTRICIONAL'!I4:I32,0,0,1)*B15 -> 0
C16: 100 gr de Bebida de Cereais Mokambo | D16: =_xlfn.XLOOKUP(C16,Cacau,'COMPOSIÇÃO NUTRICIONAL'!E552:E569,0,0,1)*B16 -> 0 | F16: =_xlfn.XLOOKUP(C16,Cacau,'COMPOSIÇÃO NUTRICIONAL'!F552:F569,0,0,1)*'CÁLCULOS PLANO ALIMENTAR'!B16 -> 0 | G16: =_xlfn.XLOOKUP(C16,Cacau,'COMPOSIÇÃO NUTRICIONAL'!G552:G569,0,0,1)*B16 -> 0 | H16: =_xlfn.XLOOKUP(C16,Cacau,'COMPOSIÇÃO NUTRICIONAL'!H552:H569,0,0,1)*B16 -> 0 | I16: =_xlfn.XLOOKUP(C16,Cacau,'COMPOSIÇÃO NUTRICIONAL'!I552:I569,0,0,1)*B16 -> 0
C17: Porção Fruta | D17: =_xlfn.XLOOKUP(C17,alimentos,'COMPOSIÇÃO NUTRICIONAL'!E4:E569,0,0,1)*B17 -> 0 | F17: =_xlfn.XLOOKUP(C17,alimentos,'COMPOSIÇÃO NUTRICIONAL'!F4:F569,0,0,1)*B17 -> 0 | G17: =_xlfn.XLOOKUP(C17,alimentos,'COMPOSIÇÃO NUTRICIONAL'!G4:G569,0,0,1)*B17 -> 0 | H17: =_xlfn.XLOOKUP(C17,alimentos,'COMPOSIÇÃO NUTRICIONAL'!H4:H569,0,0,1)*'CÁLCULOS PLANO ALIMENTAR'!B17 -> 0 | I17: =_xlfn.XLOOKUP(C17,alimentos,'COMPOSIÇÃO NUTRICIONAL'!I4:I569,0,0,1)*B17 -> 0
C18: Manteiga de Amendoim em pó | D18: =_xlfn.XLOOKUP(C18,alimentos,'COMPOSIÇÃO NUTRICIONAL'!E4:E569,0,0,1)*B18 -> 0 | F18: =_xlfn.XLOOKUP(C18,alimentos,'COMPOSIÇÃO NUTRICIONAL'!F4:F569,0,0,1)*B18 -> 0 | G18: =_xlfn.XLOOKUP(C18,alimentos,'COMPOSIÇÃO NUTRICIONAL'!G4:G569,0,0,1)*B18 -> 0 | H18: =_xlfn.XLOOKUP(C18,alimentos,'COMPOSIÇÃO NUTRICIONAL'!H4:H569,0,0,1)*B18 -> 0 | I18: =_xlfn.XLOOKUP(C18,alimentos,'COMPOSIÇÃO NUTRICIONAL'!I4:I569,0,0,1)*B18 -> 0
A21: Merenda da Manhã | N21: Merenda da Manhã
A22: Horas | B22: Quantidade | D22: (g/mL) | F22: Kcal | G22: Prot | H22: HC | I22: LP | J22: Observações
C23: Bolacha Maria | D23: =_xlfn.XLOOKUP(C23,cereais,'COMPOSIÇÃO NUTRICIONAL'!E50:E180,0,0,1)*'CÁLCULOS PLANO ALIMENTAR'!B23 -> 0 | F23: =_xlfn.XLOOKUP(C23,cereais,'COMPOSIÇÃO NUTRICIONAL'!F50:F180,0,0,1)*B23 -> 0 | G23: =_xlfn.XLOOKUP(C23,cereais,'COMPOSIÇÃO NUTRICIONAL'!G50:G180,0,0,1)*B23 -> 0 | H23: =_xlfn.XLOOKUP(C23,cereais,'COMPOSIÇÃO NUTRICIONAL'!H50:H180,0,0,1)*B23 -> 0 | I23: =_xlfn.XLOOKUP(C23,cereais,'COMPOSIÇÃO NUTRICIONAL'!I50:I180,0,0,1)*B23 -> 0 | N23: Kcal | P23: =F23+F24+F25+F26+F27+F28+F29 -> 0
C24: Queijo Vaca que ri | D24: =_xlfn.XLOOKUP($C$24,Queijofiambre,'COMPOSIÇÃO NUTRICIONAL'!E396:E431,0,0,1)*'CÁLCULOS PLANO ALIMENTAR'!$B$24 -> 0 | F24: =_xlfn.XLOOKUP($C$24,Queijofiambre,'COMPOSIÇÃO NUTRICIONAL'!F396:F431,0,0,1)*'CÁLCULOS PLANO ALIMENTAR'!$B$24 -> 0 | G24: =_xlfn.XLOOKUP($C$24,Queijofiambre,'COMPOSIÇÃO NUTRICIONAL'!G396:G431,0,0,1)*'CÁLCULOS PLANO ALIMENTAR'!$B$24 -> 0 | H24: =_xlfn.XLOOKUP($C$24,Queijofiambre,'COMPOSIÇÃO NUTRICIONAL'!H396:H431,0,0,1)*'CÁLCULOS PLANO ALIMENTAR'!$B$24 -> 0 | I24: =_xlfn.XLOOKUP($C$24,Queijofiambre,'COMPOSIÇÃO NUTRICIONAL'!I396:I431,0,0,1)*'CÁLCULOS PLANO ALIMENTAR'!$B$24 -> 0 | N24: PROT | P24: =G23+G24+G25+G26+G27+G28+G29 -> 0
C25: Colher de Sobremesa de Matinal Magra | D25: =_xlfn.XLOOKUP($C$25,manteiga,'COMPOSIÇÃO NUTRICIONAL'!E464:E487,0,0,1)*'CÁLCULOS PLANO ALIMENTAR'!$B$25 -> 0 | F25: =_xlfn.XLOOKUP($C$25,manteiga,'COMPOSIÇÃO NUTRICIONAL'!F464:F487,0,0,1)*'CÁLCULOS PLANO ALIMENTAR'!$B$25 -> 0 | G25: =_xlfn.XLOOKUP($C$25,manteiga,'COMPOSIÇÃO NUTRICIONAL'!G464:G487,0,0,1)*'CÁLCULOS PLANO ALIMENTAR'!$B$25 -> 0 | H25: =_xlfn.XLOOKUP($C$25,manteiga,'COMPOSIÇÃO NUTRICIONAL'!H464:H487,0,0,1)*'CÁLCULOS PLANO ALIMENTAR'!$B$25 -> 0 | I25: =_xlfn.XLOOKUP($C$25,manteiga,'COMPOSIÇÃO NUTRICIONAL'!I464:I487,0,0,1)*'CÁLCULOS PLANO ALIMENTAR'!$B$25 -> 0 | N25: HC | P25: =H23+H24+H25+H26+H27+H28+H29 -> 0
C26: Copo Pequeno de Leite Meio-Gordo | D26: =_xlfn.XLOOKUP($C$26,LeiteIogurte,'COMPOSIÇÃO NUTRICIONAL'!E258:E393,0,0,1)*'CÁLCULOS PLANO ALIMENTAR'!$B$26 -> 0 | F26: =_xlfn.XLOOKUP($C$26,LeiteIogurte,'COMPOSIÇÃO NUTRICIONAL'!F258:F393,0,0,1)*'CÁLCULOS PLANO ALIMENTAR'!$B$26 -> 0 | G26: =_xlfn.XLOOKUP($C$26,LeiteIogurte,'COMPOSIÇÃO NUTRICIONAL'!G258:G393,0,0,1)*'CÁLCULOS PLANO ALIMENTAR'!$B$26 -> 0 | H26: =_xlfn.XLOOKUP($C$26,LeiteIogurte,'COMPOSIÇÃO NUTRICIONAL'!H258:H393,0,0,1)*'CÁLCULOS PLANO ALIMENTAR'!$B$26 -> 0 | I26: =_xlfn.XLOOKUP($C$26,LeiteIogurte,'COMPOSIÇÃO NUTRICIONAL'!I258:I393,0,0,1)*'CÁLCULOS PLANO ALIMENTAR'!$B$26 -> 0 | N26: LIP | P26: =I23+I24+I25+I26+I28+I27+I29 -> 0
C27: Colher de Chá de Açúcar Branco | D27: =_xlfn.XLOOKUP($C$27,açucar,'COMPOSIÇÃO NUTRICIONAL'!E4:E32,0,0,1)*'CÁLCULOS PLANO ALIMENTAR'!$B$27 -> 0 | F27: =_xlfn.XLOOKUP($C$27,açucar,'COMPOSIÇÃO NUTRICIONAL'!F4:F32,0,0,1)*'CÁLCULOS PLANO ALIMENTAR'!$B$27 -> 0 | G27: =_xlfn.XLOOKUP($C$27,açucar,'COMPOSIÇÃO NUTRICIONAL'!G4:G32,0,0,1)*'CÁLCULOS PLANO ALIMENTAR'!$B$27 -> 0 | H27: =_xlfn.XLOOKUP($C$27,açucar,'COMPOSIÇÃO NUTRICIONAL'!H4:H32,0,0,1)*'CÁLCULOS PLANO ALIMENTAR'!$B$27 -> 0 | I27: =_xlfn.XLOOKUP($C$27,açucar,'COMPOSIÇÃO NUTRICIONAL'!I4:I32,0,0,1)*'CÁLCULOS PLANO ALIMENTAR'!$B$27 -> 0
C28: Porção (10 Unidades) de Morango | D28: =_xlfn.XLOOKUP($C$28,fruta,'COMPOSIÇÃO NUTRICIONAL'!E181:E241,0,0,1)*'CÁLCULOS PLANO ALIMENTAR'!$B$28 -> 0 | F28: =_xlfn.XLOOKUP($C$28,fruta,'COMPOSIÇÃO NUTRICIONAL'!F181:F241,0,0,1)*'CÁLCULOS PLANO ALIMENTAR'!$B$28 -> 0 | G28: =_xlfn.XLOOKUP($C$28,fruta,'COMPOSIÇÃO NUTRICIONAL'!G181:G241,0,0,1)*'CÁLCULOS PLANO ALIMENTAR'!$B$28 -> 0 | H28: =_xlfn.XLOOKUP($C$28,fruta,'COMPOSIÇÃO NUTRICIONAL'!H181:H241,0,0,1)*'CÁLCULOS PLANO ALIMENTAR'!$B$28 -> 0 | I28: =_xlfn.XLOOKUP($C$28,fruta,'COMPOSIÇÃO NUTRICIONAL'!I181:I241,0,0,1)*'CÁLCULOS PLANO ALIMENTAR'!$B$28 -> 0
C29: Ovo Classe M | D29: =_xlfn.XLOOKUP(C29,alimentos,'COMPOSIÇÃO NUTRICIONAL'!E4:E569,0,0,1) -> 58 | F29: =_xlfn.XLOOKUP(C29,alimentos,'COMPOSIÇÃO NUTRICIONAL'!F4:F569,0,0,1)*B29 -> 0 | G29: =_xlfn.XLOOKUP(C29,alimentos,'COMPOSIÇÃO NUTRICIONAL'!G4:G569,0,0,1)*B29 -> 0 | H29: =_xlfn.XLOOKUP(C29,alimentos,'COMPOSIÇÃO NUTRICIONAL'!H4:H569,0,0,1)*B29 -> 0 | I29: =_xlfn.XLOOKUP(C29,alimentos,'COMPOSIÇÃO NUTRICIONAL'!I4:I569,0,0,1)*B29 -> 0
A31: Almoço | N31: Almoço
A32: Horas | B32: Quantidade | D32: (g/mL) | F32: Kcal | G32: Prot | H32: HC | I32: LP | J32: Observações
C33: Tigela Pequena de Sopa de Vegetais | D33: =_xlfn.XLOOKUP(C33,sopas,'COMPOSIÇÃO NUTRICIONAL'!E519:E528,0,0,1)*'CÁLCULOS PLANO ALIMENTAR'!B33 -> 0 | F33: =_xlfn.XLOOKUP(C33,sopas,'COMPOSIÇÃO NUTRICIONAL'!F519:F528,0,0,1)*'CÁLCULOS PLANO ALIMENTAR'!B33 -> 0 | G33: =_xlfn.XLOOKUP(C33,sopas,'COMPOSIÇÃO NUTRICIONAL'!G519:G528,0,0,1)*'CÁLCULOS PLANO ALIMENTAR'!B33 -> 0 | H33: =_xlfn.XLOOKUP(C33,sopas,'COMPOSIÇÃO NUTRICIONAL'!H519:H528,0,0,1)*'CÁLCULOS PLANO ALIMENTAR'!B33 -> 0 | I33: =_xlfn.XLOOKUP(C33,sopas,'COMPOSIÇÃO NUTRICIONAL'!I519:I528,0,0,1)*'CÁLCULOS PLANO ALIMENTAR'!B33 -> 0 | N33: Kcal | P33: =F33+F34+F35+F36+F37+F38+F39+F40 -> 0
C34: 5,5 colheres de Sopa (110g) de arroz ou massa cozinhados OU 1 batata média (120g) | F34: =VLOOKUP(C34,'COMPOSIÇÃO NUTRICIONAL'!C493:G497,4,0)*B34 -> 0 | G34: =VLOOKUP(C34,'COMPOSIÇÃO NUTRICIONAL'!C493:H497,5,0)*B34 -> 0 | H34: =VLOOKUP(C34,'COMPOSIÇÃO NUTRICIONAL'!C493:H497,6,0)*B34 -> 0 | I34: =VLOOKUP(C34,'COMPOSIÇÃO NUTRICIONAL'!C493:I497,7,0)*B34 -> 0 | N34: PROT | P34: =G33+G34+G35+G36+G37+G38+G39+G40 -> 0
C35: 100gr de carne cozinhada OU 120g de pescado cozinhado OU 4 Ovos | F35: =VLOOKUP(C35,'COMPOSIÇÃO NUTRICIONAL'!C488:F492,4,0)*B35 -> 0 | G35: =VLOOKUP(C35,'COMPOSIÇÃO NUTRICIONAL'!C488:G492,5,0)*B35 -> 0 | H35: =VLOOKUP(C35,'COMPOSIÇÃO NUTRICIONAL'!C488:H492,6,0)*B35 -> 0 | I35: =VLOOKUP(C35,'COMPOSIÇÃO NUTRICIONAL'!C488:I492,7,0)*B35 -> 0 | N35: HC | P35: =H33+H34+H35+H36+H37+H38+H39+H40 -> 0
C36: ='COMPOSIÇÃO NUTRICIONAL'!C498 -> 250gr de Hortícolas Cozinhados OU 200gr de legumes em cru | F36: ='COMPOSIÇÃO NUTRICIONAL'!F498*B36 -> 0 | G36: ='COMPOSIÇÃO NUTRICIONAL'!G498*B36 -> 0 | H36: ='COMPOSIÇÃO NUTRICIONAL'!H498*B36 -> 0 | I36: ='COMPOSIÇÃO NUTRICIONAL'!I498*B36 -> 0 | N36: LIP | P36: =I33+I34+I35+I36+I37+I38+I39+I40 -> 0
C37: ='COMPOSIÇÃO NUTRICIONAL'!C499 -> 88gr de leguminosas cozidas | F37: ='COMPOSIÇÃO NUTRICIONAL'!F499*B37 -> 0 | G37: ='COMPOSIÇÃO NUTRICIONAL'!G499*B37 -> 0 | H37: ='COMPOSIÇÃO NUTRICIONAL'!H499*B37 -> 0 | I37: ='COMPOSIÇÃO NUTRICIONAL'!I499*B37 -> 0
C38: ='COMPOSIÇÃO NUTRICIONAL'!C507 -> Porção Fruta | F38: ='COMPOSIÇÃO NUTRICIONAL'!F507*B38 -> 0 | G38: ='COMPOSIÇÃO NUTRICIONAL'!G507*B38 -> 0 | H38: ='COMPOSIÇÃO NUTRICIONAL'!H507*B38 -> 0 | I38: ='COMPOSIÇÃO NUTRICIONAL'!I507*B38 -> 0
C39: 100 gr de Clara de Ovo | D39: =_xlfn.XLOOKUP(C39,alimentos,'COMPOSIÇÃO NUTRICIONAL'!E4:E569,0,0,1)*'CÁLCULOS PLANO ALIMENTAR'!B39 -> 0 | F39: =_xlfn.XLOOKUP(C39,alimentos,'COMPOSIÇÃO NUTRICIONAL'!F4:F569,0,0,1)*'CÁLCULOS PLANO ALIMENTAR'!B39 -> 0 | G39: =_xlfn.XLOOKUP(C39,alimentos,'COMPOSIÇÃO NUTRICIONAL'!G4:G569,0,0,1)*'CÁLCULOS PLANO ALIMENTAR'!B39 -> 0 | H39: =_xlfn.XLOOKUP(C39,alimentos,'COMPOSIÇÃO NUTRICIONAL'!H4:H569,0,0,1)*'CÁLCULOS PLANO ALIMENTAR'!B39 -> 0 | I39: =_xlfn.XLOOKUP(C39,alimentos,'COMPOSIÇÃO NUTRICIONAL'!I4:I569,0,0,1)*'CÁLCULOS PLANO ALIMENTAR'!B39 -> 0
D40: =_xlfn.XLOOKUP(C40,gordura,'COMPOSIÇÃO NUTRICIONAL'!E33:E39,0,0,1)*B40 -> 0 | F40: =_xlfn.XLOOKUP(C40,gordura,'COMPOSIÇÃO NUTRICIONAL'!F33:F39,0,0,1)*B40 -> 0 | G40: =_xlfn.XLOOKUP(C40,gordura,'COMPOSIÇÃO NUTRICIONAL'!G33:G39,0,0,1)*B40 -> 0 | H40: =_xlfn.XLOOKUP(C40,gordura,'COMPOSIÇÃO NUTRICIONAL'!H33:H39,0,0,1)*B40 -> 0 | I40: =_xlfn.XLOOKUP(C40,gordura,'COMPOSIÇÃO NUTRICIONAL'!I33:I39,0,0,1)*B40 -> 0
B41: Bebida: | C41: Água
A43: Merenda da Tarde | N43: Merenda da Tarde
A44: Horas | B44: Quantidade | D44: (g/mL) | F44: Kcal | G44: Prot | H44: HC | I44: LP | J44: Observações
C45: Pacote de Bolacha Água e Sal | D45: =_xlfn.XLOOKUP($C$45,cereais,'COMPOSIÇÃO NUTRICIONAL'!E50:E180,0,0,1)*'CÁLCULOS PLANO ALIMENTAR'!$B$45 -> 0 | F45: =_xlfn.XLOOKUP($C$45,cereais,'COMPOSIÇÃO NUTRICIONAL'!F50:F180,0,0,1)*'CÁLCULOS PLANO ALIMENTAR'!$B$45 -> 0 | G45: =_xlfn.XLOOKUP($C$45,cereais,'COMPOSIÇÃO NUTRICIONAL'!G50:G180,0,0,1)*'CÁLCULOS PLANO ALIMENTAR'!$B$45 -> 0 | H45: =_xlfn.XLOOKUP($C$45,cereais,'COMPOSIÇÃO NUTRICIONAL'!H50:H180,0,0,1)*'CÁLCULOS PLANO ALIMENTAR'!$B$45 -> 0 | I45: =_xlfn.XLOOKUP($C$45,cereais,'COMPOSIÇÃO NUTRICIONAL'!I50:I180,0,0,1)*'CÁLCULOS PLANO ALIMENTAR'!$B$45 -> 0 | N45: Kcal | P45: =F45+F46+F47+F48+F49+F50+F51 -> 0
C46: Queijo Babybel light | D46: =_xlfn.XLOOKUP($C$46,Queijofiambre,'COMPOSIÇÃO NUTRICIONAL'!E396:E431,0,0,1)*'CÁLCULOS PLANO ALIMENTAR'!$B$46 -> 0 | F46: =_xlfn.XLOOKUP($C$46,Queijofiambre,'COMPOSIÇÃO NUTRICIONAL'!F396:F431,0,0,1)*'CÁLCULOS PLANO ALIMENTAR'!$B$46 -> 0 | G46: =_xlfn.XLOOKUP($C$46,Queijofiambre,'COMPOSIÇÃO NUTRICIONAL'!G396:G431,0,0,1)*'CÁLCULOS PLANO ALIMENTAR'!$B$46 -> 0 | H46: =_xlfn.XLOOKUP($C$46,Queijofiambre,'COMPOSIÇÃO NUTRICIONAL'!H396:H431,0,0,1)*'CÁLCULOS PLANO ALIMENTAR'!$B$46 -> 0 | I46: =_xlfn.XLOOKUP($C$46,Queijofiambre,'COMPOSIÇÃO NUTRICIONAL'!I396:I431,0,0,1)*'CÁLCULOS PLANO ALIMENTAR'!$B$46 -> 0 | N46: PROT | P46: =G45+G46+G47+G48+G49+G50+G51 -> 0
C47: Colher de Sobemesa de Matinal Extra Light | D47: =_xlfn.XLOOKUP($C$47,manteiga,'COMPOSIÇÃO NUTRICIONAL'!E464:E487,0,0,1)*'CÁLCULOS PLANO ALIMENTAR'!$B$47 -> 0 | F47: =_xlfn.XLOOKUP($C$47,manteiga,'COMPOSIÇÃO NUTRICIONAL'!F464:F487,0,0,1)*'CÁLCULOS PLANO ALIMENTAR'!$B$47 -> 0 | G47: =_xlfn.XLOOKUP($C$47,manteiga,'COMPOSIÇÃO NUTRICIONAL'!G464:G487,0,0,1)*'CÁLCULOS PLANO ALIMENTAR'!$B$47 -> 0 | H47: =_xlfn.XLOOKUP($C$47,manteiga,'COMPOSIÇÃO NUTRICIONAL'!H464:H487,0,0,1)*'CÁLCULOS PLANO ALIMENTAR'!$B$47 -> 0 | I47: =_xlfn.XLOOKUP($C$47,manteiga,'COMPOSIÇÃO NUTRICIONAL'!I464:I487,0,0,1)*'CÁLCULOS PLANO ALIMENTAR'!$B$47 -> 0 | N47: HC | P47: =H45+H46+H47+H48+H49+H50+H51 -> 0
C48: Copo Pequeno de Leite Meio-Gordo | D48: =_xlfn.XLOOKUP($C$48,LeiteIogurte,'COMPOSIÇÃO NUTRICIONAL'!E258:E393,0,0,1)*'CÁLCULOS PLANO ALIMENTAR'!$B$48 -> 0 | F48: =_xlfn.XLOOKUP($C$48,LeiteIogurte,'COMPOSIÇÃO NUTRICIONAL'!F258:F393,0,0,1)*'CÁLCULOS PLANO ALIMENTAR'!$B$48 -> 0 | G48: =_xlfn.XLOOKUP($C$48,LeiteIogurte,'COMPOSIÇÃO NUTRICIONAL'!G258:G393,0,0,1)*'CÁLCULOS PLANO ALIMENTAR'!$B$48 -> 0 | H48: =_xlfn.XLOOKUP($C$48,LeiteIogurte,'COMPOSIÇÃO NUTRICIONAL'!H258:H393,0,0,1)*'CÁLCULOS PLANO ALIMENTAR'!$B$48 -> 0 | I48: =_xlfn.XLOOKUP($C$48,LeiteIogurte,'COMPOSIÇÃO NUTRICIONAL'!I258:I393,0,0,1)*'CÁLCULOS PLANO ALIMENTAR'!$B$48 -> 0 | N48: LIP | P48: =I45+I46+I47+I48+I49+I50+I51 -> 0
C49: Colher de Chá de Açúcar Branco | D49: =_xlfn.XLOOKUP($C$49,açucar,'COMPOSIÇÃO NUTRICIONAL'!E4:E32,0,0,1)*'CÁLCULOS PLANO ALIMENTAR'!$B$49 -> 0 | F49: =_xlfn.XLOOKUP($C$49,açucar,'COMPOSIÇÃO NUTRICIONAL'!F4:F32,0,0,1)*'CÁLCULOS PLANO ALIMENTAR'!$B$49 -> 0 | G49: =_xlfn.XLOOKUP($C$49,açucar,'COMPOSIÇÃO NUTRICIONAL'!G4:G32,0,0,1)*'CÁLCULOS PLANO ALIMENTAR'!$B$49 -> 0 | H49: =_xlfn.XLOOKUP($C$49,açucar,'COMPOSIÇÃO NUTRICIONAL'!H4:H32,0,0,1)*'CÁLCULOS PLANO ALIMENTAR'!$B$49 -> 0 | I49: =_xlfn.XLOOKUP($C$49,açucar,'COMPOSIÇÃO NUTRICIONAL'!I4:I32,0,0,1)*'CÁLCULOS PLANO ALIMENTAR'!$B$49 -> 0
C50: Porção (3) Ameixas Brancas Pequenas | D50: =_xlfn.XLOOKUP($C$50,fruta,'COMPOSIÇÃO NUTRICIONAL'!E181:E241,0,0,1)*'CÁLCULOS PLANO ALIMENTAR'!$B$50 -> 0 | F50: =_xlfn.XLOOKUP($C$50,fruta,'COMPOSIÇÃO NUTRICIONAL'!F181:F241,0,0,1)*'CÁLCULOS PLANO ALIMENTAR'!$B$50 -> 0 | G50: =_xlfn.XLOOKUP($C$50,fruta,'COMPOSIÇÃO NUTRICIONAL'!G181:G241,0,0,1)*'CÁLCULOS PLANO ALIMENTAR'!$B$50 -> 0 | H50: =_xlfn.XLOOKUP($C$50,fruta,'COMPOSIÇÃO NUTRICIONAL'!H181:H241,0,0,1)*'CÁLCULOS PLANO ALIMENTAR'!$B$50 -> 0 | I50: =_xlfn.XLOOKUP($C$50,fruta,'COMPOSIÇÃO NUTRICIONAL'!I181:I241,0,0,1)*'CÁLCULOS PLANO ALIMENTAR'!$B$50 -> 0
D51: =_xlfn.XLOOKUP($C$51,alimentos,'COMPOSIÇÃO NUTRICIONAL'!E4:E569,0,0,1)*'CÁLCULOS PLANO ALIMENTAR'!$B$51 -> 0 | F51: =_xlfn.XLOOKUP($C$51,alimentos,'COMPOSIÇÃO NUTRICIONAL'!F4:F569,0,0,1)*'CÁLCULOS PLANO ALIMENTAR'!$B$51 -> 0 | G51: =_xlfn.XLOOKUP($C$51,alimentos,'COMPOSIÇÃO NUTRICIONAL'!G4:G569,0,0,1)*'CÁLCULOS PLANO ALIMENTAR'!$B$51 -> 0 | H51: =_xlfn.XLOOKUP($C$51,alimentos,'COMPOSIÇÃO NUTRICIONAL'!H4:H569,0,0,1)*'CÁLCULOS PLANO ALIMENTAR'!$B$51 -> 0 | I51: =_xlfn.XLOOKUP($C$51,alimentos,'COMPOSIÇÃO NUTRICIONAL'!I4:I569,0,0,1)*'CÁLCULOS PLANO ALIMENTAR'!$B$51 -> 0
A53: 2ª Merenda da Tarde | N53: 2ª Merenda da Tarde
A54: Horas | B54: Quantidade | D54: (g/mL) | F54: Kcal | G54: Prot | H54: HC | I54: LP | J54: Observações
C55: Gelatina Royal 10 kcal | D55: =_xlfn.XLOOKUP($C$55,gelatina,'COMPOSIÇÃO NUTRICIONAL'!E435:E439,0,0,1)*'CÁLCULOS PLANO ALIMENTAR'!$B$55 -> 0 | F55: =_xlfn.XLOOKUP($C$55,gelatina,'COMPOSIÇÃO NUTRICIONAL'!F435:F439,0,0,1)*'CÁLCULOS PLANO ALIMENTAR'!$B$55 -> 0 | G55: =_xlfn.XLOOKUP($C$55,gelatina,'COMPOSIÇÃO NUTRICIONAL'!G435:G439,0,0,1)*'CÁLCULOS PLANO ALIMENTAR'!$B$55 -> 0 | H55: =_xlfn.XLOOKUP($C$55,gelatina,'COMPOSIÇÃO NUTRICIONAL'!H435:H439,0,0,1)*'CÁLCULOS PLANO ALIMENTAR'!$B$55 -> 0 | I55: =_xlfn.XLOOKUP($C$55,gelatina,'COMPOSIÇÃO NUTRICIONAL'!I435:I439,0,0,1)*'CÁLCULOS PLANO ALIMENTAR'!$B$55 -> 0 | N55: Kcal | P55: =F55+F56+F57+F58+F59+F60+F61+F62 -> 0
C56: Barra Cereais Nacional +Linha Frutos Vermelhos | D56: =_xlfn.XLOOKUP($C$56,barras,'COMPOSIÇÃO NUTRICIONAL'!E451:E463,0,0,1)*'CÁLCULOS PLANO ALIMENTAR'!$B$56 -> 0 | F56: =_xlfn.XLOOKUP($C$56,barras,'COMPOSIÇÃO NUTRICIONAL'!F451:F463,0,0,1)*'CÁLCULOS PLANO ALIMENTAR'!$B$56 -> 0 | G56: =_xlfn.XLOOKUP($C$56,barras,'COMPOSIÇÃO NUTRICIONAL'!G451:G463,0,0,1)*'CÁLCULOS PLANO ALIMENTAR'!$B$56 -> 0 | H56: =_xlfn.XLOOKUP($C$56,barras,'COMPOSIÇÃO NUTRICIONAL'!H451:H463,0,0,1)*'CÁLCULOS PLANO ALIMENTAR'!$B$56 -> 0 | I56: =_xlfn.XLOOKUP($C$56,barras,'COMPOSIÇÃO NUTRICIONAL'!I451:I463,0,0,1)*'CÁLCULOS PLANO ALIMENTAR'!$B$56 -> 0 | N56: PROT | P56: =G55+G56+G57+G58+G59+G60+G61+G62 -> 0
C57: Ameixa Branca | D57: =_xlfn.XLOOKUP($C$57,fruta,'COMPOSIÇÃO NUTRICIONAL'!E181:E241,0,0,1)*'CÁLCULOS PLANO ALIMENTAR'!$B$57 -> 0 | F57: =_xlfn.XLOOKUP($C$57,fruta,'COMPOSIÇÃO NUTRICIONAL'!F181:F241,0,0,1)*'CÁLCULOS PLANO ALIMENTAR'!$B$57 -> 0 | G57: =_xlfn.XLOOKUP($C$57,fruta,'COMPOSIÇÃO NUTRICIONAL'!G181:G241,0,0,1)*'CÁLCULOS PLANO ALIMENTAR'!$B$57 -> 0 | H57: =_xlfn.XLOOKUP($C$57,fruta,'COMPOSIÇÃO NUTRICIONAL'!H181:H241,0,0,1)*'CÁLCULOS PLANO ALIMENTAR'!$B$57 -> 0 | I57: =_xlfn.XLOOKUP($C$57,fruta,'COMPOSIÇÃO NUTRICIONAL'!I181:I241,0,0,1)*'CÁLCULOS PLANO ALIMENTAR'!$B$57 -> 0 | N57: HC | P57: =H55+H56+H57+H58+H59+H60+H61+H62 -> 0
C58: Vaca que ri light + palitos light | D58: =_xlfn.XLOOKUP($C$58,Queijofiambre,'COMPOSIÇÃO NUTRICIONAL'!E396:E431,0,0,1)*'CÁLCULOS PLANO ALIMENTAR'!$B$58 -> 0 | F58: =_xlfn.XLOOKUP($C$58,Queijofiambre,'COMPOSIÇÃO NUTRICIONAL'!F396:F431,0,0,1)*'CÁLCULOS PLANO ALIMENTAR'!$B$58 -> 0 | G58: =_xlfn.XLOOKUP($C$58,Queijofiambre,'COMPOSIÇÃO NUTRICIONAL'!G396:G431,0,0,1)*'CÁLCULOS PLANO ALIMENTAR'!$B$58 -> 0 | H58: =_xlfn.XLOOKUP($C$58,Queijofiambre,'COMPOSIÇÃO NUTRICIONAL'!H396:H431,0,0,1)*'CÁLCULOS PLANO ALIMENTAR'!$B$58 -> 0 | I58: =_xlfn.XLOOKUP($C$58,Queijofiambre,'COMPOSIÇÃO NUTRICIONAL'!I396:I431,0,0,1)*'CÁLCULOS PLANO ALIMENTAR'!$B$58 -> 0 | N58: LIP | P58: =I55+I56+I57+I58+I59+I60+I61+I62 -> 0
C59: Caneca de Leite Meio-Gordo Sem Lactose | D59: =_xlfn.XLOOKUP($C$59,LeiteIogurte,'COMPOSIÇÃO NUTRICIONAL'!E258:E393,0,0,1)*'CÁLCULOS PLANO ALIMENTAR'!$B$59 -> 0 | F59: =_xlfn.XLOOKUP($C$59,LeiteIogurte,'COMPOSIÇÃO NUTRICIONAL'!F258:F393,0,0,1)*'CÁLCULOS PLANO ALIMENTAR'!$B$59 -> 0 | G59: =_xlfn.XLOOKUP($C$59,LeiteIogurte,'COMPOSIÇÃO NUTRICIONAL'!G258:G393,0,0,1)*'CÁLCULOS PLANO ALIMENTAR'!$B$59 -> 0 | H59: =_xlfn.XLOOKUP($C$59,LeiteIogurte,'COMPOSIÇÃO NUTRICIONAL'!H258:H393,0,0,1)*'CÁLCULOS PLANO ALIMENTAR'!$B$59 -> 0 | I59: =_xlfn.XLOOKUP($C$59,LeiteIogurte,'COMPOSIÇÃO NUTRICIONAL'!I258:I393,0,0,1)*'CÁLCULOS PLANO ALIMENTAR'!$B$59 -> 0
C60: Pacote individual de Bolacha Maria | D60: =_xlfn.XLOOKUP($C$60,cereais,'COMPOSIÇÃO NUTRICIONAL'!E50:E180,0,0,1)*'CÁLCULOS PLANO ALIMENTAR'!$B$60 -> 0 | F60: =_xlfn.XLOOKUP($C$60,cereais,'COMPOSIÇÃO NUTRICIONAL'!F50:F180,0,0,1)*'CÁLCULOS PLANO ALIMENTAR'!$B$60 -> 0 | G60: =_xlfn.XLOOKUP($C$60,cereais,'COMPOSIÇÃO NUTRICIONAL'!G50:G180,0,0,1)*'CÁLCULOS PLANO ALIMENTAR'!$B$60 -> 0 | H60: =_xlfn.XLOOKUP($C$60,cereais,'COMPOSIÇÃO NUTRICIONAL'!H50:H180,0,0,1)*'CÁLCULOS PLANO ALIMENTAR'!$B$60 -> 0 | I60: =_xlfn.XLOOKUP($C$60,cereais,'COMPOSIÇÃO NUTRICIONAL'!I50:I180,0,0,1)*'CÁLCULOS PLANO ALIMENTAR'!$B$60 -> 0
C61: Colher de Sopa de Coco | D61: =_xlfn.XLOOKUP($C$61,frutossecos,'COMPOSIÇÃO NUTRICIONAL'!E242:E255,0,0,1)*'CÁLCULOS PLANO ALIMENTAR'!$B$61 -> 0 | F61: =_xlfn.XLOOKUP($C$61,frutossecos,'COMPOSIÇÃO NUTRICIONAL'!F242:F255,0,0,1)*'CÁLCULOS PLANO ALIMENTAR'!$B$61 -> 0 | G61: =_xlfn.XLOOKUP($C$61,frutossecos,'COMPOSIÇÃO NUTRICIONAL'!G242:G255,0,0,1)*'CÁLCULOS PLANO ALIMENTAR'!$B$61 -> 0 | H61: =_xlfn.XLOOKUP($C$61,frutossecos,'COMPOSIÇÃO NUTRICIONAL'!H242:H255,0,0,1)*'CÁLCULOS PLANO ALIMENTAR'!$B$61 -> 0 | I61: =_xlfn.XLOOKUP($C$61,frutossecos,'COMPOSIÇÃO NUTRICIONAL'!I242:I255,0,0,1)*'CÁLCULOS PLANO ALIMENTAR'!$B$61 -> 0
C62: Pacote de Açúcar Branco | D62: =_xlfn.XLOOKUP($C$62,alimentos,'COMPOSIÇÃO NUTRICIONAL'!E4:E569,0,0,1)*'CÁLCULOS PLANO ALIMENTAR'!$B$62 -> 0 | F62: =_xlfn.XLOOKUP($C$62,alimentos,'COMPOSIÇÃO NUTRICIONAL'!F4:F569,0,0,1)*'CÁLCULOS PLANO ALIMENTAR'!$B$62 -> 0 | G62: =_xlfn.XLOOKUP($C$62,alimentos,'COMPOSIÇÃO NUTRICIONAL'!G4:G569,0,0,1)*'CÁLCULOS PLANO ALIMENTAR'!$B$62 -> 0 | H62: =_xlfn.XLOOKUP($C$62,alimentos,'COMPOSIÇÃO NUTRICIONAL'!H4:H569,0,0,1)*'CÁLCULOS PLANO ALIMENTAR'!$B$62 -> 0 | I62: =_xlfn.XLOOKUP($C$62,alimentos,'COMPOSIÇÃO NUTRICIONAL'!I4:I569,0,0,1)*'CÁLCULOS PLANO ALIMENTAR'!$B$62 -> 0
A64: Jantar | N64: Jantar
A65: Horas | B65: Quantidade | D65: (g/mL) | F65: Kcal | G65: Prot | H65: HC | I65: LP | J65: Observações
C66: Tigela Grande de Canja de Galinha | D66: =_xlfn.XLOOKUP(C66,sopas,'COMPOSIÇÃO NUTRICIONAL'!E519:E528,0,0,1)*'CÁLCULOS PLANO ALIMENTAR'!B66 -> 0 | F66: =_xlfn.XLOOKUP(C66,sopas,'COMPOSIÇÃO NUTRICIONAL'!F519:F528,0,0,1)*'CÁLCULOS PLANO ALIMENTAR'!B66 -> 0 | G66: =_xlfn.XLOOKUP(C66,sopas,'COMPOSIÇÃO NUTRICIONAL'!G519:G528,0,0,1)*'CÁLCULOS PLANO ALIMENTAR'!B66 -> 0 | H66: =_xlfn.XLOOKUP(C66,sopas,'COMPOSIÇÃO NUTRICIONAL'!H519:H528,0,0,1)*'CÁLCULOS PLANO ALIMENTAR'!B66 -> 0 | I66: =_xlfn.XLOOKUP(C66,sopas,'COMPOSIÇÃO NUTRICIONAL'!I519:I528,0,0,1)*'CÁLCULOS PLANO ALIMENTAR'!B66 -> 0 | N66: Kcal | P66: =F66+F67+F69+F71+F74+F68+F70+F72+F73 -> 0
C67: 8 colheres de sopa (165g) de arroz ou massa cozinhados OU 4 batatas pequenas (180g) | F67: =VLOOKUP(C67,'COMPOSIÇÃO NUTRICIONAL'!C493:F497,4,0)*B67 -> 0 | G67: =VLOOKUP(C67,'COMPOSIÇÃO NUTRICIONAL'!C493:G497,5,0)*B67 -> 0 | H67: =VLOOKUP(C67,'COMPOSIÇÃO NUTRICIONAL'!C493:H497,6,0)*B67 -> 0 | I67: =VLOOKUP(C67,'COMPOSIÇÃO NUTRICIONAL'!C493:I497,7,0)*B67 -> 0 | N67: PROT | P67: =G66+G67+G68+G69+G71+G74+G73+G70+G72 -> 0
C68: 50gr de carne cozinhada OU 60g de pescado cozinhado OU 2 Ovos | F68: =VLOOKUP('CÁLCULOS PLANO ALIMENTAR'!C68,'COMPOSIÇÃO NUTRICIONAL'!C488:F492,4,0)*B68 -> 0 | G68: =VLOOKUP(C68,'COMPOSIÇÃO NUTRICIONAL'!C488:G492,5,0)*B68 -> 0 | H68: =VLOOKUP(C68,'COMPOSIÇÃO NUTRICIONAL'!C488:H492,6,0)*B68 -> 0 | I68: =VLOOKUP(C68,'COMPOSIÇÃO NUTRICIONAL'!C488:I492,7,0)*B68 -> 0 | N68: HC | P68: =H66+H67+H68+H69+H71+H74+H70+H72+H73 -> 0
C69: ='COMPOSIÇÃO NUTRICIONAL'!C498 -> 250gr de Hortícolas Cozinhados OU 200gr de legumes em cru | F69: ='COMPOSIÇÃO NUTRICIONAL'!F498*B69 -> 0 | G69: ='COMPOSIÇÃO NUTRICIONAL'!G498*B69 -> 0 | H69: ='COMPOSIÇÃO NUTRICIONAL'!H498*B69 -> 0 | I69: ='COMPOSIÇÃO NUTRICIONAL'!I498*B69 -> 0 | N69: LIP | P69: =I66+I67+I68+I69+I71+I74+I70+I72+I73 -> 0
C70: Colher de Sobremesa de Azeite | D70: =_xlfn.XLOOKUP(C70,gordura,'COMPOSIÇÃO NUTRICIONAL'!E33:E39,0,0,1)*'CÁLCULOS PLANO ALIMENTAR'!B70 -> 0 | F70: =_xlfn.XLOOKUP(C70,gordura,'COMPOSIÇÃO NUTRICIONAL'!F33:F39,0,0,1)*'CÁLCULOS PLANO ALIMENTAR'!B70 -> 0 | G70: =_xlfn.XLOOKUP(C70,gordura,'COMPOSIÇÃO NUTRICIONAL'!G33:G39,0,0,1)*'CÁLCULOS PLANO ALIMENTAR'!B70 -> 0 | H70: =_xlfn.XLOOKUP(C70,gordura,'COMPOSIÇÃO NUTRICIONAL'!H33:H39,0,0,1)*'CÁLCULOS PLANO ALIMENTAR'!B70 -> 0 | I70: =_xlfn.XLOOKUP(C70,gordura,'COMPOSIÇÃO NUTRICIONAL'!I33:I39,0,0,1)*'CÁLCULOS PLANO ALIMENTAR'!B70 -> 0
C71: ='COMPOSIÇÃO NUTRICIONAL'!C499 -> 88gr de leguminosas cozidas | F71: ='COMPOSIÇÃO NUTRICIONAL'!F499*B71 -> 0 | G71: ='COMPOSIÇÃO NUTRICIONAL'!G499*B71 -> 0 | H71: ='COMPOSIÇÃO NUTRICIONAL'!H499*B71 -> 0 | I71: ='COMPOSIÇÃO NUTRICIONAL'!I499*B71 -> 0
C72: Colher de Sobremesa de Açúcar Branco | D72: =_xlfn.XLOOKUP(C72,alimentos,'COMPOSIÇÃO NUTRICIONAL'!E4:E569,0,0,1)*'CÁLCULOS PLANO ALIMENTAR'!B72 -> 0 | F72: =_xlfn.XLOOKUP(C72,alimentos,'COMPOSIÇÃO NUTRICIONAL'!F4:F569,0,0,1)*'CÁLCULOS PLANO ALIMENTAR'!B72 -> 0 | G72: =_xlfn.XLOOKUP(C72,alimentos,'COMPOSIÇÃO NUTRICIONAL'!G4:G569,0,0,1)*B72 -> 0 | H72: =_xlfn.XLOOKUP(C72,alimentos,'COMPOSIÇÃO NUTRICIONAL'!H4:H569,0,0,1)*B72 -> 0 | I72: =_xlfn.XLOOKUP(C72,alimentos,'COMPOSIÇÃO NUTRICIONAL'!I4:I569,0,0,1)*B72 -> 0
D73: =_xlfn.XLOOKUP($C$73,alimentos,'COMPOSIÇÃO NUTRICIONAL'!E4:E569,0,0,1)*'CÁLCULOS PLANO ALIMENTAR'!$B$73 -> 0 | F73: =_xlfn.XLOOKUP($C$73,alimentos,'COMPOSIÇÃO NUTRICIONAL'!F4:F569,0,0,1)*'CÁLCULOS PLANO ALIMENTAR'!$B$73 -> 0 | G73: =_xlfn.XLOOKUP($C$73,alimentos,'COMPOSIÇÃO NUTRICIONAL'!G4:G569,0,0,1)*'CÁLCULOS PLANO ALIMENTAR'!$B$73 -> 0 | H73: =_xlfn.XLOOKUP($C$73,alimentos,'COMPOSIÇÃO NUTRICIONAL'!H4:H569,0,0,1)*'CÁLCULOS PLANO ALIMENTAR'!$B$73 -> 0 | I73: =_xlfn.XLOOKUP($C$73,alimentos,'COMPOSIÇÃO NUTRICIONAL'!I4:I569,0,0,1)*'CÁLCULOS PLANO ALIMENTAR'!$B$73 -> 0
C74: ='COMPOSIÇÃO NUTRICIONAL'!C507 -> Porção Fruta | F74: ='COMPOSIÇÃO NUTRICIONAL'!F507*B74 -> 0 | G74: ='COMPOSIÇÃO NUTRICIONAL'!G507*B74 -> 0 | H74: ='COMPOSIÇÃO NUTRICIONAL'!H507*B74 -> 0 | I74: ='COMPOSIÇÃO NUTRICIONAL'!I507*B74 -> 0
B75: Bebida: | C75: Água
A77: Ceia | N77: Ceia
A78: Horas | B78: Quantidade | D78: (g/mL) | F78: Kcal | G78: Prot | H78: HC | I78: LP | J78: Observações
C79: Bolacha Maria | D79: =_xlfn.XLOOKUP($C$79,cereais,'COMPOSIÇÃO NUTRICIONAL'!E50:E180,0,0,1)*'CÁLCULOS PLANO ALIMENTAR'!$B$79 -> 0 | F79: =_xlfn.XLOOKUP($C$79,cereais,'COMPOSIÇÃO NUTRICIONAL'!F50:F180,0,0,1)*'CÁLCULOS PLANO ALIMENTAR'!$B$79 -> 0 | G79: =_xlfn.XLOOKUP($C$79,cereais,'COMPOSIÇÃO NUTRICIONAL'!G50:G180,0,0,1)*'CÁLCULOS PLANO ALIMENTAR'!$B$79 -> 0 | H79: =_xlfn.XLOOKUP($C$79,cereais,'COMPOSIÇÃO NUTRICIONAL'!H50:H180,0,0,1)*'CÁLCULOS PLANO ALIMENTAR'!$B$79 -> 0 | I79: =_xlfn.XLOOKUP($C$79,cereais,'COMPOSIÇÃO NUTRICIONAL'!I50:I180,0,0,1)*'CÁLCULOS PLANO ALIMENTAR'!$B$79 -> 0 | N79: Kcal | P79: =F79+F80+F81+F82 -> 0
C80: Copo Pequeno de Leite Magro | D80: =_xlfn.XLOOKUP($C$80,LeiteIogurte,'COMPOSIÇÃO NUTRICIONAL'!E258:E393,0,0,1)*'CÁLCULOS PLANO ALIMENTAR'!$B$80 -> 0 | F80: =_xlfn.XLOOKUP($C$80,LeiteIogurte,'COMPOSIÇÃO NUTRICIONAL'!F258:F393,0,0,1)*'CÁLCULOS PLANO ALIMENTAR'!$B$80 -> 0 | G80: =_xlfn.XLOOKUP($C$80,LeiteIogurte,'COMPOSIÇÃO NUTRICIONAL'!G258:G393,0,0,1)*'CÁLCULOS PLANO ALIMENTAR'!$B$80 -> 0 | H80: =_xlfn.XLOOKUP($C$80,LeiteIogurte,'COMPOSIÇÃO NUTRICIONAL'!H258:H393,0,0,1)*'CÁLCULOS PLANO ALIMENTAR'!$B$80 -> 0 | I80: =_xlfn.XLOOKUP($C$80,LeiteIogurte,'COMPOSIÇÃO NUTRICIONAL'!I258:I393,0,0,1)*'CÁLCULOS PLANO ALIMENTAR'!$B$80 -> 0 | N80: PROT | P80: =G79+G80+G81+G82 -> 0
C81: Colher de Sobremesa de Açúcar Branco | D81: =_xlfn.XLOOKUP($C$81,açucar,'COMPOSIÇÃO NUTRICIONAL'!E4:E32,0,0,1)*'CÁLCULOS PLANO ALIMENTAR'!$B$81 -> 0 | F81: =_xlfn.XLOOKUP($C$81,açucar,'COMPOSIÇÃO NUTRICIONAL'!F4:F32,0,0,1)*'CÁLCULOS PLANO ALIMENTAR'!$B$81 -> 0 | G81: =_xlfn.XLOOKUP($C$81,açucar,'COMPOSIÇÃO NUTRICIONAL'!G4:G32,0,0,1)*'CÁLCULOS PLANO ALIMENTAR'!$B$81 -> 0 | H81: =_xlfn.XLOOKUP($C$81,açucar,'COMPOSIÇÃO NUTRICIONAL'!H4:H32,0,0,1)*'CÁLCULOS PLANO ALIMENTAR'!$B$81 -> 0 | I81: =_xlfn.XLOOKUP($C$81,açucar,'COMPOSIÇÃO NUTRICIONAL'!I4:I32,0,0,1)*'CÁLCULOS PLANO ALIMENTAR'!$B$81 -> 0 | N81: HC | P81: =H79+H80+H81+H82 -> 0
D82: =_xlfn.XLOOKUP($C$82,alimentos,'COMPOSIÇÃO NUTRICIONAL'!E4:E569,0,0,1)*'CÁLCULOS PLANO ALIMENTAR'!$B$82 -> 0 | F82: =_xlfn.XLOOKUP($C$82,alimentos,'COMPOSIÇÃO NUTRICIONAL'!F4:F569,0,0,1)*'CÁLCULOS PLANO ALIMENTAR'!$B$82 -> 0 | G82: =_xlfn.XLOOKUP($C$82,alimentos,'COMPOSIÇÃO NUTRICIONAL'!G4:G569,0,0,1)*'CÁLCULOS PLANO ALIMENTAR'!$B$82 -> 0 | H82: =_xlfn.XLOOKUP($C$82,alimentos,'COMPOSIÇÃO NUTRICIONAL'!H4:H569,0,0,1)*'CÁLCULOS PLANO ALIMENTAR'!$B$82 -> 0 | I82: =_xlfn.XLOOKUP($C$82,alimentos,'COMPOSIÇÃO NUTRICIONAL'!I4:I569,0,0,1)*'CÁLCULOS PLANO ALIMENTAR'!$B$82 -> 0 | N82: LIP | P82: =I79+I80+I81+I82 -> 0

Sheet PLANO ALIMENTAR
C1: PLANO ALIMENTAR
D3: Eduarda Carvalho
D4: 44854
J7: LISTA DE COMPRAS
A8: PEQUENO-ALMOÇO
A9: Opção 1
A12: Opção 2
A16: MERENDA DA MANHÃ
A17: Opção 1
A20: Opção 2
A24: ALMOÇO e JANTAR
B27: 1/2 prato com hortícolas cozinhados ou frios
A33: Bebida | B33: Água
A34: Sobremesa | B34: 1 porção de fruta
A36: MERENDA DA TARDE
A37: Opção 1
A40: Opção 2
A43: 2ª MERENDA DA TARDE
A47: CEIA
A52: RECOMENDAÇÕES
C74: EDUARDA CARVALHO | Nutricionista
D75: Contacto Telefónico: 910175422
D76: ´@nutri_eduarda | G76: CP: 5084N

Sheet MATERIAIS
L5: 1 PORÇÃO DE FRUTA
L6: A que corresponde?
K8: 140g | M8: Ameixa (3 pequenas) • Ananás (2 fatias sem casca) • Cereja (2 mãos cheias) • Damasco (2 unidades) • framboesas (3 mãos cheias) • Kiwi (2 unidades) • Laranja (1 unidade média) • Maçã (1 unidade média) • Manga, •Nêspera (2 unidades) • Papaia • Pêssego •Romã • Tangerina (2 unidades). 1 banana (120g)
K15: 260g | M15: Morango (8-10 unidades pequenas) • Melancia (1 fatia) • Melão (2 fatias finas) • Mirtilos, Amora.
K19: 350g | M19: Meloa (2 fatias)
M22: Quantas Kcal corresponde 1 porção de fruta
K25: melancia - 38kcal ameixa - 48kcal pêssego - 48kcal dióspiro - 52kcal pêra - 54kcal | M25: meloa - 60kcal mirtilos - 63 kcal figo - 63kcal uvas - 66kcal laranja - 67kcal | O25: ananás- 67kcal damasco- 67kcal framboesas - 69kcal banana - 76kcal melão - 78kcal manga - 82kcal | Q25: kiwi - 84kcal maçã - 87kcal morango - 88kcal cerejas - 94kcal amoras- 111kcal
L36: 1 PORÇÃO DE FRUTOS SECOS - 30g
L37: A que corresponde?
K39: 15 AMÊNDOAS - 20 AVELÃS - 18 CAJUS - 38 PISTÁCIOS - 6 CASTANHAS DO BRASIL - 33 AMENDOINS - 12 NOZES
K54: QUANTIFICAÇÃO ALIMENTAR
K58: HIDRATOS DE CARBONO
J61: 55g
J67: 75g
J73: 110g. Arroz 143
B76: VEGETARIANOS
A77: Equivalente para 125g carne e 150g pescado ---: 250g de tofu OU 125g de seitan OU 100g de soja OU (200g de leguminosas + 55g de arroz integral/massa de leguminosas +1 ovo, e apenas meia porção de fruta de sobremesa)
J79: 165g. Arroz 227
B85: EQUIVALÊNCIAS REFEIÇÕES PRINCIPAIS
A86: 5,5 colheres de Sopa (110g) de arroz ou massa cozinhados (40g em cru) OU 1 batata média (120g) ;3 colheres de sopa (55g) de arroz ou massa cozinhados (20g em cru) OU 1 batata pequena (60g);8 colheres de sopa (165g) de arroz ou massa cozinhados (66g em cru) OU 4 batatas pequenas (180g); 11 colheres de Sopa (220g) de arroz ou massa cozinhados (88g em cru) OU 2 batatas médias (240g) ;16,5 colheres de Sopa (330g) de arroz ou massa cozinhados (129g em cru) OU 3 batatas médias (360g)
K91: PROTEÍNA
A93: 75gr de carne cozinhada (90g em cru) OU 90g de pescado cozinhado (105g em cru) OU 3 Ovos; 100gr de carne cozinhada (120g cru) OU 120g (145g) de pescado cozinhado OU 4 Ovos; 125gr de carne cozinhada (150g em cru) OU 150g de pescado cozinhado (180g em cru) OU 5 Ovos | J93: 75g
A102: PHISIOCLINIC | J102: 100g
A103: Contacto Telefónico: 916294195
A104: ´@_phisioclinic_ | C104: nutricao@phisioclinic.pt
A108: NUTRIÇÃO AURANUA | J108: 189g/240
A109: Contacto Telefónico: 928133743
A110: ´@auranua.com_ | C110: info.auranua@gmail.com
A111: ´@nutri_eduarda
A112: www.auranua.com
J127: 150g

Sheet RECEITAS
E2: 353.591 | F2: 28.5568 | G2: 31.0666 | H2: 12.535
C3: Alimento | D3: Quantidade | E3: Kcal | F3: pt | G3: HC | H3: lp | K3: PAPAS DE AVEIA NO FORNO | W3: PÃO NA AIRFRYER
C4: Ovo Classe M | D4: =_xlfn.XLOOKUP(C4,alimentos,'COMPOSIÇÃO NUTRICIONAL'!E4:E569,0,0,1)*B4 -> 0 | E4: =_xlfn.XLOOKUP(C4,alimentos,'COMPOSIÇÃO NUTRICIONAL'!F4:F569,0,0,1)*B4 -> 0 | F4: =_xlfn.XLOOKUP(C4,alimentos,'COMPOSIÇÃO NUTRICIONAL'!G4:G569,0,0,1)*B4 -> 0 | G4: =_xlfn.XLOOKUP(C4,alimentos,'COMPOSIÇÃO NUTRICIONAL'!H4:H569,0,0,1)*B4 -> 0 | H4: =_xlfn.XLOOKUP(C4,alimentos,'COMPOSIÇÃO NUTRICIONAL'!I4:I569,0,0,1)*B4 -> 0 | K4: Ingredientes: 1 ovo classe M; 1 banana madura; 15g de farinha de aveia; 50g de flocos de aveia; 100 ml (1/2 copo) de leite magro; 1 colher de chá de fermento; canela a gosto Preparação: Misturar todos os ingredientes (com exceção da banana). Colocar num tabuleiro forrado com papel vegetal. Adicionar a banana às rodelas, envolvendo na mistura anterior. Polvilhar com canela e levar ao forno (180ºC) cerca de 25-30 minutos. | W4: 70g de farinha de aveia; 1 colher café de fermento; 150g iogurte skyr natural sólido. Preparação: juntar tudo e temperar com um pouco de sal. Aamassar bem até formar uma bola. Passar farinha em ambos os lados e moldar a gosto. Levar à airfryer a 180º por 15 minutos. Abrir o pão ao meio e deixar mais 5 minutos a cozinhar.
C5: Tortita de Arroz | D5: =_xlfn.XLOOKUP(C5,alimentos,'COMPOSIÇÃO NUTRICIONAL'!E4:E569,0,0,1)*B5 -> 0 | E5: =_xlfn.XLOOKUP(C5,alimentos,'COMPOSIÇÃO NUTRICIONAL'!F4:F569,0,0,1)*B5 -> 0 | F5: =_xlfn.XLOOKUP(C5,alimentos,'COMPOSIÇÃO NUTRICIONAL'!G4:G569,0,0,1)*B5 -> 0 | G5: =_xlfn.XLOOKUP(C5,alimentos,'COMPOSIÇÃO NUTRICIONAL'!H4:H569,0,0,1)*B5 -> 0 | H5: =_xlfn.XLOOKUP(C5,alimentos,'COMPOSIÇÃO NUTRICIONAL'!I4:I569,0,0,1)*B5 -> 0
C6: Porção Fruta | D6: =_xlfn.XLOOKUP(C6,alimentos,'COMPOSIÇÃO NUTRICIONAL'!E4:E569,0,0,1)*B6 -> 0 | E6: =_xlfn.XLOOKUP(C6,alimentos,'COMPOSIÇÃO NUTRICIONAL'!F4:F569,0,0,1)*B6 -> 0 | F6: =_xlfn.XLOOKUP(C6,alimentos,'COMPOSIÇÃO NUTRICIONAL'!G4:G569,0,0,1)*B6 -> 0 | G6: =_xlfn.XLOOKUP(C6,alimentos,'COMPOSIÇÃO NUTRICIONAL'!H4:H569,0,0,1)*B6 -> 0 | H6: =_xlfn.XLOOKUP(C6,alimentos,'COMPOSIÇÃO NUTRICIONAL'!I4:I569,0,0,1)*B6 -> 0
C7: Iogurte soja natural continente equilíbrio | D7: =_xlfn.XLOOKUP(C7,alimentos,'COMPOSIÇÃO NUTRICIONAL'!E4:E569,0,0,1)*B7 -> 0 | E7: =_xlfn.XLOOKUP(C7,alimentos,'COMPOSIÇÃO NUTRICIONAL'!F4:F569,0,0,1)*B7 -> 0 | F7: =_xlfn.XLOOKUP(C7,alimentos,'COMPOSIÇÃO NUTRICIONAL'!G4:G569,0,0,1)*B7 -> 0 | G7: =_xlfn.XLOOKUP(C7,alimentos,'COMPOSIÇÃO NUTRICIONAL'!H4:H569,0,0,1)*B7 -> 0 | H7: =_xlfn.XLOOKUP(C7,alimentos,'COMPOSIÇÃO NUTRICIONAL'!I4:I569,0,0,1)*B7 -> 0
C8: Porção Fruta | D8: =_xlfn.XLOOKUP(C8,alimentos,'COMPOSIÇÃO NUTRICIONAL'!E4:E569,0,0,1)*B8 -> 0 | E8: =_xlfn.XLOOKUP(C8,alimentos,'COMPOSIÇÃO NUTRICIONAL'!F4:F569,0,0,1)*B8 -> 0 | F8: =_xlfn.XLOOKUP(C8,alimentos,'COMPOSIÇÃO NUTRICIONAL'!G4:G569,0,0,1)*B8 -> 0 | G8: =_xlfn.XLOOKUP(C8,alimentos,'COMPOSIÇÃO NUTRICIONAL'!H4:H569,0,0,1)*B8 -> 0 | H8: =_xlfn.XLOOKUP(C8,alimentos,'COMPOSIÇÃO NUTRICIONAL'!I4:I569,0,0,1)*B8 -> 0
C9: Colher de Sopa de Azeite | D9: =_xlfn.XLOOKUP(C9,alimentos,'COMPOSIÇÃO NUTRICIONAL'!E4:E569,0,0,1)*B9 -> 0 | E9: =_xlfn.XLOOKUP(C9,alimentos,'COMPOSIÇÃO NUTRICIONAL'!F4:F569,0,0,1)*B9 -> 0 | F9: =_xlfn.XLOOKUP(C9,alimentos,'COMPOSIÇÃO NUTRICIONAL'!G4:G569,0,0,1)*B9 -> 0 | G9: =_xlfn.XLOOKUP(C9,alimentos,'COMPOSIÇÃO NUTRICIONAL'!H4:H569,0,0,1)*B9 -> 0 | H9: =_xlfn.XLOOKUP(C9,alimentos,'COMPOSIÇÃO NUTRICIONAL'!I4:I569,0,0,1)*B9 -> 0
C10: Iogurte Origem Vegetal Alpro Natural, 0%Açúcar | D10: =_xlfn.XLOOKUP(C10,alimentos,'COMPOSIÇÃO NUTRICIONAL'!E4:E569,0,0,1)*B10 -> 0 | E10: =_xlfn.XLOOKUP(C10,alimentos,'COMPOSIÇÃO NUTRICIONAL'!F4:F569,0,0,1)*B10 -> 0 | F10: =_xlfn.XLOOKUP(C10,alimentos,'COMPOSIÇÃO NUTRICIONAL'!G4:G569,0,0,1)*B10 -> 0 | G10: =_xlfn.XLOOKUP(C10,alimentos,'COMPOSIÇÃO NUTRICIONAL'!H4:H569,0,0,1)*B10 -> 0 | H10: =_xlfn.XLOOKUP(C10,alimentos,'COMPOSIÇÃO NUTRICIONAL'!I4:I569,0,0,1)*B10 -> 0
C11: Receita | D11: Bolachas de Banana | E11: =E4+E5+E6+E8+E7+E9+E10+E13+E14 -> 299.17 | F11: =F4+F5+F6+F7+F8+F9+F10+F13+F14 -> 24.595625 | G11: =G4+G5+G6+G7+G8+G9+G10+G13+G14 -> 29.0285 | H11: =H4+H5+H6+H7+H8+H9+H10+H13+H14 -> 9.288 | K11: PANQUECAS DE BANANA E AVEIA
C12: Porção | D12: 8 | E12: =E11/D12*B12 -> 0 | F12: =F11/D12*B12 -> 0 | G12: =G11/D12*B12 -> 0 | H12: =H11/D12*B12 -> 0 | K12: Ingredientes: Ovo classe M ; 1 colher de sopa de Farinha de Aveia; ½ banana Opcional: Canela Preparação: Começa por triturar, com a ajuda de um garfo, a meia banana. Num recipiente, mistura a banana esmagada, o ovo, a farinha e a canela, até obteres uma mistura homogénea. Numa frigideira antiaderente, adiciona pequenas porções do preparado. Deixa cozer entre 1 a 2 minutos de cada lado. | W12: BAGEL
B13: 0.8 | C13: Whey sabor | E13: =118.2*B13 -> 94.56 | F13: =22.8*B13 -> 18.24 | G13: =1.02*B13 -> 0.816 | H13: =2.55*B13 -> 2.04 | W13: Ingredientes: 35g farinha à escolha; 30g iogurte natural magro; 1 colher de chá de sementes. Preparação: Juntar tudo e moldar em forma de bagel. Untar a massa com as sementes e levar ao forno pré-aquecido, por cerca de 12 minutos.
E14: =E74 -> 204.61 | F14: =F74 -> 6.355625 | G14: =G74 -> 28.2125 | H14: =H74 -> 7.248
C15: Receitas | D15: Quantidade | E15: Kcal | F15: pt | G15: HC | H15: lp
C16: PAPAS DE AVEIA E BANANA NO FORNO - rende 4 porções | D16: 1 porção | E16: 110.21535 | F16: 5.10114 | G16: 15.204595 | H16: 2.80466
C17: PANQUECAS DE BANANA E AVEIA | E17: 189 | F17: 10.7 | G17: 18.23 | H17: 7.72 | K17: PANQUECAS DE IOGURTE E AVEIA
C18: PANQUECAS DE IOGURTE E AVEIA - rende 4 porções | D18: 2 porções | E18: 163.33 | F18: 10.08 | G18: 18.52 | H18: 5.06 | K18: Ingredientes: 1 ovo Classe M - 1 Iogurte sólido de aromas magro - 2 colheres de sopa de flocos de aveia - 2 colheres de sopa de farinha de aveia - Opcional: Canela a gosto Preparação: Deves optar por cozinhá-las numa frigideira antiaderente, para que não necessites mais do que 1 colher de café de azeite na sua confeção!
C19: BOLO DE BANANA E AVEIA- rende 8 fatias | D19: 1 porção | E19: 125.8 | F19: 5.7 | G19: 16.36 | H19: 3.72
C20: CREPES - rende 4 crepes | D20: 2 porções | E20: 146.41 | F20: 10.32 | G20: 11.38 | H20: 6.55
C21: CREPES DE CLARA, IOGURTE E CACAU | D21: 1porção | E21: =96.13*2 -> 192.26 | F21: =7.7*2 -> 15.4 | G21: =11.97*2 -> 23.94 | H21: =1.63*2 -> 3.26 | W21: pão de Batata
C22: PAPAS DE AVEIA, MAÇÃ E CANELA | D22: 1 porção | E22: 285.122 | F22: 11.3116 | G22: 49.3062 | H22: 3.338 | W22: 1 ovo - 30g farinha de trigo - 1 colher de sopa azeite - 100ml leite magro - 1 colher de sopa de sementes - 100g batata cozida -. Preparação_ 10 mintuos na air fryer
C23: PANQUECAS DE CAJU E BANANA | E23: 216.4 | F23: 11.07 | G23: 10.88 | H23: 13.91
C24: SMOTHIE | E24: 432.5214 | F24: 18.91956 | G24: 59.70838 | H24: 11.25964 | K24: BOLO DE BANANA E AVEIA
C25: SMOTHIE | D25: 1/2 porção | E25: =(E24/2) -> 216.2607 | F25: =(F24/2) -> 9.45978 | G25: =(G24/2) -> 29.85419 | H25: =(H24/2) -> 5.62982 | K25: Ingredientes: 2 bananas maduras – 3 ovos – 100g de farinha de aveia – 40g de flocos de aveia – 1colher de chá de fermento – canela a gosto Preparação: Começa por triturar, com ajuda de um garfo, as bananas. Num recipiente, adiciona a farinha os flocos de aveia, os ovos e mexe até obter uma mistura homogénea. De seguida, adiciona as bananas trituradas, o fermento e canela a gosto. Leva ao forno (pré-aquecido a 180ºC), durante 30 minutos. O bolo deve ser dividido em 8 fatias iguais. Para versão de queque, adicionar em 8 formas e levar apenas 17 minutos ao forno.
C26: BOLO DE CENOURA E LARANJA | D26: 1 Fatia | E26: 98.7725 | F26: 5.44375 | G26: 10.97625 | H26: 3.344
C27: PANQUECAS DE CAJU E BANANA - COM CLARA OVO | E27: 228.0364 | F27: 19.11056 | G27: 19.90888 | H27: 7.79264
C28: PANQUECAS BANANA E AVEIA - COM CLARA OVO | E28: 181.4264 | F28: 13.78056 | G28: 26.90888 | H28: 1.60664 | W28: Rice Cake
C29: PANQUECAS DE CENOURA E BANANA - COM CLARA | D29: 2 Panquecas | E29: 373.14 | F29: 20.19 | G29: 59.95 | H29: 5.56 | W29: Rende 15 porções! 500g arroz muito bem cozido;1L de água;pitada de canela;300g queijo creme light; 1 colher de sopa de mel ou agave; Preparação: 1. Cubra o arroz com a água e cozinhe. Adicione a canela para dar sabor.No fim, quase toda a água deverá ter sido absorvida. 2. Com o arroz ainda quente, acrescente o queijo creme e o mel. 3. Misturar bem num tabuleiro plano. Cubrir tudo, embrulhar em pelúcila aderente e deixar no frigorífico durante a noite. 4. Corte em 15 pedaços e embrulha em papel de alumínio individualmente.
C30: MUFFINS CENOURA E BANANA - COM CLARA | D30: 1 | E30: 93.29 | F30: 5.04 | G30: 14.9 | H30: 1.39
C31: BOLACHAS DE BANANA E FLOCOS DE AVEIA + CACAU | D31: 1 | E31: 34.39664 | F31: 1.039056 | G31: 5.738888 | H31: 0.625664
C32: MUFFINS CENOURA E BANANA - COM CLARA | D32: 1 muffin | E32: 124.38107 | F32: 6.7284267 | G32: 19.983147 | H32: 1.8521067
C33: PANQUECAS DE LARANJA | D33: completa | E33: 320 | F33: 24 | G33: 32.8 | H33: 9.44 | K33: CREPES
C34: PANQUECAS DE IOGURTE ALPRO E AVEIA | D34: Receita completa - 7 panquecas | E34: 317.24 | F34: 22.42 | G34: 40.136 | H34: 6.748 | K34: Ingredientes: 2 colheres de sopa de farinha de trigo; 2 ovos; 10 colheres de sopa de leite magro Preparação: Deves proceder à preparação como se fosse uma “panqueca gigante”, adicionando todo o preparado de uma só vez numa frigideira antiaderente por cerca de 1-2minutos de cada lado.
C35: BOLO DA CANECA DE CACAU | D35: 1 UNIDADE | E35: 175.085 | F35: 12.13 | G35: 11.88 | H35: 8.1705
C36: PANQUECAS POLVILHO | E36: 129.2 | F36: 10.96 | G36: 21.99 | H36: 0.02 | W36: Bolacha de Caju
C37: PANQUECA DE MAÇÃ E CANELA | D37: RECEITA COMPLETA | E37: 370.892 | F37: 21.8736 | G37: 50.7712 | H37: 8.048 | W37: 100g flocos de aveia; 100g cajus; 2 colheres de sopa de água; 2 colheres de sopa de mel; levar 20 minutos ao forno.
C38: PANQUECA DE MAÇÃ E CANELA | D38: 1/2 RECEITA | E38: =E37/2 -> 185.446 | F38: =F37/2 -> 10.9368 | G38: =G37/2 -> 25.3856 | H38: =H37/2 -> 4.024
C39: PANQUECAS DE MAÇÃ E CANELA COM 1/2 WHEY, SEM OVO | D39: RECEITA COMPLETA | E39: 343.572 | F39: 25.7336 | G39: 51.2812 | H39: 3.059 | K39: PAPAS DE AVEIA, MAÇÃ E CANELA
C40: PANQUECA MAÇÃ E CLARA OVO | E40: 226.422 | F40: 18.6186 | G40: 33.9712 | H40: 1.381 | K40: Ingredientes: 1 copo de leite (200ml); 30g de flocos de aveia; 1 maçã às rodelas; canela q.b. Preparação: Começa por cozer as rodelas de 1/2 maçã. De seguida, coloca, num recipiente em lume médio, o leite, os flocos de aveia e a maçã. Deves ir mexendo o preparado até obteres a consistência desejada. Passa o preparado para uma taça, adiciona a outra metade da maçã em rodelas e polvilha com canela.
C41: BOLO UNIDADE MAÇÃ DESERT
C42: PANQUECAS DE LARANJA E CENOURA | D42: RECEITA COMPLETA | E42: 215.22 | F42: 11.46 | G42: 23.1 | H42: 7.904
C43: Panquecas de Iogurte Natural | D43: receita completa | E43: 274 | F43: 15.91 | G43: 36.154 | H43: 9.394 | W43: Bolacha de Canela
C44: PANQUECA DE IOGURTE PROTEICO | D44: RECEITA COMPLETA | E44: 394.82 | F44: 32.54 | G44: 42.54 | H44: 12.064 | W44: 60g farinha de aveia; 40g farinha de linhaça; 2 colheres de sopa de canela;2 colheres de sopa de azeite;2 colheres de sopa de mel;1 colher de café de fermento;100ml água quente. 10 minutos no forno a 180º
C45: GRANOLA | D45: RECEITA COMPLETA | E45: 343.42 | F45: 23.54 | G45: 40.07 | H45: 11.435
C46: GRANOLA | D46: 1/2 RECEITA | E46: =E45/2 -> 171.71 | F46: =F45/2 -> 11.77 | G46: =G45/2 -> 20.035 | H46: =H45/2 -> 5.7175 | K46: PANQUECAS DE CAJU E BANANA
C47: PÃO NA AIRFRYIER | E47: 343.36 | F47: 24.44 | G47: 47.04 | H47: 5.756 | K47: Ingredientes: 1 ovo; 1/2 banana; 15g de cajus torrados sem sal Preparação: Junta tudo numa misturadora, até obteres uma massa homogénea. De seguida, numa frigideira antiaderente adiciona o preparado e deixa cozer por cerca de 1 minuto de cada lado.
C48: BAGEL | E48: 163.08 | F48: 7.245 | G48: 22.205 | H48: 4.788
C49: PÃO DE BATATA | E49: 245.005 | F49: 9.877 | G49: 28.675 | H49: 9.8735 | W49: DOCE BANANA, AVEIA, COM RECHEIO
C50: Bolo Proteico Whey e Banana | D50: porção completa | E50: 549.3964 | F50: 50.64556 | G50: 53.57888 | H50: 13.70564 | W50: 1 Banana + 100g farinha de aveia. Moldar, em forma retangular (com bordas) . Levar a cozinhar 10 minutos a 180º. Recheio: 400g iogurte natural + 200g morango+ 2 colheres de sopa de mel + 2 folhas gelatina incolor. Triturar tudo. Cobertura: 2 colheres de chá de manteiga de amendoim. Rechear e levar ao frio a solidificar.
C51: BOLO IOGURTE | D51: 1 porção | E51: 205.1575 | F51: 11.80125 | G51: 19.7925 | H51: 8.39925
C52: BOLO DE MAÇÃ | D52: 1 porção | E52: 388.077 | F52: 22.8336 | G52: 45.7437 | H52: 11.23225 | K52: SMOTHIE
C53: RICE CAKE | D53: 1 porção | E53: 79.74 | F53: 2.2508667 | G53: 10.774467 | H53: 2.9093333 | K53: Ingredientes: 1 banana média congelada; 20g sementes de chia; 10g cacau puro; 50g iogurte natural magro; 100ml leite magro;50g flocos de aveia Preparação: Liquidificar tudo
C54: BOLO INDIVIDUAL DE BANANA | D54: 1 porção | E54: 412.585 | F54: 13.619 | G54: 75.4315 | H54: 4.907
C55: BOLACHA DE CAJU | D55: Porção completa | E55: 1125.65 | F55: 33.7 | G55: 106.794 | H55: 59.78
C56: Bolachas de Canela | D56: Porção completa | E56: 661.668 | F56: 16.24 | G56: 67.6208 | H56: 32.922
C57: BROWNIE GRÃO DE BICO | D57: Porção completa | E57: 1277.1 | F57: 93.675 | G57: 204.844 | H57: 50.232 | W57: PÃO DE QUINOA
C58: DOCE DE BANANA E AVEIA COM RECHEIO | D58: RECEITA COMPLETA | E58: 963.2864 | F58: 37.53056 | G58: 151.12888 | H58: 26.13264 | W58: 300g de quinoa (deixar demolhar durante a noite) + 4 ovos + 1 colher de chá de fermento + sal q.b. --- triturar tudo, moldar, colocar topping 1 colher de chá de sementes e levar ao forno a 180º durante 30 minutos. Dividir em 8 fatias iguais.
C59: PAPAS FERRERO ROCHER | D59: Unidose | E59: 410.7475 | F59: 12.338 | G59: 35.72 | H59: 22.8 | K59: PAPAS FERRERO ROCHER
C60: PÃO DE QUINOA | D60: 1 fatia | E60: 183.46 | F60: 8.6825 | G60: 25.8375 | H60: 5.307 | K60: 2 tortitas de arroz + 2 colheres de chá de pasta de avelãs + 100g iogurte natural magro + 1 colher de chá de cacau magro em pó. Para o topping: 15g de avelãs trituradas + 1 colher de chá de mel + canela q.b.
C61: PAPAS MEXIDAS DE FRIGIDEIRA
C62: Crumble de Maçã | D62: porção completa | E62: 302.802 | F62: 4.9036 | G62: 43.7772 | H62: 10.654
C63: BOLO INDIVIDUAL DE MAÇÃ | D63: COMPLETO | E63: 518.062 | F63: 20.6336 | G63: 60.5012 | H63: 20.99 | W63: PAPAS MEXIDAS DE FRIGIDEIRA
C64: BOLACHA DE BANANA, AVEIA E CAJU | D64: 1 bolacha | E64: 136.47978 | F64: 7.254412 | G64: 14.260326 | H64: 5.089728 | W64: Adicionar ovo, flocos de aveia + banana esmagada + canela e fazer na frigideira como se fossem ovos mexidos. Adicionar em cima de iogurte, com toppings
C65: BOLO DE MAÇÃ | D65: 1 FATIA | E65: 264.208 | F65: 10.7304 | G65: 39.5498 | H65: 6.5335
C66: Bolo de Banana e farinha Arroz | D66: 1 fatia | E66: 89.8816 | F66: 4.68764 | G66: 9.26722 | H66: 3.55516 | K66: PANQUECAS CENOURA E BANANA
C67: BOLO DE CÔCO | D67: 1 fatia | E67: 199.05 | F67: 15.1205 | G67: 7.30575 | H67: 11.61225 | K67: RENDE 4 PANQUECAS 150g clara ovo; 140g farinha aveia; 3 cenouras; 1 banana; fermento; canela q.b. RENDE 8 MUFFINS
C68: PÃO DE FRIGIDEIRA | D68: Porção completa | E68: 255.38 | F68: 14.144 | G68: 13.53 | H68: 15.194 | W68: CRUMBLE DE MAÇÃ
C69: BARRITA DE CEREAIS | D69: 1 barrita | E69: 128.2708 | F69: 3.3644 | G69: 20.19264 | H69: 3.415 | W69: Começa por dar uma pré-cozedura a 1 maçã aos cubos, depois, num tabuleiro de forno junta a maçã, 15g de flocos de aveia + 15g de frutos secos sem sal + 2 colheres de chá de mel + canela q.b. -- levar ao forno a 180º, durante 15 minutos.
C70: PÃO DE QUEIJO
C71: BOLO DE MAÇÃ E CENOURA | D71: 1 FATIA | E71: 137.983 | F71: 5.50965 | G71: 14.7553 | H71: 5.98875
C72: GRANOLA COMPLETA | D72: Porção completa | E72: 1128.455 | F72: 29.833 | G72: 126.692 | H72: 52.1115
B73: T | C73: PÃO DE QUEIJO COTTAGE
C74: BOLO DE CENOURA, AVEIA E MEL | D74: 1 fatia | E74: 204.61 | F74: 6.355625 | G74: 28.2125 | H74: 7.248 | W74: BOLACHA DE BANANA, AVEIA E CAJU
C75: PÃO DE BANANA , ESPELTA E AMÊNDOA | D75: 1 fatia | E75: 194.2539 | F75: 7.687585 | G75: 22.53933 | H75: 7.537515 | W75: 140g flocos de aveia + 100ml leite magro + canela q.b. + 30g de manteiga de amendoim/caju (3 colheres chá) + 2 bananas + 1 colher sopa de sementes + 1scoop e meio de proteína sabor --- rendem 10 bolachas! Levar 10 minutos ao forno
C76: MUFFINS DE TANGERINA, CENOURA E CÔCO | D76: 1 muffin | E76: 237.34507 | F76: 7.6922133 | G76: 14.449953 | H76: 15.42816 | K76: PANQUECAS DE BANANA E AVEIA COM CLARAS
C77: Banana bread proteico | E77: 144.2658 | F77: 12.64507 | G77: 13.18986 | H77: 4.190705 | K77: 100g clara ovos ; 1 colher de sopa de Farinha de Aveia; 1 banana Opcional: Canela
C78: Bolo de Laranja e côco | D78: 1 fatia | E78: 201.29875 | F78: 6.7105 | G78: 17.907 | H78: 10.716875
W80: PÃO DE FRIGIDEIRA
W81: 1 ovo + 10g de farinha de linhaça + 20g de farinha de aveia/espelta + 1 colher de sopa de sementes
E84: =E63/2 -> 259.031 | F84: =F63/2 -> 10.3168 | G84: =G63/2 -> 30.2506 | H84: =H63/2 -> 10.495 | K84: CAJU E BANANA COM CLARA DE OVOS
K85: 150g de clara de ovos; 1 banana; 15g de cajus torrados sem sal
W86: BARRA DE PRÉ-TREINO
W87: 250g de flocos de aveia; 300g de mel; 55g de sementes de linhaça; 150g de tâmaras; 100g de manteiga de amendoim;60g de flocos de trigo ou arroz Preparação: juntar todos os ingredientes, em lume médio por 2 minutos, à exceção dos flocos de arroz/trigo. De seguida, moldar e esperar que endureça para cortar em 25 barritas iguais.
K90: BOLACHAS DE BANANA E PEPITAS
K91: 2 COLHERES SOPA FARINHA DE AVEIA + 1 BANANA + 1 COLHER DE CHÁ DE PEPITAS DE CACAU + 30G FLOCOS AVEIA . 30 MINUTOS . RENDE 10
W94: GRANOLA
W95: 150g de flocos integrais (aveia, puff de trigo, puff de quinoa) + 30g de amêndoas e nozes + 15g de mix de sementes + 1 colher de sopa de azeite + 30g de maple syrup + (opcional: cacau magro em pó, canela, gengibre, curcuma) // preparação: pré-aquece o forno a 180º. Junta os ingredientes secos e, de seguida os líquidos (envolvendo bem a mistura). Depois, dispõe num tabuleiro de ir ao forno, sem sobrepôr os ingredientes. Deixar ficar 30 minutos no forno e ir mexendo a cada 10, para não queimar. Deixa arrefecer completamente, depois de retirar do forno
K96: CREPES CLARA DE OVO E IOGURTE
B97: 1 | K97: RENDE 2 CREPES . 70g claras+ 50g de iogurte natural magro + 2 colheres de sopa de farinha de aveia + 1 colher de café de cacau magro em pó
K101: PANQUECAS LARANJA
K102: RENDEM 8 PANQUECAS OU 17 MINI PANQUECAS .1 OVO +100g claras + sumo e raspas de 1/2 laranja + 50g farinha de aveia + 1 colher de café de fermento
K107: PANQUECAS IOGURTE MANGA E AVEIA
K108: Rende 7 Panquecas . 100g clara de ovos; 100g iogurte alpro manga 0%açúcares; 2 colheres de sopa de farinha de aveia; 2 colheres de sopa de flocos de aveia
K113: BOLO DA CANECA - CACAU
K114: 1 Ovo -1 colher de sopa de farinha de aveia (ou trigo) - 1 colher de café de cacau magro em pó- 1 colher de sopa de iogurte natural magro
K119: Panquecas de Polvilho Doce
K120: 100g clara de ovo; 25g polvilho; 25g iogurte natural magro
K126: PANQUECAS MAÇÃ E CANELA
K127: 1 Ovo; 100g de clara de ovo; 35g de farinha de arroz ou trigo; 10g flocos de aveia; 1/2 maçã + 1/2 maçã na frigideira
K133: PANQUECAS MAÇÃ E CLARA OVO + POLVILHO
...

Sheet IMC
A1: BMI-for-age GIRLS
A2: 2 to 19 years (percentiles)
A4: Percentiles (BMI in kg/m2)
A5: Year: Month | B5: Month | C5: L | D5: M | E5: S | F5: <1st | G5: 1st | H5: 3rd | I5: 5th | J5: 15th | K5: 25th | L5: 50th | M5: 75th | N5: 85th | O5: 95th | P5: 97th | Q5: 99th | R5: >99
A6: 2: 0 | B6: 24 | C6: -0.568 | D6: 15.688 | E6: 0.0845 | F6: -1 | G6: 13 | H6: 13.5 | I6: 13.7 | J6: 14.4 | K6: 14.8 | L6: 15.7 | M6: 16.6 | N6: 17.2 | O6: 18.1 | P6: 18.5 | Q6: 19.3 | R6: 9999
A7: 2: 1 | B7: 25 | C7: -0.5684 | D7: 15.659 | E7: 0.08452 | F7: -1 | G7: 13 | H7: 13.4 | I7: 13.7 | J7: 14.4 | K7: 14.8 | L7: 15.7 | M7: 16.6 | N7: 17.1 | O7: 18.1 | P7: 18.5 | Q7: 19.3 | R7: 9999
A8: 2: 2 | B8: 26 | C8: -0.5684 | D8: 15.6308 | E8: 0.08449 | F8: -1 | G8: 13 | H8: 13.4 | I8: 13.7 | J8: 14.4 | K8: 14.8 | L8: 15.6 | M8: 16.6 | N8: 17.1 | O8: 18.1 | P8: 18.5 | Q8: 19.3 | R8: 9999
A9: 2: 3 | B9: 27 | C9: -0.5684 | D9: 15.6037 | E9: 0.08446 | F9: -1 | G9: 13 | H9: 13.4 | I9: 13.7 | J9: 14.3 | K9: 14.8 | L9: 15.6 | M9: 16.5 | N9: 17.1 | O9: 18 | P9: 18.4 | Q9: 19.2 | R9: 9999
A10: 2: 4 | B10: 28 | C10: -0.5684 | D10: 15.5777 | E10: 0.08444 | F10: -1 | G10: 12.9 | H10: 13.4 | I10: 13.6 | J10: 14.3 | K10: 14.7 | L10: 15.6 | M10: 16.5 | N10: 17 | O10: 18 | P10: 18.4 | Q10: 19.2 | R10: 9999
A11: 2: 5 | B11: 29 | C11: -0.5684 | D11: 15.5523 | E11: 0.08443 | F11: -1 | G11: 12.9 | H11: 13.4 | I11: 13.6 | J11: 14.3 | K11: 14.7 | L11: 15.6 | M11: 16.5 | N11: 17 | O11: 18 | P11: 18.4 | Q11: 19.2 | R11: 9999
A12: 2: 6 | B12: 30 | C12: -0.5684 | D12: 15.5276 | E12: 0.08444 | F12: -1 | G12: 12.9 | H12: 13.3 | I12: 13.6 | J12: 14.3 | K12: 14.7 | L12: 15.5 | M12: 16.5 | N12: 17 | O12: 17.9 | P12: 18.3 | Q12: 19.1 | R12: 9999
A13: 2: 7 | B13: 31 | C13: -0.5684 | D13: 15.5034 | E13: 0.08448 | F13: -1 | G13: 12.9 | H13: 13.3 | I13: 13.6 | J13: 14.2 | K13: 14.7 | L13: 15.5 | M13: 16.4 | N13: 17 | O13: 17.9 | P13: 18.3 | Q13: 19.1 | R13: 9999
A14: 2: 8 | B14: 32 | C14: -0.5684 | D14: 15.4798 | E14: 0.08455 | F14: -1 | G14: 12.8 | H14: 13.3 | I14: 13.5 | J14: 14.2 | K14: 14.6 | L14: 15.5 | M14: 16.4 | N14: 16.9 | O14: 17.9 | P14: 18.3 | Q14: 19.1 | R14: 9999
A15: 2: 9 | B15: 33 | C15: -0.5684 | D15: 15.4572 | E15: 0.08467 | F15: -1 | G15: 12.8 | H15: 13.3 | I15: 13.5 | J15: 14.2 | K15: 14.6 | L15: 15.5 | M15: 16.4 | N15: 16.9 | O15: 17.9 | P15: 18.3 | Q15: 19 | R15: 9999
A16: 2:10 | B16: 34 | C16: -0.5684 | D16: 15.4356 | E16: 0.08484 | F16: -1 | G16: 12.8 | H16: 13.2 | I16: 13.5 | J16: 14.2 | K16: 14.6 | L16: 15.4 | M16: 16.4 | N16: 16.9 | O16: 17.9 | P16: 18.2 | Q16: 19 | R16: 9999
A17: 2:11 | B17: 35 | C17: -0.5684 | D17: 15.4155 | E17: 0.08506 | F17: -1 | G17: 12.8 | H17: 13.2 | I17: 13.5 | J17: 14.1 | K17: 14.6 | L17: 15.4 | M17: 16.3 | N17: 16.9 | O17: 17.8 | P17: 18.2 | Q17: 19 | R17: 9999
... A210: 19: 0 | B210: 228 | C210: -0.7496 | D210: 21.4269 | E210: 0.14441 | F210: -1 | G210: 15.879 | H210: 16.734 | I210: 17.22 | J210: 18.593 | K210: 19.504 | L210: 21.427 | M210: 23.707 | N210: 25.113 | O210: 27.833 | P210: 29.03 | Q210: 31.553 | R210: 9999

Sheet PEDIATRIA
A1: Turma | B1: Nº | C1: Nome | D1: Data Medição | E1: Data Nascimento | F1: Meses | G1: Anos e Meses | H1: Peso | I1: Altura | J1: Altura (cm) | K1: PC | L1: PC/alt | M1: IMC | N1: Linha | O1: Coluna | P1: Perc IMC | Q1: Classificação IMC | R1: Linha | S1: Coluna | T1: Perc cint | U1: IMC ideal | V1: Coluna pretendida | W1: Perc IMC ideal | X1: Peso ideal | Y1: Peso a perder | AA1: <1st | AB1: 1st | AC1: 3rd | AD1: 5th | AE1: 15th | AF1: 25th | AG1: 50th | AH1: 75th | AI1: 85th | AJ1: 95th | AK1: 97th | AL1: 99th | AM1: >99
D2: 44717 | E2: 38797 | F2: =DATEDIF(E2,D2,"M") -> 194 | G2: =YEARFRAC(D2,E2) -> 16.205556 | H2: 59 | I2: 1.75 | J2: =I2*100 -> 175 | K2: 70 | L2: =K2/J2 -> 0.4 | M2: =IF(H2>0,IF(I2>0,H2/I2^2,""),"") -> 19.265306 | N2: =MATCH(F2,[2]IMC!B:B,0) -> 176 | O2: =MATCH(M2,INDIRECT("IMC!F" & N2 & ":R" &N2),1) -> 6 | P2: =CONCATENATE(INDEX(IMC!$F$1:$R$5,5,$O2) & " e " & INDEX(IMC!$F$1:$R$5,5,$O2+1)) -> 25th e 50th | R2: =MATCH(F2,[3]PC!A:A,0) -> 82 | S2: =MATCH(K2,INDIRECT("PC!E" & R2 & ":L" &R2),1) -> #REF! | T2: =CONCATENATE(INDEX([3]PC!$E$1:$M$2,1,$S2) & " e " & INDEX([3]PC!$E$1:$M$2,1,$S2+1)) -> #REF! | U2: 17 | V2: =MATCH(U2,INDIRECT("IMC!F" & N2 & ":R" &N2),1) -> 4 | W2: =CONCATENATE(INDEX([3]IMC!$F$1:$R$5,5,$V2) & " e " & INDEX([3]IMC!$F$1:$R$5,5,$V2+1)) -> 5th e 15th | X2: =U2*(I2*I2) -> 52.0625 | Y2: =H2-X2 -> 6.9375 | AA2: =VLOOKUP(F2,[3]IMC!$B$6:$R$210,5,FALSE) -> -1 | AB2: =VLOOKUP(F2,[3]IMC!$B$6:$R$210,6,FALSE) -> 15.651 | AC2: =VLOOKUP(F2,[3]IMC!$B$6:$R$210,7,FALSE) -> 16.424 | AD2: =VLOOKUP(F2,[3]IMC!$B$6:$R$210,8,FALSE) -> 16.866 | AE2: =VLOOKUP(F2,[3]IMC!$B$6:$R$210,9,FALSE) -> 18.123 | AF2: =VLOOKUP(F2,[3]IMC!$B$6:$R$210,10,FALSE) -> 18.966 | AG2: =VLOOKUP(F2,[3]IMC!$B$6:$R$210,11,FALSE) -> 20.767 | AH2: =VLOOKUP(F2,[3]IMC!$B$6:$R$210,12,FALSE) -> 22.951 | AI2: =VLOOKUP(F2,[3]IMC!$B$6:$R$210,13,FALSE) -> 24.326 | AJ2: =VLOOKUP(F2,[3]IMC!$B$6:$R$210,14,FALSE) -> 27.056 | AK2: =VLOOKUP(F2,[3]IMC!$B$6:$R$210,15,FALSE) -> 28.289 | AL2: =VLOOKUP(F2,[3]IMC!$B$6:$R$210,16,FALSE) -> 30.957 | AM2: =VLOOKUP(F2,[3]IMC!$B$6:$R$210,17,FALSE) -> 9999
D3: 44717 | E3: 38797 | F3: =DATEDIF(E3,D3,"M") -> 194 | G3: =YEARFRAC(D3,E3) -> 16.205556 | H3: 59 | I3: 1.75 | J3: =I3*100 -> 175 | L3: =K3/J3 -> 0 | M3: =IF(H3>0,IF(I3>0,H3/I3^2,""),"") -> 19.265306 | N3: =MATCH(F3,[2]IMC!B:B,0) -> 176 | O3: =MATCH(M3,INDIRECT("IMC!F" & N3 & ":R" &N3),1) -> 6 | P3: =CONCATENATE(INDEX(IMC!$F$1:$R$5,5,$O3) & " e " & INDEX(IMC!$F$1:$R$5,5,$O3+1)) -> 25th e 50th | R3: =MATCH(F3,[3]PC!A:A,0) -> 82 | S3: =MATCH(K3,INDIRECT("PC!E" & R3 & ":L" &R3),1) -> #REF! | T3: =CONCATENATE(INDEX([3]PC!$E$1:$M$2,1,$S3) & " e " & INDEX([3]PC!$E$1:$M$2,1,$S3+1)) -> #REF! | W3: =CONCATENATE(INDEX([3]IMC!$F$1:$R$5,5,$V3) & " e " & INDEX([3]IMC!$F$1:$R$5,5,$V3+1)) -> #VALUE! | X3: =U3*(I3*I3) -> 0 | Y3: =H3-X3 -> 59
F4: =DATEDIF(E4,D4,"M") -> 0 | G4: =YEARFRAC(D4,E4) -> 0 | J4: =I4*100 -> 0 | L4: =K4/J4 -> #DIV/0! | M4: =IF(H4>0,IF(I4>0,H4/I4^2,""),"") | N4: =MATCH(F4,[2]IMC!B:B,0) -> #N/A | O4: =MATCH(M4,INDIRECT("IMC!F" & N4 & ":R" &N4),1) -> #N/A | P4: =CONCATENATE(INDEX(IMC!$F$1:$R$5,5,$O4) & " e " & INDEX(IMC!$F$1:$R$5,5,$O4+1)) -> #N/A | R4: =MATCH(F4,[3]PC!A:A,0) -> #N/A | S4: =MATCH(K4,INDIRECT("PC!E" & R4 & ":L" &R4),1) -> #N/A | T4: =CONCATENATE(INDEX([3]PC!$E$1:$M$2,1,$S4) & " e " & INDEX([3]PC!$E$1:$M$2,1,$S4+1)) -> #N/A | W4: =CONCATENATE(INDEX([3]IMC!$F$1:$R$5,5,$V4) & " e " & INDEX([3]IMC!$F$1:$R$5,5,$V4+1)) -> #VALUE! | X4: =U4*(I4*I4) -> 0 | Y4: =H4-X4 -> 0
F5: =DATEDIF(E5,D5,"M") -> 0 | G5: =YEARFRAC(D5,E5) -> 0 | J5: =I5*100 -> 0 | L5: =K5/J5 -> #DIV/0! | M5: =IF(H5>0,IF(I5>0,H5/I5^2,""),"") | N5: =MATCH(F5,[2]IMC!B:B,0) -> #N/A | O5: =MATCH(M5,INDIRECT("IMC!F" & N5 & ":R" &N5),1) -> #N/A | P5: =CONCATENATE(INDEX(IMC!$F$1:$R$5,5,$O5) & " e " & INDEX(IMC!$F$1:$R$5,5,$O5+1)) -> #N/A | R5: =MATCH(F5,[3]PC!A:A,0) -> #N/A | S5: =MATCH(K5,INDIRECT("PC!E" & R5 & ":L" &R5),1) -> #N/A | T5: =CONCATENATE(INDEX([3]PC!$E$1:$M$2,1,$S5) & " e " & INDEX([3]PC!$E$1:$M$2,1,$S5+1)) -> #N/A | W5: =CONCATENATE(INDEX([3]IMC!$F$1:$R$5,5,$V5) & " e " & INDEX([3]IMC!$F$1:$R$5,5,$V5+1)) -> #VALUE! | X5: =U5*(I5*I5) -> 0 | Y5: =H5-X5 -> 0
F6: =DATEDIF(E6,D6,"M") -> 0 | G6: =YEARFRAC(D6,E6) -> 0 | J6: =I6*100 -> 0 | L6: =K6/J6 -> #DIV/0! | M6: =IF(H6>0,IF(I6>0,H6/I6^2,""),"") | N6: =MATCH(F6,[2]IMC!B:B,0) -> #N/A | O6: =MATCH(M6,INDIRECT("IMC!F" & N6 & ":R" &N6),1) -> #N/A | P6: =CONCATENATE(INDEX(IMC!$F$1:$R$5,5,$O6) & " e " & INDEX(IMC!$F$1:$R$5,5,$O6+1)) -> #N/A | R6: =MATCH(F6,[3]PC!A:A,0) -> #N/A | S6: =MATCH(K6,INDIRECT("PC!E" & R6 & ":L" &R6),1) -> #N/A | T6: =CONCATENATE(INDEX([3]PC!$E$1:$M$2,1,$S6) & " e " & INDEX([3]PC!$E$1:$M$2,1,$S6+1)) -> #N/A | W6: =CONCATENATE(INDEX([3]IMC!$F$1:$R$5,5,$V6) & " e " & INDEX([3]IMC!$F$1:$R$5,5,$V6+1)) -> #VALUE! | X6: =U6*(I6*I6) -> 0 | Y6: =H6-X6 -> 0
F7: =DATEDIF(E7,D7,"M") -> 0 | G7: =YEARFRAC(D7,E7) -> 0 | J7: =I7*100 -> 0 | L7: =K7/J7 -> #DIV/0! | M7: =IF(H7>0,IF(I7>0,H7/I7^2,""),"") | N7: =MATCH(F7,[2]IMC!B:B,0) -> #N/A | O7: =MATCH(M7,INDIRECT("IMC!F" & N7 & ":R" &N7),1) -> #N/A | P7: =CONCATENATE(INDEX(IMC!$F$1:$R$5,5,$O7) & " e " & INDEX(IMC!$F$1:$R$5,5,$O7+1)) -> #N/A | R7: =MATCH(F7,[3]PC!A:A,0) -> #N/A | S7: =MATCH(K7,INDIRECT("PC!E" & R7 & ":L" &R7),1) -> #N/A | T7: =CONCATENATE(INDEX([3]PC!$E$1:$M$2,1,$S7) & " e " & INDEX([3]PC!$E$1:$M$2,1,$S7+1)) -> #N/A | W7: =CONCATENATE(INDEX([3]IMC!$F$1:$R$5,5,$V7) & " e " & INDEX([3]IMC!$F$1:$R$5,5,$V7+1)) -> #VALUE! | X7: =U7*(I7*I7) -> 0 | Y7: =H7-X7 -> 0
D8: 44570 | E8: 39714 | F8: =DATEDIF(E8,D8,"M") -> 159 | G8: =YEARFRAC(D8,E8) -> 13.294444 | H8: 69.1 | I8: 1.72 | J8: =I8*100 -> 172 | L8: =K8/J8 -> 0 | M8: =IF(H8>0,IF(I8>0,H8/I8^2,""),"") -> 23.35722 | N8: =MATCH(F8,[3]IMC!B:B,0) -> 141 | O8: =MATCH(M8,INDIRECT("IMC!F" & N8 & ":R" &N8),1) -> 9 | P8: =CONCATENATE(INDEX(IMC!$F$1:$R$5,5,$O8) & " e " & INDEX(IMC!$F$1:$R$5,5,$O8+1)) -> 85th e 95th | R8: =MATCH(F8,[3]PC!A:A,0) -> 47 | S8: =MATCH(K8,INDIRECT("PC!E" & R8 & ":L" &R8),1) -> #REF! | T8: =CONCATENATE(INDEX([3]PC!$E$1:$M$2,1,$S8) & " e " & INDEX([3]PC!$E$1:$M$2,1,$S8+1)) -> #REF! | W8: =CONCATENATE(INDEX([3]IMC!$F$1:$R$5,5,$V8) & " e " & INDEX([3]IMC!$F$1:$R$5,5,$V8+1)) -> #VALUE! | X8: =U8*(I8*I8) -> 0 | Y8: =H8-X8 -> 69.1
F9: =DATEDIF(E9,D9,"M") -> 0 | G9: =YEARFRAC(D9,E9) -> 0 | J9: =I9*100 -> 0 | L9: =K9/J9 -> #DIV/0! | M9: =IF(H9>0,IF(I9>0,H9/I9^2,""),"") | N9: =MATCH(F9,[3]IMC!B:B,0) -> #N/A | O9: =MATCH(M9,INDIRECT("IMC!F" & N9 & ":R" &N9),1) -> #N/A | P9: =CONCATENATE(INDEX(IMC!$F$1:$R$5,5,$O9) & " e " & INDEX(IMC!$F$1:$R$5,5,$O9+1)) -> #N/A | R9: =MATCH(F9,[3]PC!A:A,0) -> #N/A | S9: =MATCH(K9,INDIRECT("PC!E" & R9 & ":L" &R9),1) -> #N/A | T9: =CONCATENATE(INDEX([3]PC!$E$1:$M$2,1,$S9) & " e " & INDEX([3]PC!$E$1:$M$2,1,$S9+1)) -> #N/A | W9: =CONCATENATE(INDEX([3]IMC!$F$1:$R$5,5,$V9) & " e " & INDEX([3]IMC!$F$1:$R$5,5,$V9+1)) -> #VALUE! | X9: =U9*(I9*I9) -> 0 | Y9: =H9-X9 -> 0
F10: =DATEDIF(E10,D10,"M") -> 0 | G10: =YEARFRAC(D10,E10) -> 0 | J10: =I10*100 -> 0 | L10: =K10/J10 -> #DIV/0! | M10: =IF(H10>0,IF(I10>0,H10/I10^2,""),"") | N10: =MATCH(F10,[3]IMC!B:B,0) -> #N/A | O10: =MATCH(M10,INDIRECT("IMC!F" & N10 & ":R" &N10),1) -> #N/A | P10: =CONCATENATE(INDEX(IMC!$F$1:$R$5,5,$O10) & " e " & INDEX(IMC!$F$1:$R$5,5,$O10+1)) -> #N/A | R10: =MATCH(F10,[3]PC!A:A,0) -> #N/A | S10: =MATCH(K10,INDIRECT("PC!E" & R10 & ":L" &R10),1) -> #N/A | T10: =CONCATENATE(INDEX([3]PC!$E$1:$M$2,1,$S10) & " e " & INDEX([3]PC!$E$1:$M$2,1,$S10+1)) -> #N/A | W10: =CONCATENATE(INDEX([3]IMC!$F$1:$R$5,5,$V10) & " e " & INDEX([3]IMC!$F$1:$R$5,5,$V10+1)) -> #VALUE! | X10: =U10*(I10*I10) -> 0 | Y10: =H10-X10 -> 0
F11: =DATEDIF(E11,D11,"M") -> 0 | G11: =YEARFRAC(D11,E11) -> 0 | J11: =I11*100 -> 0 | L11: =K11/J11 -> #DIV/0! | M11: =IF(H11>0,IF(I11>0,H11/I11^2,""),"") | N11: =MATCH(F11,[3]IMC!B:B,0) -> #N/A | O11: =MATCH(M11,INDIRECT("IMC!F" & N11 & ":R" &N11),1) -> #N/A | P11: =CONCATENATE(INDEX(IMC!$F$1:$R$5,5,$O11) & " e " & INDEX(IMC!$F$1:$R$5,5,$O11+1)) -> #N/A | R11: =MATCH(F11,[3]PC!A:A,0) -> #N/A | S11: =MATCH(K11,INDIRECT("PC!E" & R11 & ":L" &R11),1) -> #N/A | T11: =CONCATENATE(INDEX([3]PC!$E$1:$M$2,1,$S11) & " e " & INDEX([3]PC!$E$1:$M$2,1,$S11+1)) -> #N/A | W11: =CONCATENATE(INDEX([3]IMC!$F$1:$R$5,5,$V11) & " e " & INDEX([3]IMC!$F$1:$R$5,5,$V11+1)) -> #VALUE! | X11: =U11*(I11*I11) -> 0 | Y11: =H11-X11 -> 0
F12: =DATEDIF(E12,D12,"M") -> 0 | G12: =YEARFRAC(D12,E12) -> 0 | J12: =I12*100 -> 0 | L12: =K12/J12 -> #DIV/0! | M12: =IF(H12>0,IF(I12>0,H12/I12^2,""),"") | N12: =MATCH(F12,[3]IMC!B:B,0) -> #N/A | O12: =MATCH(M12,INDIRECT("IMC!F" & N12 & ":R" &N12),1) -> #N/A | P12: =CONCATENATE(INDEX(IMC!$F$1:$R$5,5,$O12) & " e " & INDEX(IMC!$F$1:$R$5,5,$O12+1)) -> #N/A | R12: =MATCH(F12,[3]PC!A:A,0) -> #N/A | S12: =MATCH(K12,INDIRECT("PC!E" & R12 & ":L" &R12),1) -> #N/A | T12: =CONCATENATE(INDEX([3]PC!$E$1:$M$2,1,$S12) & " e " & INDEX([3]PC!$E$1:$M$2,1,$S12+1)) -> #N/A | W12: =CONCATENATE(INDEX([3]IMC!$F$1:$R$5,5,$V12) & " e " & INDEX([3]IMC!$F$1:$R$5,5,$V12+1)) -> #VALUE! | X12: =U12*(I12*I12) -> 0 | Y12: =H12-X12 -> 0
F13: =DATEDIF(E13,D13,"M") -> 0 | G13: =YEARFRAC(D13,E13) -> 0 | J13: =I13*100 -> 0 | L13: =K13/J13 -> #DIV/0! | M13: =IF(H13>0,IF(I13>0,H13/I13^2,""),"") | N13: =MATCH(F13,[3]IMC!B:B,0) -> #N/A | O13: =MATCH(M13,INDIRECT("IMC!F" & N13 & ":R" &N13),1) -> #N/A | P13: =CONCATENATE(INDEX(IMC!$F$1:$R$5,5,$O13) & " e " & INDEX(IMC!$F$1:$R$5,5,$O13+1)) -> #N/A | R13: =MATCH(F13,[3]PC!A:A,0) -> #N/A | S13: =MATCH(K13,INDIRECT("PC!E" & R13 & ":L" &R13),1) -> #N/A | T13: =CONCATENATE(INDEX([3]PC!$E$1:$M$2,1,$S13) & " e " & INDEX([3]PC!$E$1:$M$2,1,$S13+1)) -> #N/A | W13: =CONCATENATE(INDEX([3]IMC!$F$1:$R$5,5,$V13) & " e " & INDEX([3]IMC!$F$1:$R$5,5,$V13+1)) -> #VALUE! | X13: =U13*(I13*I13) -> 0 | Y13: =H13-X13 -> 0
F14: =DATEDIF(E14,D14,"M") -> 0 | G14: =YEARFRAC(D14,E14) -> 0 | J14: =I14*100 -> 0 | L14: =K14/J14 -> #DIV/0! | M14: =IF(H14>0,IF(I14>0,H14/I14^2,""),"") | N14: =MATCH(F14,[3]IMC!B:B,0) -> #N/A | O14: =MATCH(M14,INDIRECT("IMC!F" & N14 & ":R" &N14),1) -> #N/A | P14: =CONCATENATE(INDEX(IMC!$F$1:$R$5,5,$O14) & " e " & INDEX(IMC!$F$1:$R$5,5,$O14+1)) -> #N/A | R14: =MATCH(F14,[3]PC!A:A,0) -> #N/A | S14: =MATCH(K14,INDIRECT("PC!E" & R14 & ":L" &R14),1) -> #N/A | T14: =CONCATENATE(INDEX([3]PC!$E$1:$M$2,1,$S14) & " e " & INDEX([3]PC!$E$1:$M$2,1,$S14+1)) -> #N/A | W14: =CONCATENATE(INDEX([3]IMC!$F$1:$R$5,5,$V14) & " e " & INDEX([3]IMC!$F$1:$R$5,5,$V14+1)) -> #VALUE! | X14: =U14*(I14*I14) -> 0 | Y14: =H14-X14 -> 0
F15: =DATEDIF(E15,D15,"M") -> 0 | G15: =YEARFRAC(D15,E15) -> 0 | J15: =I15*100 -> 0 | L15: =K15/J15 -> #DIV/0! | M15: =IF(H15>0,IF(I15>0,H15/I15^2,""),"") | N15: =MATCH(F15,[3]IMC!B:B,0) -> #N/A | O15: =MATCH(M15,INDIRECT("IMC!F" & N15 & ":R" &N15),1) -> #N/A | P15: =CONCATENATE(INDEX(IMC!$F$1:$R$5,5,$O15) & " e " & INDEX(IMC!$F$1:$R$5,5,$O15+1)) -> #N/A | R15: =MATCH(F15,[3]PC!A:A,0) -> #N/A | S15: =MATCH(K15,INDIRECT("PC!E" & R15 & ":L" &R15),1) -> #N/A | T15: =CONCATENATE(INDEX([3]PC!$E$1:$M$2,1,$S15) & " e " & INDEX([3]PC!$E$1:$M$2,1,$S15+1)) -> #N/A | W15: =CONCATENATE(INDEX([3]IMC!$F$1:$R$5,5,$V15) & " e " & INDEX([3]IMC!$F$1:$R$5,5,$V15+1)) -> #VALUE! | X15: =U15*(I15*I15) -> 0 | Y15: =H15-X15 -> 0
F16: =DATEDIF(E16,D16,"M") -> 0 | G16: =YEARFRAC(D16,E16) -> 0 | J16: =I16*100 -> 0 | L16: =K16/J16 -> #DIV/0! | M16: =IF(H16>0,IF(I16>0,H16/I16^2,""),"") | N16: =MATCH(F16,[3]IMC!B:B,0) -> #N/A | O16: =MATCH(M16,INDIRECT("IMC!F" & N16 & ":R" &N16),1) -> #N/A | P16: =CONCATENATE(INDEX(IMC!$F$1:$R$5,5,$O16) & " e " & INDEX(IMC!$F$1:$R$5,5,$O16+1)) -> #N/A | R16: =MATCH(F16,[3]PC!A:A,0) -> #N/A | S16: =MATCH(K16,INDIRECT("PC!E" & R16 & ":L" &R16),1) -> #N/A | T16: =CONCATENATE(INDEX([3]PC!$E$1:$M$2,1,$S16) & " e " & INDEX([3]PC!$E$1:$M$2,1,$S16+1)) -> #N/A | W16: =CONCATENATE(INDEX([3]IMC!$F$1:$R$5,5,$V16) & " e " & INDEX([3]IMC!$F$1:$R$5,5,$V16+1)) -> #VALUE! | X16: =U16*(I16*I16) -> 0 | Y16: =H16-X16 -> 0
F17: =DATEDIF(E17,D17,"M") -> 0 | G17: =YEARFRAC(D17,E17) -> 0 | J17: =I17*100 -> 0 | L17: =K17/J17 -> #DIV/0! | M17: =IF(H17>0,IF(I17>0,H17/I17^2,""),"") | N17: =MATCH(F17,[3]IMC!B:B,0) -> #N/A | O17: =MATCH(M17,INDIRECT("IMC!F" & N17 & ":R" &N17),1) -> #N/A | P17: =CONCATENATE(INDEX(IMC!$F$1:$R$5,5,$O17) & " e " & INDEX(IMC!$F$1:$R$5,5,$O17+1)) -> #N/A | R17: =MATCH(F17,[3]PC!A:A,0) -> #N/A | S17: =MATCH(K17,INDIRECT("PC!E" & R17 & ":L" &R17),1) -> #N/A | T17: =CONCATENATE(INDEX([3]PC!$E$1:$M$2,1,$S17) & " e " & INDEX([3]PC!$E$1:$M$2,1,$S17+1)) -> #N/A | W17: =CONCATENATE(INDEX([3]IMC!$F$1:$R$5,5,$V17) & " e " & INDEX([3]IMC!$F$1:$R$5,5,$V17+1)) -> #VALUE! | X17: =U17*(I17*I17) -> 0 | Y17: =H17-X17 -> 0
F18: =DATEDIF(E18,D18,"M") -> 0 | G18: =YEARFRAC(D18,E18) -> 0 | J18: =I18*100 -> 0 | L18: =K18/J18 -> #DIV/0! | M18: =IF(H18>0,IF(I18>0,H18/I18^2,""),"") | N18: =MATCH(F18,[3]IMC!B:B,0) -> #N/A | O18: =MATCH(M18,INDIRECT("IMC!F" & N18 & ":R" &N18),1) -> #N/A | P18: =CONCATENATE(INDEX(IMC!$F$1:$R$5,5,$O18) & " e " & INDEX(IMC!$F$1:$R$5,5,$O18+1)) -> #N/A | R18: =MATCH(F18,[3]PC!A:A,0) -> #N/A | S18: =MATCH(K18,INDIRECT("PC!E" & R18 & ":L" &R18),1) -> #N/A | T18: =CONCATENATE(INDEX([3]PC!$E$1:$M$2,1,$S18) & " e " & INDEX([3]PC!$E$1:$M$2,1,$S18+1)) -> #N/A | W18: =CONCATENATE(INDEX([3]IMC!$F$1:$R$5,5,$V18) & " e " & INDEX([3]IMC!$F$1:$R$5,5,$V18+1)) -> #VALUE! | X18: =U18*(I18*I18) -> 0 | Y18: =H18-X18 -> 0
F19: =DATEDIF(E19,D19,"M") -> 0 | G19: =YEARFRAC(D19,E19) -> 0 | J19: =I19*100 -> 0 | L19: =K19/J19 -> #DIV/0! | M19: =IF(H19>0,IF(I19>0,H19/I19^2,""),"") | N19: =MATCH(F19,[3]IMC!B:B,0) -> #N/A | O19: =MATCH(M19,INDIRECT("IMC!F" & N19 & ":R" &N19),1) -> #N/A | P19: =CONCATENATE(INDEX(IMC!$F$1:$R$5,5,$O19) & " e " & INDEX(IMC!$F$1:$R$5,5,$O19+1)) -> #N/A | R19: =MATCH(F19,[3]PC!A:A,0) -> #N/A | S19: =MATCH(K19,INDIRECT("PC!E" & R19 & ":L" &R19),1) -> #N/A | T19: =CONCATENATE(INDEX([3]PC!$E$1:$M$2,1,$S19) & " e " & INDEX([3]PC!$E$1:$M$2,1,$S19+1)) -> #N/A | W19: =CONCATENATE(INDEX([3]IMC!$F$1:$R$5,5,$V19) & " e " & INDEX([3]IMC!$F$1:$R$5,5,$V19+1)) -> #VALUE! | X19: =U19*(I19*I19) -> 0 | Y19: =H19-X19 -> 0
F20: =DATEDIF(E20,D20,"M") -> 0 | G20: =YEARFRAC(D20,E20) -> 0 | J20: =I20*100 -> 0 | L20: =K20/J20 -> #DIV/0! | M20: =IF(H20>0,IF(I20>0,H20/I20^2,""),"") | N20: =MATCH(F20,[3]IMC!B:B,0) -> #N/A | O20: =MATCH(M20,INDIRECT("IMC!F" & N20 & ":R" &N20),1) -> #N/A | P20: =CONCATENATE(INDEX(IMC!$F$1:$R$5,5,$O20) & " e " & INDEX(IMC!$F$1:$R$5,5,$O20+1)) -> #N/A | R20: =MATCH(F20,[3]PC!A:A,0) -> #N/A | S20: =MATCH(K20,INDIRECT("PC!E" & R20 & ":L" &R20),1) -> #N/A | T20: =CONCATENATE(INDEX([3]PC!$E$1:$M$2,1,$S20) & " e " & INDEX([3]PC!$E$1:$M$2,1,$S20+1)) -> #N/A | W20: =CONCATENATE(INDEX([3]IMC!$F$1:$R$5,5,$V20) & " e " & INDEX([3]IMC!$F$1:$R$5,5,$V20+1)) -> #VALUE! | X20: =U20*(I20*I20) -> 0 | Y20: =H20-X20 -> 0
... F92: =DATEDIF(E92,D92,"M") -> 0 | G92: =YEARFRAC(D92,E92) -> 0 | J92: =I92*100 -> 0 | L92: =K92/J92 -> #DIV/0! | M92: =IF(H92>0,IF(I92>0,H92/I92^2,""),"") | N92: =MATCH(F92,[3]IMC!B:B,0) -> #N/A | O92: =MATCH(M92,INDIRECT("IMC!F" & N92 & ":R" &N92),1) -> #N/A | P92: =CONCATENATE(INDEX(IMC!$F$1:$R$5,5,$O92) & " e " & INDEX(IMC!$F$1:$R$5,5,$O92+1)) -> #N/A | R92: =MATCH(F92,[3]PC!A:A,0) -> #N/A | S92: =MATCH(K92,INDIRECT("PC!E" & R92 & ":L" &R92),1) -> #N/A | T92: =CONCATENATE(INDEX([3]PC!$E$1:$M$2,1,$S92) & " e " & INDEX([3]PC!$E$1:$M$2,1,$S92+1)) -> #N/A | W92: =CONCATENATE(INDEX([3]IMC!$F$1:$R$5,5,$V92) & " e " & INDEX([3]IMC!$F$1:$R$5,5,$V92+1)) -> #VALUE! | X92: =U92*(I92*I92) -> 0 | Y92: =H92-X92 -> 0
F93: =DATEDIF(E93,D93,"M") -> 0 | G93: =YEARFRAC(D93,E93) -> 0 | J93: =I93*100 -> 0 | L93: =K93/J93 -> #DIV/0! | M93: =IF(H93>0,IF(I93>0,H93/I93^2,""),"") | N93: =MATCH(F93,[3]IMC!B:B,0) -> #N/A | O93: =MATCH(M93,INDIRECT("IMC!F" & N93 & ":R" &N93),1) -> #N/A | P93: =CONCATENATE(INDEX([3]IMC!$F$1:$R$5,5,$O93) & " e " & INDEX([3]IMC!$F$1:$R$5,5,$O93+1)) -> #N/A | R93: =MATCH(F93,[3]PC!A:A,0) -> #N/A | S93: =MATCH(K93,INDIRECT("PC!E" & R93 & ":L" &R93),1) -> #N/A | T93: =CONCATENATE(INDEX([3]PC!$E$1:$M$2,1,$S93) & " e " & INDEX([3]PC!$E$1:$M$2,1,$S93+1)) -> #N/A | W93: =CONCATENATE(INDEX([3]IMC!$F$1:$R$5,5,$V93) & " e " & INDEX([3]IMC!$F$1:$R$5,5,$V93+1)) -> #VALUE! | X93: =U93*(I93*I93) -> 0 | Y93: =H93-X93 -> 0
F94: =DATEDIF(E94,D94,"M") -> 0 | G94: =YEARFRAC(D94,E94) -> 0 | J94: =I94*100 -> 0 | L94: =K94/J94 -> #DIV/0! | M94: =IF(H94>0,IF(I94>0,H94/I94^2,""),"") | N94: =MATCH(F94,[3]IMC!B:B,0) -> #N/A | O94: =MATCH(M94,INDIRECT("IMC!F" & N94 & ":R" &N94),1) -> #N/A | P94: =CONCATENATE(INDEX([3]IMC!$F$1:$R$5,5,$O94) & " e " & INDEX([3]IMC!$F$1:$R$5,5,$O94+1)) -> #N/A | R94: =MATCH(F94,[3]PC!A:A,0) -> #N/A | S94: =MATCH(K94,INDIRECT("PC!E" & R94 & ":L" &R94),1) -> #N/A | T94: =CONCATENATE(INDEX([3]PC!$E$1:$M$2,1,$S94) & " e " & INDEX([3]PC!$E$1:$M$2,1,$S94+1)) -> #N/A | W94: =CONCATENATE(INDEX([3]IMC!$F$1:$R$5,5,$V94) & " e " & INDEX([3]IMC!$F$1:$R$5,5,$V94+1)) -> #VALUE! | X94: =U94*(I94*I94) -> 0 | Y94: =H94-X94 -> 0
F95: =DATEDIF(E95,D95,"M") -> 0 | G95: =YEARFRAC(D95,E95) -> 0 | J95: =I95*100 -> 0 | L95: =K95/J95 -> #DIV/0! | M95: =IF(H95>0,IF(I95>0,H95/I95^2,""),"") | N95: =MATCH(F95,[3]IMC!B:B,0) -> #N/A | O95: =MATCH(M95,INDIRECT("IMC!F" & N95 & ":R" &N95),1) -> #N/A | P95: =CONCATENATE(INDEX([3]IMC!$F$1:$R$5,5,$O95) & " e " & INDEX([3]IMC!$F$1:$R$5,5,$O95+1)) -> #N/A | R95: =MATCH(F95,[3]PC!A:A,0) -> #N/A | S95: =MATCH(K95,INDIRECT("PC!E" & R95 & ":L" &R95),1) -> #N/A | T95: =CONCATENATE(INDEX([3]PC!$E$1:$M$2,1,$S95) & " e " & INDEX([3]PC!$E$1:$M$2,1,$S95+1)) -> #N/A | W95: =CONCATENATE(INDEX([3]IMC!$F$1:$R$5,5,$V95) & " e " & INDEX([3]IMC!$F$1:$R$5,5,$V95+1)) -> #VALUE! | X95: =U95*(I95*I95) -> 0 | Y95: =H95-X95 -> 0
F96: =DATEDIF(E96,D96,"M") -> 0 | G96: =YEARFRAC(D96,E96) -> 0 | J96: =I96*100 -> 0 | L96: =K96/J96 -> #DIV/0! | M96: =IF(H96>0,IF(I96>0,H96/I96^2,""),"") | N96: =MATCH(F96,[3]IMC!B:B,0) -> #N/A | O96: =MATCH(M96,INDIRECT("IMC!F" & N96 & ":R" &N96),1) -> #N/A | P96: =CONCATENATE(INDEX([3]IMC!$F$1:$R$5,5,$O96) & " e " & INDEX([3]IMC!$F$1:$R$5,5,$O96+1)) -> #N/A | R96: =MATCH(F96,[3]PC!A:A,0) -> #N/A | S96: =MATCH(K96,INDIRECT("PC!E" & R96 & ":L" &R96),1) -> #N/A | T96: =CONCATENATE(INDEX([3]PC!$E$1:$M$2,1,$S96) & " e " & INDEX([3]PC!$E$1:$M$2,1,$S96+1)) -> #N/A | W96: =CONCATENATE(INDEX([3]IMC!$F$1:$R$5,5,$V96) & " e " & INDEX([3]IMC!$F$1:$R$5,5,$V96+1)) -> #VALUE! | X96: =U96*(I96*I96) -> 0 | Y96: =H96-X96 -> 0
F97: =DATEDIF(E97,D97,"M") -> 0 | G97: =YEARFRAC(D97,E97) -> 0 | J97: =I97*100 -> 0 | L97: =K97/J97 -> #DIV/0! | M97: =IF(H97>0,IF(I97>0,H97/I97^2,""),"") | N97: =MATCH(F97,[3]IMC!B:B,0) -> #N/A | O97: =MATCH(M97,INDIRECT("IMC!F" & N97 & ":R" &N97),1) -> #N/A | P97: =CONCATENATE(INDEX([3]IMC!$F$1:$R$5,5,$O97) & " e " & INDEX([3]IMC!$F$1:$R$5,5,$O97+1)) -> #N/A | R97: =MATCH(F97,[3]PC!A:A,0) -> #N/A | S97: =MATCH(K97,INDIRECT("PC!E" & R97 & ":L" &R97),1) -> #N/A | T97: =CONCATENATE(INDEX([3]PC!$E$1:$M$2,1,$S97) & " e " & INDEX([3]PC!$E$1:$M$2,1,$S97+1)) -> #N/A | W97: =CONCATENATE(INDEX([3]IMC!$F$1:$R$5,5,$V97) & " e " & INDEX([3]IMC!$F$1:$R$5,5,$V97+1)) -> #VALUE! | X97: =U97*(I97*I97) -> 0 | Y97: =H97-X97 -> 0
F98: =DATEDIF(E98,D98,"M") -> 0 | G98: =YEARFRAC(D98,E98) -> 0 | J98: =I98*100 -> 0 | L98: =K98/J98 -> #DIV/0! | M98: =IF(H98>0,IF(I98>0,H98/I98^2,""),"") | N98: =MATCH(F98,[3]IMC!B:B,0) -> #N/A | O98: =MATCH(M98,INDIRECT("IMC!F" & N98 & ":R" &N98),1) -> #N/A | P98: =CONCATENATE(INDEX([3]IMC!$F$1:$R$5,5,$O98) & " e " & INDEX([3]IMC!$F$1:$R$5,5,$O98+1)) -> #N/A | R98: =MATCH(F98,[3]PC!A:A,0) -> #N/A | S98: =MATCH(K98,INDIRECT("PC!E" & R98 & ":L" &R98),1) -> #N/A | T98: =CONCATENATE(INDEX([3]PC!$E$1:$M$2,1,$S98) & " e " & INDEX([3]PC!$E$1:$M$2,1,$S98+1)) -> #N/A | W98: =CONCATENATE(INDEX([3]IMC!$F$1:$R$5,5,$V98) & " e " & INDEX([3]IMC!$F$1:$R$5,5,$V98+1)) -> #VALUE! | X98: =U98*(I98*I98) -> 0 | Y98: =H98-X98 -> 0
F99: =DATEDIF(E99,D99,"M") -> 0 | G99: =YEARFRAC(D99,E99) -> 0 | J99: =I99*100 -> 0 | L99: =K99/J99 -> #DIV/0! | M99: =IF(H99>0,IF(I99>0,H99/I99^2,""),"") | N99: =MATCH(F99,[3]IMC!B:B,0) -> #N/A | O99: =MATCH(M99,INDIRECT("IMC!F" & N99 & ":R" &N99),1) -> #N/A | P99: =CONCATENATE(INDEX([3]IMC!$F$1:$R$5,5,$O99) & " e " & INDEX([3]IMC!$F$1:$R$5,5,$O99+1)) -> #N/A | R99: =MATCH(F99,[3]PC!A:A,0) -> #N/A | S99: =MATCH(K99,INDIRECT("PC!E" & R99 & ":L" &R99),1) -> #N/A | T99: =CONCATENATE(INDEX([3]PC!$E$1:$M$2,1,$S99) & " e " & INDEX([3]PC!$E$1:$M$2,1,$S99+1)) -> #N/A | W99: =CONCATENATE(INDEX([3]IMC!$F$1:$R$5,5,$V99) & " e " & INDEX([3]IMC!$F$1:$R$5,5,$V99+1)) -> #VALUE! | X99: =U99*(I99*I99) -> 0 | Y99: =H99-X99 -> 0
A100: Baixo Peso | C100: =COUNTIF(Q2:Q1000,"Baixo Peso") -> 0 | F100: =DATEDIF(E100,D100,"M") -> 0 | G100: =YEARFRAC(D100,E100) -> 0 | J100: =I100*100 -> 0 | L100: =K100/J100 -> #DIV/0! | M100: =IF(H100>0,IF(I100>0,H100/I100^2,""),"") | N100: =MATCH(F100,[3]IMC!B:B,0) -> #N/A | O100: =MATCH(M100,INDIRECT("IMC!F" & N100 & ":R" &N100),1) -> #N/A | P100: =CONCATENATE(INDEX([3]IMC!$F$1:$R$5,5,$O100) & " e " & INDEX([3]IMC!$F$1:$R$5,5,$O100+1)) -> #N/A | R100: =MATCH(F100,[3]PC!A:A,0) -> #N/A | S100: =MATCH(K100,INDIRECT("PC!E" & R100 & ":L" &R100),1) -> #N/A | T100: =CONCATENATE(INDEX([3]PC!$E$1:$M$2,1,$S100) & " e " & INDEX([3]PC!$E$1:$M$2,1,$S100+1)) -> #N/A | W100: =CONCATENATE(INDEX([3]IMC!$F$1:$R$5,5,$V100) & " e " & INDEX([3]IMC!$F$1:$R$5,5,$V100+1)) -> #VALUE! | X100: =U100*(I100*I100) -> 0 | Y100: =H100-X100 -> 0
A101: Normoponderal | C101: =COUNTIF(Q2:Q1000,"Normoponderal") -> 0 | F101: =DATEDIF(E101,D101,"M") -> 0 | G101: =YEARFRAC(D101,E101) -> 0 | J101: =I101*100 -> 0 | L101: =K101/J101 -> #DIV/0! | M101: =IF(H101>0,IF(I101>0,H101/I101^2,""),"") | N101: =MATCH(F101,[3]IMC!B:B,0) -> #N/A | O101: =MATCH(M101,INDIRECT("IMC!F" & N101 & ":R" &N101),1) -> #N/A | P101: =CONCATENATE(INDEX([3]IMC!$F$1:$R$5,5,$O101) & " e " & INDEX([3]IMC!$F$1:$R$5,5,$O101+1)) -> #N/A | R101: =MATCH(F101,[3]PC!A:A,0) -> #N/A | S101: =MATCH(K101,INDIRECT("PC!E" & R101 & ":L" &R101),1) -> #N/A | T101: =CONCATENATE(INDEX([3]PC!$E$1:$M$2,1,$S101) & " e " & INDEX([3]PC!$E$1:$M$2,1,$S101+1)) -> #N/A | W101: =CONCATENATE(INDEX([3]IMC!$F$1:$R$5,5,$V101) & " e " & INDEX([3]IMC!$F$1:$R$5,5,$V101+1)) -> #VALUE! | X101: =U101*(I101*I101) -> 0 | Y101: =H101-X101 -> 0
A102: Excesso de Peso | C102: =COUNTIF(Q2:Q1000,"Excesso de Peso") -> 0 | F102: =DATEDIF(E102,D102,"M") -> 0 | G102: =YEARFRAC(D102,E102) -> 0 | J102: =I102*100 -> 0 | L102: =K102/J102 -> #DIV/0! | M102: =IF(H102>0,IF(I102>0,H102/I102^2,""),"") | N102: =MATCH(F102,[3]IMC!B:B,0) -> #N/A | O102: =MATCH(M102,INDIRECT("IMC!F" & N102 & ":R" &N102),1) -> #N/A | P102: =CONCATENATE(INDEX([3]IMC!$F$1:$R$5,5,$O102) & " e " & INDEX([3]IMC!$F$1:$R$5,5,$O102+1)) -> #N/A | R102: =MATCH(F102,[3]PC!A:A,0) -> #N/A | S102: =MATCH(K102,INDIRECT("PC!E" & R102 & ":L" &R102),1) -> #N/A | T102: =CONCATENATE(INDEX([3]PC!$E$1:$M$2,1,$S102) & " e " & INDEX([3]PC!$E$1:$M$2,1,$S102+1)) -> #N/A | W102: =CONCATENATE(INDEX([3]IMC!$F$1:$R$5,5,$V102) & " e " & INDEX([3]IMC!$F$1:$R$5,5,$V102+1)) -> #VALUE! | X102: =U102*(I102*I102) -> 0 | Y102: =H102-X102 -> 0
A103: Obesidade | C103: =COUNTIF(Q2:Q1000,"Obesidade") -> 0 | F103: =DATEDIF(E103,D103,"M") -> 0 | G103: =YEARFRAC(D103,E103) -> 0 | J103: =I103*100 -> 0 | L103: =K103/J103 -> #DIV/0! | M103: =IF(H103>0,IF(I103>0,H103/I103^2,""),"") | N103: =MATCH(F103,[3]IMC!B:B,0) -> #N/A | O103: =MATCH(M103,INDIRECT("IMC!F" & N103 & ":R" &N103),1) -> #N/A | P103: =CONCATENATE(INDEX([3]IMC!$F$1:$R$5,5,$O103) & " e " & INDEX([3]IMC!$F$1:$R$5,5,$O103+1)) -> #N/A | R103: =MATCH(F103,[3]PC!A:A,0) -> #N/A | S103: =MATCH(K103,INDIRECT("PC!E" & R103 & ":L" &R103),1) -> #N/A | T103: =CONCATENATE(INDEX([3]PC!$E$1:$M$2,1,$S103) & " e " & INDEX([3]PC!$E$1:$M$2,1,$S103+1)) -> #N/A | W103: =CONCATENATE(INDEX([3]IMC!$F$1:$R$5,5,$V103) & " e " & INDEX([3]IMC!$F$1:$R$5,5,$V103+1)) -> #VALUE! | X103: =U103*(I103*I103) -> 0 | Y103: =H103-X103 -> 0
C104: =SUM(C100:C103) -> 0 | F104: =DATEDIF(E104,D104,"M") -> 0 | G104: =YEARFRAC(D104,E104) -> 0 | J104: =I104*100 -> 0 | L104: =K104/J104 -> #DIV/0! | M104: =IF(H104>0,IF(I104>0,H104/I104^2,""),"") | N104: =MATCH(F104,[3]IMC!B:B,0) -> #N/A | O104: =MATCH(M104,INDIRECT("IMC!F" & N104 & ":R" &N104),1) -> #N/A | P104: =CONCATENATE(INDEX([3]IMC!$F$1:$R$5,5,$O104) & " e " & INDEX([3]IMC!$F$1:$R$5,5,$O104+1)) -> #N/A | R104: =MATCH(F104,[3]PC!A:A,0) -> #N/A | S104: =MATCH(K104,INDIRECT("PC!E" & R104 & ":L" &R104),1) -> #N/A | T104: =CONCATENATE(INDEX([3]PC!$E$1:$M$2,1,$S104) & " e " & INDEX([3]PC!$E$1:$M$2,1,$S104+1)) -> #N/A | W104: =CONCATENATE(INDEX([3]IMC!$F$1:$R$5,5,$V104) & " e " & INDEX([3]IMC!$F$1:$R$5,5,$V104+1)) -> #VALUE! | X104: =U104*(I104*I104) -> 0 | Y104: =H104-X104 -> 0
F105: =DATEDIF(E105,D105,"M") -> 0 | G105: =YEARFRAC(D105,E105) -> 0 | J105: =I105*100 -> 0 | L105: =K105/J105 -> #DIV/0! | M105: =IF(H105>0,IF(I105>0,H105/I105^2,""),"") | N105: =MATCH(F105,[3]IMC!B:B,0) -> #N/A | O105: =MATCH(M105,INDIRECT("IMC!F" & N105 & ":R" &N105),1) -> #N/A | P105: =CONCATENATE(INDEX([3]IMC!$F$1:$R$5,5,$O105) & " e " & INDEX([3]IMC!$F$1:$R$5,5,$O105+1)) -> #N/A | R105: =MATCH(F105,[3]PC!A:A,0) -> #N/A | S105: =MATCH(K105,INDIRECT("PC!E" & R105 & ":L" &R105),1) -> #N/A | T105: =CONCATENATE(INDEX([3]PC!$E$1:$M$2,1,$S105) & " e " & INDEX([3]PC!$E$1:$M$2,1,$S105+1)) -> #N/A | W105: =CONCATENATE(INDEX([3]IMC!$F$1:$R$5,5,$V105) & " e " & INDEX([3]IMC!$F$1:$R$5,5,$V105+1)) -> #VALUE! | X105: =U105*(I105*I105) -> 0 | Y105: =H105-X105 -> 0
F106: =DATEDIF(E106,D106,"M") -> 0 | G106: =YEARFRAC(D106,E106) -> 0 | J106: =I106*100 -> 0 | L106: =K106/J106 -> #DIV/0! | M106: =IF(H106>0,IF(I106>0,H106/I106^2,""),"") | N106: =MATCH(F106,[3]IMC!B:B,0) -> #N/A | O106: =MATCH(M106,INDIRECT("IMC!F" & N106 & ":R" &N106),1) -> #N/A | P106: =CONCATENATE(INDEX([3]IMC!$F$1:$R$5,5,$O106) & " e " & INDEX([3]IMC!$F$1:$R$5,5,$O106+1)) -> #N/A | R106: =MATCH(F106,[3]PC!A:A,0) -> #N/A | S106: =MATCH(K106,INDIRECT("PC!E" & R106 & ":L" &R106),1) -> #N/A | T106: =CONCATENATE(INDEX([3]PC!$E$1:$M$2,1,$S106) & " e " & INDEX([3]PC!$E$1:$M$2,1,$S106+1)) -> #N/A | W106: =CONCATENATE(INDEX([3]IMC!$F$1:$R$5,5,$V106) & " e " & INDEX([3]IMC!$F$1:$R$5,5,$V106+1)) -> #VALUE! | X106: =U106*(I106*I106) -> 0 | Y106: =H106-X106 -> 0
F107: =DATEDIF(E107,D107,"M") -> 0 | G107: =YEARFRAC(D107,E107) -> 0 | J107: =I107*100 -> 0 | L107: =K107/J107 -> #DIV/0! | M107: =IF(H107>0,IF(I107>0,H107/I107^2,""),"") | N107: =MATCH(F107,[3]IMC!B:B,0) -> #N/A | O107: =MATCH(M107,INDIRECT("IMC!F" & N107 & ":R" &N107),1) -> #N/A | P107: =CONCATENATE(INDEX([3]IMC!$F$1:$R$5,5,$O107) & " e " & INDEX([3]IMC!$F$1:$R$5,5,$O107+1)) -> #N/A | R107: =MATCH(F107,[3]PC!A:A,0) -> #N/A | S107: =MATCH(K107,INDIRECT("PC!E" & R107 & ":L" &R107),1) -> #N/A | T107: =CONCATENATE(INDEX([3]PC!$E$1:$M$2,1,$S107) & " e " & INDEX([3]PC!$E$1:$M$2,1,$S107+1)) -> #N/A | W107: =CONCATENATE(INDEX([3]IMC!$F$1:$R$5,5,$V107) & " e " & INDEX([3]IMC!$F$1:$R$5,5,$V107+1)) -> #VALUE! | X107: =U107*(I107*I107) -> 0 | Y107: =H107-X107 -> 0
F108: =DATEDIF(E108,D108,"M") -> 0 | G108: =YEARFRAC(D108,E108) -> 0 | J108: =I108*100 -> 0 | L108: =K108/J108 -> #DIV/0! | M108: =IF(H108>0,IF(I108>0,H108/I108^2,""),"") | N108: =MATCH(F108,[3]IMC!B:B,0) -> #N/A | O108: =MATCH(M108,INDIRECT("IMC!F" & N108 & ":R" &N108),1) -> #N/A | P108: =CONCATENATE(INDEX([3]IMC!$F$1:$R$5,5,$O108) & " e " & INDEX([3]IMC!$F$1:$R$5,5,$O108+1)) -> #N/A | R108: =MATCH(F108,[3]PC!A:A,0) -> #N/A | S108: =MATCH(K108,INDIRECT("PC!E" & R108 & ":L" &R108),1) -> #N/A | T108: =CONCATENATE(INDEX([3]PC!$E$1:$M$2,1,$S108) & " e " & INDEX([3]PC!$E$1:$M$2,1,$S108+1)) -> #N/A | W108: =CONCATENATE(INDEX([3]IMC!$F$1:$R$5,5,$V108) & " e " & INDEX([3]IMC!$F$1:$R$5,5,$V108+1)) -> #VALUE! | X108: =U108*(I108*I108) -> 0 | Y108: =H108-X108 -> 0
F109: =DATEDIF(E109,D109,"M") -> 0 | G109: =YEARFRAC(D109,E109) -> 0 | J109: =I109*100 -> 0 | L109: =K109/J109 -> #DIV/0! | M109: =IF(H109>0,IF(I109>0,H109/I109^2,""),"") | N109: =MATCH(F109,[3]IMC!B:B,0) -> #N/A | O109: =MATCH(M109,INDIRECT("IMC!F" & N109 & ":R" &N109),1) -> #N/A | P109: =CONCATENATE(INDEX([3]IMC!$F$1:$R$5,5,$O109) & " e " & INDEX([3]IMC!$F$1:$R$5,5,$O109+1)) -> #N/A | R109: =MATCH(F109,[3]PC!A:A,0) -> #N/A | S109: =MATCH(K109,INDIRECT("PC!E" & R109 & ":L" &R109),1) -> #N/A | T109: =CONCATENATE(INDEX([3]PC!$E$1:$M$2,1,$S109) & " e " & INDEX([3]PC!$E$1:$M$2,1,$S109+1)) -> #N/A | W109: =CONCATENATE(INDEX([3]IMC!$F$1:$R$5,5,$V109) & " e " & INDEX([3]IMC!$F$1:$R$5,5,$V109+1)) -> #VALUE! | X109: =U109*(I109*I109) -> 0 | Y109: =H109-X109 -> 0
F110: =DATEDIF(E110,D110,"M") -> 0 | G110: =YEARFRAC(D110,E110) -> 0 | J110: =I110*100 -> 0 | L110: =K110/J110 -> #DIV/0! | M110: =IF(H110>0,IF(I110>0,H110/I110^2,""),"") | N110: =MATCH(F110,[3]IMC!B:B,0) -> #N/A | O110: =MATCH(M110,INDIRECT("IMC!F" & N110 & ":R" &N110),1) -> #N/A | P110: =CONCATENATE(INDEX([3]IMC!$F$1:$R$5,5,$O110) & " e " & INDEX([3]IMC!$F$1:$R$5,5,$O110+1)) -> #N/A | R110: =MATCH(F110,[3]PC!A:A,0) -> #N/A | S110: =MATCH(K110,INDIRECT("PC!E" & R110 & ":L" &R110),1) -> #N/A | T110: =CONCATENATE(INDEX([3]PC!$E$1:$M$2,1,$S110) & " e " & INDEX([3]PC!$E$1:$M$2,1,$S110+1)) -> #N/A | W110: =CONCATENATE(INDEX([3]IMC!$F$1:$R$5,5,$V110) & " e " & INDEX([3]IMC!$F$1:$R$5,5,$V110+1)) -> #VALUE! | X110: =U110*(I110*I110) -> 0 | Y110: =H110-X110 -> 0
F111: =DATEDIF(E111,D111,"M") -> 0 | G111: =YEARFRAC(D111,E111) -> 0 | J111: =I111*100 -> 0 | L111: =K111/J111 -> #DIV/0! | M111: =IF(H111>0,IF(I111>0,H111/I111^2,""),"") | N111: =MATCH(F111,[3]IMC!B:B,0) -> #N/A | O111: =MATCH(M111,INDIRECT("IMC!F" & N111 & ":R" &N111),1) -> #N/A | P111: =CONCATENATE(INDEX([3]IMC!$F$1:$R$5,5,$O111) & " e " & INDEX([3]IMC!$F$1:$R$5,5,$O111+1)) -> #N/A | R111: =MATCH(F111,[3]PC!A:A,0) -> #N/A | S111: =MATCH(K111,INDIRECT("PC!E" & R111 & ":L" &R111),1) -> #N/A | T111: =CONCATENATE(INDEX([3]PC!$E$1:$M$2,1,$S111) & " e " & INDEX([3]PC!$E$1:$M$2,1,$S111+1)) -> #N/A | W111: =CONCATENATE(INDEX([3]IMC!$F$1:$R$5,5,$V111) & " e " & INDEX([3]IMC!$F$1:$R$5,5,$V111+1)) -> #VALUE! | X111: =U111*(I111*I111) -> 0 | Y111: =H111-X111 -> 0
F112: =DATEDIF(E112,D112,"M") -> 0 | G112: =YEARFRAC(D112,E112) -> 0 | J112: =I112*100 -> 0 | L112: =K112/J112 -> #DIV/0! | M112: =IF(H112>0,IF(I112>0,H112/I112^2,""),"") | N112: =MATCH(F112,[3]IMC!B:B,0) -> #N/A | O112: =MATCH(M112,INDIRECT("IMC!F" & N112 & ":R" &N112),1) -> #N/A | P112: =CONCATENATE(INDEX([3]IMC!$F$1:$R$5,5,$O112) & " e " & INDEX([3]IMC!$F$1:$R$5,5,$O112+1)) -> #N/A | R112: =MATCH(F112,[3]PC!A:A,0) -> #N/A | S112: =MATCH(K112,INDIRECT("PC!E" & R112 & ":L" &R112),1) -> #N/A | T112: =CONCATENATE(INDEX([3]PC!$E$1:$M$2,1,$S112) & " e " & INDEX([3]PC!$E$1:$M$2,1,$S112+1)) -> #N/A | W112: =CONCATENATE(INDEX([3]IMC!$F$1:$R$5,5,$V112) & " e " & INDEX([3]IMC!$F$1:$R$5,5,$V112+1)) -> #VALUE! | X112: =U112*(I112*I112) -> 0 | Y112: =H112-X112 -> 0
F113: =DATEDIF(E113,D113,"M") -> 0 | G113: =YEARFRAC(D113,E113) -> 0 | J113: =I113*100 -> 0 | L113: =K113/J113 -> #DIV/0! | M113: =IF(H113>0,IF(I113>0,H113/I113^2,""),"") | N113: =MATCH(F113,[3]IMC!B:B,0) -> #N/A | O113: =MATCH(M113,INDIRECT("IMC!F" & N113 & ":R" &N113),1) -> #N/A | P113: =CONCATENATE(INDEX([3]IMC!$F$1:$R$5,5,$O113) & " e " & INDEX([3]IMC!$F$1:$R$5,5,$O113+1)) -> #N/A | R113: =MATCH(F113,[3]PC!A:A,0) -> #N/A | S113: =MATCH(K113,INDIRECT("PC!E" & R113 & ":L" &R113),1) -> #N/A | T113: =CONCATENATE(INDEX([3]PC!$E$1:$M$2,1,$S113) & " e " & INDEX([3]PC!$E$1:$M$2,1,$S113+1)) -> #N/A | W113: =CONCATENATE(INDEX([3]IMC!$F$1:$R$5,5,$V113) & " e " & INDEX([3]IMC!$F$1:$R$5,5,$V113+1)) -> #VALUE! | X113: =U113*(I113*I113) -> 0 | Y113: =H113-X113 -> 0
F114: =DATEDIF(E114,D114,"M") -> 0 | G114: =YEARFRAC(D114,E114) -> 0 | J114: =I114*100 -> 0 | L114: =K114/J114 -> #DIV/0! | M114: =IF(H114>0,IF(I114>0,H114/I114^2,""),"") | N114: =MATCH(F114,[3]IMC!B:B,0) -> #N/A | O114: =MATCH(M114,INDIRECT("IMC!F" & N114 & ":R" &N114),1) -> #N/A | P114: =CONCATENATE(INDEX([3]IMC!$F$1:$R$5,5,$O114) & " e " & INDEX([3]IMC!$F$1:$R$5,5,$O114+1)) -> #N/A | R114: =MATCH(F114,[3]PC!A:A,0) -> #N/A | S114: =MATCH(K114,INDIRECT("PC!E" & R114 & ":L" &R114),1) -> #N/A | T114: =CONCATENATE(INDEX([3]PC!$E$1:$M$2,1,$S114) & " e " & INDEX([3]PC!$E$1:$M$2,1,$S114+1)) -> #N/A | W114: =CONCATENATE(INDEX([3]IMC!$F$1:$R$5,5,$V114) & " e " & INDEX([3]IMC!$F$1:$R$5,5,$V114+1)) -> #VALUE! | X114: =U114*(I114*I114) -> 0 | Y114: =H114-X114 -> 0
F115: =DATEDIF(E115,D115,"M") -> 0 | G115: =YEARFRAC(D115,E115) -> 0 | J115: =I115*100 -> 0 | L115: =K115/J115 -> #DIV/0! | M115: =IF(H115>0,IF(I115>0,H115/I115^2,""),"") | N115: =MATCH(F115,[3]IMC!B:B,0) -> #N/A | O115: =MATCH(M115,INDIRECT("IMC!F" & N115 & ":R" &N115),1) -> #N/A | P115: =CONCATENATE(INDEX([3]IMC!$F$1:$R$5,5,$O115) & " e " & INDEX([3]IMC!$F$1:$R$5,5,$O115+1)) -> #N/A | R115: =MATCH(F115,[3]PC!A:A,0) -> #N/A | S115: =MATCH(K115,INDIRECT("PC!E" & R115 & ":L" &R115),1) -> #N/A | T115: =CONCATENATE(INDEX([3]PC!$E$1:$M$2,1,$S115) & " e " & INDEX([3]PC!$E$1:$M$2,1,$S115+1)) -> #N/A | W115: =CONCATENATE(INDEX([3]IMC!$F$1:$R$5,5,$V115) & " e " & INDEX([3]IMC!$F$1:$R$5,5,$V115+1)) -> #VALUE! | X115: =U115*(I115*I115) -> 0 | Y115: =H115-X115 -> 0
F116: =DATEDIF(E116,D116,"M") -> 0 | G116: =YEARFRAC(D116,E116) -> 0 | J116: =I116*100 -> 0 | L116: =K116/J116 -> #DIV/0! | M116: =IF(H116>0,IF(I116>0,H116/I116^2,""),"") | N116: =MATCH(F116,[3]IMC!B:B,0) -> #N/A | O116: =MATCH(M116,INDIRECT("IMC!F" & N116 & ":R" &N116),1) -> #N/A | P116: =CONCATENATE(INDEX([3]IMC!$F$1:$R$5,5,$O116) & " e " & INDEX([3]IMC!$F$1:$R$5,5,$O116+1)) -> #N/A | R116: =MATCH(F116,[3]PC!A:A,0) -> #N/A | S116: =MATCH(K116,INDIRECT("PC!E" & R116 & ":L" &R116),1) -> #N/A | T116: =CONCATENATE(INDEX([3]PC!$E$1:$M$2,1,$S116) & " e " & INDEX([3]PC!$E$1:$M$2,1,$S116+1)) -> #N/A | W116: =CONCATENATE(INDEX([3]IMC!$F$1:$R$5,5,$V116) & " e " & INDEX([3]IMC!$F$1:$R$5,5,$V116+1)) -> #VALUE! | X116: =U116*(I116*I116) -> 0 | Y116: =H116-X116 -> 0
F117: =DATEDIF(E117,D117,"M") -> 0 | G117: =YEARFRAC(D117,E117) -> 0 | J117: =I117*100 -> 0 | L117: =K117/J117 -> #DIV/0! | M117: =IF(H117>0,IF(I117>0,H117/I117^2,""),"") | N117: =MATCH(F117,[3]IMC!B:B,0) -> #N/A | O117: =MATCH(M117,INDIRECT("IMC!F" & N117 & ":R" &N117),1) -> #N/A | P117: =CONCATENATE(INDEX([3]IMC!$F$1:$R$5,5,$O117) & " e " & INDEX([3]IMC!$F$1:$R$5,5,$O117+1)) -> #N/A | R117: =MATCH(F117,[3]PC!A:A,0) -> #N/A | S117: =MATCH(K117,INDIRECT("PC!E" & R117 & ":L" &R117),1) -> #N/A | T117: =CONCATENATE(INDEX([3]PC!$E$1:$M$2,1,$S117) & " e " & INDEX([3]PC!$E$1:$M$2,1,$S117+1)) -> #N/A | W117: =CONCATENATE(INDEX([3]IMC!$F$1:$R$5,5,$V117) & " e " & INDEX([3]IMC!$F$1:$R$5,5,$V117+1)) -> #VALUE! | X117: =U117*(I117*I117) -> 0 | Y117: =H117-X117 -> 0
F118: =DATEDIF(E118,D118,"M") -> 0 | G118: =YEARFRAC(D118,E118) -> 0 | J118: =I118*100 -> 0 | M118: =IF(H118>0,IF(I118>0,H118/I118^2,""),"") | N118: =MATCH(F118,[3]IMC!B:B,0) -> #N/A | O118: =MATCH(M118,INDIRECT("IMC!F" & N118 & ":R" &N118),1) -> #N/A | P118: =CONCATENATE(INDEX([3]IMC!$F$1:$R$5,5,$O118) & " e " & INDEX([3]IMC!$F$1:$R$5,5,$O118+1)) -> #N/A | R118: =MATCH(F118,[3]PC!A:A,0) -> #N/A | S118: =MATCH(K118,INDIRECT("PC!E" & R118 & ":L" &R118),1) -> #N/A | T118: =CONCATENATE(INDEX([3]PC!$E$1:$M$2,1,$S118) & " e " & INDEX([3]PC!$E$1:$M$2,1,$S118+1)) -> #N/A | W118: =CONCATENATE(INDEX([3]IMC!$F$1:$R$5,5,$V118) & " e " & INDEX([3]IMC!$F$1:$R$5,5,$V118+1)) -> #VALUE! | X118: =U118*(I118*I118) -> 0 | Y118: =H118-X118 -> 0
F119: =meses(E119,D119) -> #NAME? | G119: =YEARFRAC(D119,E119) -> 0 | J119: =I119*100 -> 0 | M119: =IF(H119>0,IF(I119>0,H119/I119^2,""),"") | N119: =MATCH(F119,[3]IMC!B:B,0) -> #NAME? | O119: =MATCH(M119,INDIRECT("IMC!F" & N119 & ":R" &N119),1) -> #NAME? | P119: =CONCATENATE(INDEX([3]IMC!$F$1:$R$5,5,$O119) & " e " & INDEX([3]IMC!$F$1:$R$5,5,$O119+1)) -> #NAME? | R119: =MATCH(F119,[3]PC!A:A,0) -> #NAME? | S119: =MATCH(K119,INDIRECT("PC!E" & R119 & ":L" &R119),1) -> #NAME? | T119: =CONCATENATE(INDEX([3]PC!$E$1:$M$2,1,$S119) & " e " & INDEX([3]PC!$E$1:$M$2,1,$S119+1)) -> #NAME? | W119: =CONCATENATE(INDEX([3]IMC!$F$1:$R$5,5,$V119) & " e " & INDEX([3]IMC!$F$1:$R$5,5,$V119+1)) -> #VALUE! | X119: =U119*(I119*I119) -> 0 | Y119: =H119-X119 -> 0
F120: =meses(E120,D120) -> #NAME? | G120: =YEARFRAC(D120,E120) -> 0 | J120: =I120*100 -> 0 | M120: =IF(H120>0,IF(I120>0,H120/I120^2,""),"") | N120: =MATCH(F120,[3]IMC!B:B,0) -> #NAME? | O120: =MATCH(M120,INDIRECT("IMC!F" & N120 & ":R" &N120),1) -> #NAME? | P120: =CONCATENATE(INDEX([3]IMC!$F$1:$R$5,5,$O120) & " e " & INDEX([3]IMC!$F$1:$R$5,5,$O120+1)) -> #NAME? | R120: =MATCH(F120,[3]PC!A:A,0) -> #NAME? | S120: =MATCH(K120,INDIRECT("PC!E" & R120 & ":L" &R120),1) -> #NAME? | T120: =CONCATENATE(INDEX([3]PC!$E$1:$M$2,1,$S120) & " e " & INDEX([3]PC!$E$1:$M$2,1,$S120+1)) -> #NAME? | W120: =CONCATENATE(INDEX([3]IMC!$F$1:$R$5,5,$V120) & " e " & INDEX([3]IMC!$F$1:$R$5,5,$V120+1)) -> #VALUE! | X120: =U120*(I120*I120) -> 0 | Y120: =H120-X120 -> 0
F121: =meses(E121,D121) -> #NAME? | G121: =YEARFRAC(D121,E121) -> 0 | J121: =I121*100 -> 0 | M121: =IF(H121>0,IF(I121>0,H121/I121^2,""),"") | N121: =MATCH(F121,[3]IMC!B:B,0) -> #NAME? | O121: =MATCH(M121,INDIRECT("IMC!F" & N121 & ":R" &N121),1) -> #NAME? | P121: =CONCATENATE(INDEX([3]IMC!$F$1:$R$5,5,$O121) & " e " & INDEX([3]IMC!$F$1:$R$5,5,$O121+1)) -> #NAME? | R121: =MATCH(F121,[3]PC!A:A,0) -> #NAME? | S121: =MATCH(K121,INDIRECT("PC!E" & R121 & ":L" &R121),1) -> #NAME? | T121: =CONCATENATE(INDEX([3]PC!$E$1:$M$2,1,$S121) & " e " & INDEX([3]PC!$E$1:$M$2,1,$S121+1)) -> #NAME? | W121: =CONCATENATE(INDEX([3]IMC!$F$1:$R$5,5,$V121) & " e " & INDEX([3]IMC!$F$1:$R$5,5,$V121+1)) -> #VALUE! | X121: =U121*(I121*I121) -> 0 | Y121: =H121-X121 -> 0
F122: =meses(E122,D122) -> #NAME? | G122: =YEARFRAC(D122,E122) -> 0 | J122: =I122*100 -> 0 | M122: =IF(H122>0,IF(I122>0,H122/I122^2,""),"") | N122: =MATCH(F122,[3]IMC!B:B,0) -> #NAME? | O122: =MATCH(M122,INDIRECT("IMC!F" & N122 & ":R" &N122),1) -> #NAME? | P122: =CONCATENATE(INDEX([3]IMC!$F$1:$R$5,5,$O122) & " e " & INDEX([3]IMC!$F$1:$R$5,5,$O122+1)) -> #NAME? | R122: =MATCH(F122,[3]PC!A:A,0) -> #NAME? | S122: =MATCH(K122,INDIRECT("PC!E" & R122 & ":L" &R122),1) -> #NAME? | T122: =CONCATENATE(INDEX([3]PC!$E$1:$M$2,1,$S122) & " e " & INDEX([3]PC!$E$1:$M$2,1,$S122+1)) -> #NAME? | W122: =CONCATENATE(INDEX([3]IMC!$F$1:$R$5,5,$V122) & " e " & INDEX([3]IMC!$F$1:$R$5,5,$V122+1)) -> #VALUE! | X122: =U122*(I122*I122) -> 0 | Y122: =H122-X122 -> 0
F123: =meses(E123,D123) -> #NAME? | G123: =YEARFRAC(D123,E123) -> 0 | J123: =I123*100 -> 0 | M123: =IF(H123>0,IF(I123>0,H123/I123^2,""),"") | N123: =MATCH(F123,[3]IMC!B:B,0) -> #NAME? | O123: =MATCH(M123,INDIRECT("IMC!F" & N123 & ":R" &N123),1) -> #NAME? | P123: =CONCATENATE(INDEX([3]IMC!$F$1:$R$5,5,$O123) & " e " & INDEX([3]IMC!$F$1:$R$5,5,$O123+1)) -> #NAME? | R123: =MATCH(F123,[3]PC!A:A,0) -> #NAME? | S123: =MATCH(K123,INDIRECT("PC!E" & R123 & ":L" &R123),1) -> #NAME? | T123: =CONCATENATE(INDEX([3]PC!$E$1:$M$2,1,$S123) & " e " & INDEX([3]PC!$E$1:$M$2,1,$S123+1)) -> #NAME? | W123: =CONCATENATE(INDEX([3]IMC!$F$1:$R$5,5,$V123) & " e " & INDEX([3]IMC!$F$1:$R$5,5,$V123+1)) -> #VALUE! | X123: =U123*(I123*I123) -> 0 | Y123: =H123-X123 -> 0
F124: =meses(E124,D124) -> #NAME? | G124: =YEARFRAC(D124,E124) -> 0 | J124: =I124*100 -> 0 | M124: =IF(H124>0,IF(I124>0,H124/I124^2,""),"") | N124: =MATCH(F124,[3]IMC!B:B,0) -> #NAME? | O124: =MATCH(M124,INDIRECT("IMC!F" & N124 & ":R" &N124),1) -> #NAME? | P124: =CONCATENATE(INDEX([3]IMC!$F$1:$R$5,5,$O124) & " e " & INDEX([3]IMC!$F$1:$R$5,5,$O124+1)) -> #NAME? | R124: =MATCH(F124,[3]PC!A:A,0) -> #NAME? | S124: =MATCH(K124,INDIRECT("PC!E" & R124 & ":L" &R124),1) -> #NAME? | T124: =CONCATENATE(INDEX([3]PC!$E$1:$M$2,1,$S124) & " e " & INDEX([3]PC!$E$1:$M$2,1,$S124+1)) -> #NAME? | W124: =CONCATENATE(INDEX([3]IMC!$F$1:$R$5,5,$V124) & " e " & INDEX([3]IMC!$F$1:$R$5,5,$V124+1)) -> #VALUE! | X124: =U124*(I124*I124) -> 0 | Y124: =H124-X124 -> 0
F125: =meses(E125,D125) -> #NAME? | G125: =YEARFRAC(D125,E125) -> 0 | J125: =I125*100 -> 0 | M125: =IF(H125>0,IF(I125>0,H125/I125^2,""),"") | N125: =MATCH(F125,[3]IMC!B:B,0) -> #NAME? | O125: =MATCH(M125,INDIRECT("IMC!F" & N125 & ":R" &N125),1) -> #NAME? | P125: =CONCATENATE(INDEX([3]IMC!$F$1:$R$5,5,$O125) & " e " & INDEX([3]IMC!$F$1:$R$5,5,$O125+1)) -> #NAME? | R125: =MATCH(F125,[3]PC!A:A,0) -> #NAME? | S125: =MATCH(K125,INDIRECT("PC!E" & R125 & ":L" &R125),1) -> #NAME? | T125: =CONCATENATE(INDEX([3]PC!$E$1:$M$2,1,$S125) & " e " & INDEX([3]PC!$E$1:$M$2,1,$S125+1)) -> #NAME? | W125: =CONCATENATE(INDEX([3]IMC!$F$1:$R$5,5,$V125) & " e " & INDEX([3]IMC!$F$1:$R$5,5,$V125+1)) -> #VALUE! | X125: =U125*(I125*I125) -> 0 | Y125: =H125-X125 -> 0
F126: =meses(E126,D126) -> #NAME? | G126: =YEARFRAC(D126,E126) -> 0 | J126: =I126*100 -> 0 | M126: =IF(H126>0,IF(I126>0,H126/I126^2,""),"") | N126: =MATCH(F126,[3]IMC!B:B,0) -> #NAME? | O126: =MATCH(M126,INDIRECT("IMC!F" & N126 & ":R" &N126),1) -> #NAME? | P126: =CONCATENATE(INDEX([3]IMC!$F$1:$R$5,5,$O126) & " e " & INDEX([3]IMC!$F$1:$R$5,5,$O126+1)) -> #NAME? | R126: =MATCH(F126,[3]PC!A:A,0) -> #NAME? | S126: =MATCH(K126,INDIRECT("PC!E" & R126 & ":L" &R126),1) -> #NAME? | T126: =CONCATENATE(INDEX([3]PC!$E$1:$M$2,1,$S126) & " e " & INDEX([3]PC!$E$1:$M$2,1,$S126+1)) -> #NAME? | W126: =CONCATENATE(INDEX([3]IMC!$F$1:$R$5,5,$V126) & " e " & INDEX([3]IMC!$F$1:$R$5,5,$V126+1)) -> #VALUE! | X126: =U126*(I126*I126) -> 0 | Y126: =H126-X126 -> 0
F127: =meses(E127,D127) -> #NAME? | G127: =YEARFRAC(D127,E127) -> 0 | J127: =I127*100 -> 0 | M127: =IF(H127>0,IF(I127>0,H127/I127^2,""),"") | N127: =MATCH(F127,[3]IMC!B:B,0) -> #NAME? | O127: =MATCH(M127,INDIRECT("IMC!F" & N127 & ":R" &N127),1) -> #NAME? | P127: =CONCATENATE(INDEX([3]IMC!$F$1:$R$5,5,$O127) & " e " & INDEX([3]IMC!$F$1:$R$5,5,$O127+1)) -> #NAME? | R127: =MATCH(F127,[3]PC!A:A,0) -> #NAME? | S127: =MATCH(K127,INDIRECT("PC!E" & R127 & ":L" &R127),1) -> #NAME? | T127: =CONCATENATE(INDEX([3]PC!$E$1:$M$2,1,$S127) & " e " & INDEX([3]PC!$E$1:$M$2,1,$S127+1)) -> #NAME? | W127: =CONCATENATE(INDEX([3]IMC!$F$1:$R$5,5,$V127) & " e " & INDEX([3]IMC!$F$1:$R$5,5,$V127+1)) -> #VALUE! | X127: =U127*(I127*I127) -> 0 | Y127: =H127-X127 -> 0
F128: =meses(E128,D128) -> #NAME? | G128: =YEARFRAC(D128,E128) -> 0 | J128: =I128*100 -> 0 | M128: =IF(H128>0,IF(I128>0,H128/I128^2,""),"") | N128: =MATCH(F128,[3]IMC!B:B,0) -> #NAME? | O128: =MATCH(M128,INDIRECT("IMC!F" & N128 & ":R" &N128),1) -> #NAME? | P128: =CONCATENATE(INDEX([3]IMC!$F$1:$R$5,5,$O128) & " e " & INDEX([3]IMC!$F$1:$R$5,5,$O128+1)) -> #NAME? | R128: =MATCH(F128,[3]PC!A:A,0) -> #NAME? | S128: =MATCH(K128,INDIRECT("PC!E" & R128 & ":L" &R128),1) -> #NAME? | T128: =CONCATENATE(INDEX([3]PC!$E$1:$M$2,1,$S128) & " e " & INDEX([3]PC!$E$1:$M$2,1,$S128+1)) -> #NAME? | W128: =CONCATENATE(INDEX([3]IMC!$F$1:$R$5,5,$V128) & " e " & INDEX([3]IMC!$F$1:$R$5,5,$V128+1)) -> #VALUE! | X128: =U128*(I128*I128) -> 0 | Y128: =H128-X128 -> 0
F129: =meses(E129,D129) -> #NAME? | G129: =YEARFRAC(D129,E129) -> 0 | J129: =I129*100 -> 0 | M129: =IF(H129>0,IF(I129>0,H129/I129^2,""),"") | N129: =MATCH(F129,[3]IMC!B:B,0) -> #NAME? | O129: =MATCH(M129,INDIRECT("IMC!F" & N129 & ":R" &N129),1) -> #NAME? | P129: =CONCATENATE(INDEX([3]IMC!$F$1:$R$5,5,$O129) & " e " & INDEX([3]IMC!$F$1:$R$5,5,$O129+1)) -> #NAME? | R129: =MATCH(F129,[3]PC!A:A,0) -> #NAME? | S129: =MATCH(K129,INDIRECT("PC!E" & R129 & ":L" &R129),1) -> #NAME? | T129: =CONCATENATE(INDEX([3]PC!$E$1:$M$2,1,$S129) & " e " & INDEX([3]PC!$E$1:$M$2,1,$S129+1)) -> #NAME? | W129: =CONCATENATE(INDEX([3]IMC!$F$1:$R$5,5,$V129) & " e " & INDEX([3]IMC!$F$1:$R$5,5,$V129+1)) -> #VALUE! | X129: =U129*(I129*I129) -> 0 | Y129: =H129-X129 -> 0
F130: =meses(E130,D130) -> #NAME? | G130: =YEARFRAC(D130,E130) -> 0 | J130: =I130*100 -> 0 | M130: =IF(H130>0,IF(I130>0,H130/I130^2,""),"") | N130: =MATCH(F130,[3]IMC!B:B,0) -> #NAME? | O130: =MATCH(M130,INDIRECT("IMC!F" & N130 & ":R" &N130),1) -> #NAME? | P130: =CONCATENATE(INDEX([3]IMC!$F$1:$R$5,5,$O130) & " e " & INDEX([3]IMC!$F$1:$R$5,5,$O130+1)) -> #NAME? | R130: =MATCH(F130,[3]PC!A:A,0) -> #NAME? | S130: =MATCH(K130,INDIRECT("PC!E" & R130 & ":L" &R130),1) -> #NAME? | T130: =CONCATENATE(INDEX([3]PC!$E$1:$M$2,1,$S130) & " e " & INDEX([3]PC!$E$1:$M$2,1,$S130+1)) -> #NAME? | W130: =CONCATENATE(INDEX([3]IMC!$F$1:$R$5,5,$V130) & " e " & INDEX([3]IMC!$F$1:$R$5,5,$V130+1)) -> #VALUE! | X130: =U130*(I130*I130) -> 0 | Y130: =H130-X130 -> 0
... F287: =meses(E287,D287) -> #NAME? | G287: =YEARFRAC(D287,E287) -> 0 | J287: =I287*100 -> 0 | M287: =IF(H287>0,IF(I287>0,H287/I287^2,""),"") | N287: =MATCH(F287,[3]IMC!B:B,0) -> #NAME? | O287: =MATCH(M287,INDIRECT("IMC!F" & N287 & ":R" &N287),1) -> #NAME? | P287: =CONCATENATE(INDEX([3]IMC!$F$1:$R$5,5,$O287) & " e " & INDEX([3]IMC!$F$1:$R$5,5,$O287+1)) -> #NAME? | R287: =MATCH(F287,[3]PC!A:A,0) -> #NAME? | S287: =MATCH(K287,INDIRECT("PC!E" & R287 & ":L" &R287),1) -> #NAME? | T287: =CONCATENATE(INDEX([3]PC!$E$1:$M$2,1,$S287) & " e " & INDEX([3]PC!$E$1:$M$2,1,$S287+1)) -> #NAME? | W287: =CONCATENATE(INDEX([3]IMC!$F$1:$R$5,5,$V287) & " e " & INDEX([3]IMC!$F$1:$R$5,5,$V287+1)) -> #VALUE! | X287: =U287*(I287*I287) -> 0 | Y287: =H287-X287 -> 0
F288: =meses(E288,D288) -> #NAME? | G288: =YEARFRAC(D288,E288) -> 0 | M288: =IF(H288>0,IF(I288>0,H288/I288^2,""),"") | N288: =MATCH(F288,[3]IMC!B:B,0) -> #NAME? | O288: =MATCH(M288,INDIRECT("IMC!F" & N288 & ":R" &N288),1) -> #NAME? | P288: =CONCATENATE(INDEX([3]IMC!$F$1:$R$5,5,$O288) & " e " & INDEX([3]IMC!$F$1:$R$5,5,$O288+1)) -> #NAME? | R288: =MATCH(F288,[3]PC!A:A,0) -> #NAME? | S288: =MATCH(K288,INDIRECT("PC!E" & R288 & ":L" &R288),1) -> #NAME? | T288: =CONCATENATE(INDEX([3]PC!$E$1:$M$2,1,$S288) & " e " & INDEX([3]PC!$E$1:$M$2,1,$S288+1)) -> #NAME? | W288: =CONCATENATE(INDEX([3]IMC!$F$1:$R$5,5,$V288) & " e " & INDEX([3]IMC!$F$1:$R$5,5,$V288+1)) -> #VALUE! | X288: =U288*(I288*I288) -> 0 | Y288: =H288-X288 -> 0
F289: =meses(E289,D289) -> #NAME? | G289: =YEARFRAC(D289,E289) -> 0 | M289: =IF(H289>0,IF(I289>0,H289/I289^2,""),"") | N289: =MATCH(F289,[3]IMC!B:B,0) -> #NAME? | O289: =MATCH(M289,INDIRECT("IMC!F" & N289 & ":R" &N289),1) -> #NAME? | P289: =CONCATENATE(INDEX([3]IMC!$F$1:$R$5,5,$O289) & " e " & INDEX([3]IMC!$F$1:$R$5,5,$O289+1)) -> #NAME? | R289: =MATCH(F289,[3]PC!A:A,0) -> #NAME? | S289: =MATCH(K289,INDIRECT("PC!E" & R289 & ":L" &R289),1) -> #NAME? | T289: =CONCATENATE(INDEX([3]PC!$E$1:$M$2,1,$S289) & " e " & INDEX([3]PC!$E$1:$M$2,1,$S289+1)) -> #NAME? | W289: =CONCATENATE(INDEX([3]IMC!$F$1:$R$5,5,$V289) & " e " & INDEX([3]IMC!$F$1:$R$5,5,$V289+1)) -> #VALUE! | X289: =U289*(I289*I289) -> 0 | Y289: =H289-X289 -> 0
F290: =meses(E290,D290) -> #NAME? | G290: =YEARFRAC(D290,E290) -> 0 | M290: =IF(H290>0,IF(I290>0,H290/I290^2,""),"") | N290: =MATCH(F290,[3]IMC!B:B,0) -> #NAME? | O290: =MATCH(M290,INDIRECT("IMC!F" & N290 & ":R" &N290),1) -> #NAME? | P290: =CONCATENATE(INDEX([3]IMC!$F$1:$R$5,5,$O290) & " e " & INDEX([3]IMC!$F$1:$R$5,5,$O290+1)) -> #NAME? | R290: =MATCH(F290,[3]PC!A:A,0) -> #NAME? | S290: =MATCH(K290,INDIRECT("PC!E" & R290 & ":L" &R290),1) -> #NAME? | T290: =CONCATENATE(INDEX([3]PC!$E$1:$M$2,1,$S290) & " e " & INDEX([3]PC!$E$1:$M$2,1,$S290+1)) -> #NAME? | W290: =CONCATENATE(INDEX([3]IMC!$F$1:$R$5,5,$V290) & " e " & INDEX([3]IMC!$F$1:$R$5,5,$V290+1)) -> #VALUE! | X290: =U290*(I290*I290) -> 0 | Y290: =H290-X290 -> 0
F291: =meses(E291,D291) -> #NAME? | G291: =YEARFRAC(D291,E291) -> 0 | M291: =IF(H291>0,IF(I291>0,H291/I291^2,""),"") | N291: =MATCH(F291,[3]IMC!B:B,0) -> #NAME? | O291: =MATCH(M291,INDIRECT("IMC!F" & N291 & ":R" &N291),1) -> #NAME? | P291: =CONCATENATE(INDEX([3]IMC!$F$1:$R$5,5,$O291) & " e " & INDEX([3]IMC!$F$1:$R$5,5,$O291+1)) -> #NAME? | R291: =MATCH(F291,[3]PC!A:A,0) -> #NAME? | S291: =MATCH(K291,INDIRECT("PC!E" & R291 & ":L" &R291),1) -> #NAME? | T291: =CONCATENATE(INDEX([3]PC!$E$1:$M$2,1,$S291) & " e " & INDEX([3]PC!$E$1:$M$2,1,$S291+1)) -> #NAME? | W291: =CONCATENATE(INDEX([3]IMC!$F$1:$R$5,5,$V291) & " e " & INDEX([3]IMC!$F$1:$R$5,5,$V291+1)) -> #VALUE! | X291: =U291*(I291*I291) -> 0 | Y291: =H291-X291 -> 0
F292: =meses(E292,D292) -> #NAME? | G292: =YEARFRAC(D292,E292) -> 0 | M292: =IF(H292>0,IF(I292>0,H292/I292^2,""),"") | N292: =MATCH(F292,[3]IMC!B:B,0) -> #NAME? | O292: =MATCH(M292,INDIRECT("IMC!F" & N292 & ":R" &N292),1) -> #NAME? | P292: =CONCATENATE(INDEX([3]IMC!$F$1:$R$5,5,$O292) & " e " & INDEX([3]IMC!$F$1:$R$5,5,$O292+1)) -> #NAME? | R292: =MATCH(F292,[3]PC!A:A,0) -> #NAME? | S292: =MATCH(K292,INDIRECT("PC!E" & R292 & ":L" &R292),1) -> #NAME? | T292: =CONCATENATE(INDEX([3]PC!$E$1:$M$2,1,$S292) & " e " & INDEX([3]PC!$E$1:$M$2,1,$S292+1)) -> #NAME? | W292: =CONCATENATE(INDEX([3]IMC!$F$1:$R$5,5,$V292) & " e " & INDEX([3]IMC!$F$1:$R$5,5,$V292+1)) -> #VALUE! | X292: =U292*(I292*I292) -> 0 | Y292: =H292-X292 -> 0
F293: =meses(E293,D293) -> #NAME? | G293: =YEARFRAC(D293,E293) -> 0 | M293: =IF(H293>0,IF(I293>0,H293/I293^2,""),"") | N293: =MATCH(F293,[3]IMC!B:B,0) -> #NAME? | O293: =MATCH(M293,INDIRECT("IMC!F" & N293 & ":R" &N293),1) -> #NAME? | P293: =CONCATENATE(INDEX([3]IMC!$F$1:$R$5,5,$O293) & " e " & INDEX([3]IMC!$F$1:$R$5,5,$O293+1)) -> #NAME? | R293: =MATCH(F293,[3]PC!A:A,0) -> #NAME? | S293: =MATCH(K293,INDIRECT("PC!E" & R293 & ":L" &R293),1) -> #NAME? | T293: =CONCATENATE(INDEX([3]PC!$E$1:$M$2,1,$S293) & " e " & INDEX([3]PC!$E$1:$M$2,1,$S293+1)) -> #NAME? | W293: =CONCATENATE(INDEX([3]IMC!$F$1:$R$5,5,$V293) & " e " & INDEX([3]IMC!$F$1:$R$5,5,$V293+1)) -> #VALUE! | X293: =U293*(I293*I293) -> 0 | Y293: =H293-X293 -> 0
F294: =meses(E294,D294) -> #NAME? | G294: =YEARFRAC(D294,E294) -> 0 | M294: =IF(H294>0,IF(I294>0,H294/I294^2,""),"") | N294: =MATCH(F294,[3]IMC!B:B,0) -> #NAME? | O294: =MATCH(M294,INDIRECT("IMC!F" & N294 & ":R" &N294),1) -> #NAME? | P294: =CONCATENATE(INDEX([3]IMC!$F$1:$R$5,5,$O294) & " e " & INDEX([3]IMC!$F$1:$R$5,5,$O294+1)) -> #NAME? | R294: =MATCH(F294,[3]PC!A:A,0) -> #NAME? | S294: =MATCH(K294,INDIRECT("PC!E" & R294 & ":L" &R294),1) -> #NAME? | T294: =CONCATENATE(INDEX([3]PC!$E$1:$M$2,1,$S294) & " e " & INDEX([3]PC!$E$1:$M$2,1,$S294+1)) -> #NAME? | W294: =CONCATENATE(INDEX([3]IMC!$F$1:$R$5,5,$V294) & " e " & INDEX([3]IMC!$F$1:$R$5,5,$V294+1)) -> #VALUE! | X294: =U294*(I294*I294) -> 0 | Y294: =H294-X294 -> 0
F295: =meses(E295,D295) -> #NAME? | G295: =YEARFRAC(D295,E295) -> 0 | M295: =IF(H295>0,IF(I295>0,H295/I295^2,""),"") | N295: =MATCH(F295,[3]IMC!B:B,0) -> #NAME? | O295: =MATCH(M295,INDIRECT("IMC!F" & N295 & ":R" &N295),1) -> #NAME? | P295: =CONCATENATE(INDEX([3]IMC!$F$1:$R$5,5,$O295) & " e " & INDEX([3]IMC!$F$1:$R$5,5,$O295+1)) -> #NAME? | R295: =MATCH(F295,[3]PC!A:A,0) -> #NAME? | S295: =MATCH(K295,INDIRECT("PC!E" & R295 & ":L" &R295),1) -> #NAME? | T295: =CONCATENATE(INDEX([3]PC!$E$1:$M$2,1,$S295) & " e " & INDEX([3]PC!$E$1:$M$2,1,$S295+1)) -> #NAME? | W295: =CONCATENATE(INDEX([3]IMC!$F$1:$R$5,5,$V295) & " e " & INDEX([3]IMC!$F$1:$R$5,5,$V295+1)) -> #VALUE! | X295: =U295*(I295*I295) -> 0 | Y295: =H295-X295 -> 0
F296: =meses(E296,D296) -> #NAME? | G296: =YEARFRAC(D296,E296) -> 0 | M296: =IF(H296>0,IF(I296>0,H296/I296^2,""),"") | N296: =MATCH(F296,[3]IMC!B:B,0) -> #NAME? | O296: =MATCH(M296,INDIRECT("IMC!F" & N296 & ":R" &N296),1) -> #NAME? | P296: =CONCATENATE(INDEX([3]IMC!$F$1:$R$5,5,$O296) & " e " & INDEX([3]IMC!$F$1:$R$5,5,$O296+1)) -> #NAME? | R296: =MATCH(F296,[3]PC!A:A,0) -> #NAME? | S296: =MATCH(K296,INDIRECT("PC!E" & R296 & ":L" &R296),1) -> #NAME? | T296: =CONCATENATE(INDEX([3]PC!$E$1:$M$2,1,$S296) & " e " & INDEX([3]PC!$E$1:$M$2,1,$S296+1)) -> #NAME? | W296: =CONCATENATE(INDEX([3]IMC!$F$1:$R$5,5,$V296) & " e " & INDEX([3]IMC!$F$1:$R$5,5,$V296+1)) -> #VALUE! | X296: =U296*(I296*I296) -> 0 | Y296: =H296-X296 -> 0
F297: =meses(E297,D297) -> #NAME? | G297: =YEARFRAC(D297,E297) -> 0 | M297: =IF(H297>0,IF(I297>0,H297/I297^2,""),"") | N297: =MATCH(F297,[3]IMC!B:B,0) -> #NAME? | O297: =MATCH(M297,INDIRECT("IMC!F" & N297 & ":R" &N297),1) -> #NAME? | P297: =CONCATENATE(INDEX([3]IMC!$F$1:$R$5,5,$O297) & " e " & INDEX([3]IMC!$F$1:$R$5,5,$O297+1)) -> #NAME? | R297: =MATCH(F297,[3]PC!A:A,0) -> #NAME? | S297: =MATCH(K297,INDIRECT("PC!E" & R297 & ":L" &R297),1) -> #NAME? | T297: =CONCATENATE(INDEX([3]PC!$E$1:$M$2,1,$S297) & " e " & INDEX([3]PC!$E$1:$M$2,1,$S297+1)) -> #NAME? | W297: =CONCATENATE(INDEX([3]IMC!$F$1:$R$5,5,$V297) & " e " & INDEX([3]IMC!$F$1:$R$5,5,$V297+1)) -> #VALUE! | X297: =U297*(I297*I297) -> 0 | Y297: =H297-X297 -> 0
F298: =meses(E298,D298) -> #NAME? | G298: =YEARFRAC(D298,E298) -> 0 | M298: =IF(H298>0,IF(I298>0,H298/I298^2,""),"") | N298: =MATCH(F298,[3]IMC!B:B,0) -> #NAME? | O298: =MATCH(M298,INDIRECT("IMC!F" & N298 & ":R" &N298),1) -> #NAME? | P298: =CONCATENATE(INDEX([3]IMC!$F$1:$R$5,5,$O298) & " e " & INDEX([3]IMC!$F$1:$R$5,5,$O298+1)) -> #NAME? | R298: =MATCH(F298,[3]PC!A:A,0) -> #NAME? | S298: =MATCH(K298,INDIRECT("PC!E" & R298 & ":L" &R298),1) -> #NAME? | T298: =CONCATENATE(INDEX([3]PC!$E$1:$M$2,1,$S298) & " e " & INDEX([3]PC!$E$1:$M$2,1,$S298+1)) -> #NAME? | W298: =CONCATENATE(INDEX([3]IMC!$F$1:$R$5,5,$V298) & " e " & INDEX([3]IMC!$F$1:$R$5,5,$V298+1)) -> #VALUE! | X298: =U298*(I298*I298) -> 0 | Y298: =H298-X298 -> 0
F299: =meses(E299,D299) -> #NAME? | G299: =YEARFRAC(D299,E299) -> 0 | M299: =IF(H299>0,IF(I299>0,H299/I299^2,""),"") | N299: =MATCH(F299,[3]IMC!B:B,0) -> #NAME? | O299: =MATCH(M299,INDIRECT("IMC!F" & N299 & ":R" &N299),1) -> #NAME? | P299: =CONCATENATE(INDEX([3]IMC!$F$1:$R$5,5,$O299) & " e " & INDEX([3]IMC!$F$1:$R$5,5,$O299+1)) -> #NAME? | R299: =MATCH(F299,[3]PC!A:A,0) -> #NAME? | S299: =MATCH(K299,INDIRECT("PC!E" & R299 & ":L" &R299),1) -> #NAME? | T299: =CONCATENATE(INDEX([3]PC!$E$1:$M$2,1,$S299) & " e " & INDEX([3]PC!$E$1:$M$2,1,$S299+1)) -> #NAME? | W299: =CONCATENATE(INDEX([3]IMC!$F$1:$R$5,5,$V299) & " e " & INDEX([3]IMC!$F$1:$R$5,5,$V299+1)) -> #VALUE! | X299: =U299*(I299*I299) -> 0 | Y299: =H299-X299 -> 0
... F362: =meses(E362,D362) -> #NAME? | G362: =YEARFRAC(D362,E362) -> 0 | M362: =IF(H362>0,IF(I362>0,H362/I362^2,""),"") | N362: =MATCH(F362,[3]IMC!B:B,0) -> #NAME? | O362: =MATCH(M362,INDIRECT("IMC!F" & N362 & ":R" &N362),1) -> #NAME? | P362: =CONCATENATE(INDEX([3]IMC!$F$1:$R$5,5,$O362) & " e " & INDEX([3]IMC!$F$1:$R$5,5,$O362+1)) -> #NAME? | R362: =MATCH(F362,[3]PC!A:A,0) -> #NAME? | S362: =MATCH(K362,INDIRECT("PC!E" & R362 & ":L" &R362),1) -> #NAME? | T362: =CONCATENATE(INDEX([3]PC!$E$1:$M$2,1,$S362) & " e " & INDEX([3]PC!$E$1:$M$2,1,$S362+1)) -> #NAME? | W362: =CONCATENATE(INDEX([3]IMC!$F$1:$R$5,5,$V362) & " e " & INDEX([3]IMC!$F$1:$R$5,5,$V362+1)) -> #VALUE! | X362: =U362*(I362*I362) -> 0 | Y362: =H362-X362 -> 0
F363: =meses(E363,D363) -> #NAME? | G363: =AnosMeses(E363,D363) -> #NAME? | M363: =IF(H363>0,IF(I363>0,H363/I363^2,""),"") | N363: =MATCH(F363,[3]IMC!B:B,0) -> #NAME? | O363: =MATCH(M363,INDIRECT("IMC!F" & N363 & ":R" &N363),1) -> #NAME? | P363: =CONCATENATE(INDEX([3]IMC!$F$1:$R$5,5,$O363) & " e " & INDEX([3]IMC!$F$1:$R$5,5,$O363+1)) -> #NAME? | R363: =MATCH(F363,[3]PC!A:A,0) -> #NAME? | S363: =MATCH(K363,INDIRECT("PC!E" & R363 & ":L" &R363),1) -> #NAME? | T363: =CONCATENATE(INDEX([3]PC!$E$1:$M$2,1,$S363) & " e " & INDEX([3]PC!$E$1:$M$2,1,$S363+1)) -> #NAME? | W363: =CONCATENATE(INDEX([3]IMC!$F$1:$R$5,5,$V363) & " e " & INDEX([3]IMC!$F$1:$R$5,5,$V363+1)) -> #VALUE! | X363: =U363*(I363*I363) -> 0 | Y363: =H363-X363 -> 0
F364: =meses(E364,D364) -> #NAME? | G364: =AnosMeses(E364,D364) -> #NAME? | M364: =IF(H364>0,IF(I364>0,H364/I364^2,""),"") | N364: =MATCH(F364,[3]IMC!B:B,0) -> #NAME? | O364: =MATCH(M364,INDIRECT("IMC!F" & N364 & ":R" &N364),1) -> #NAME? | P364: =CONCATENATE(INDEX([3]IMC!$F$1:$R$5,5,$O364) & " e " & INDEX([3]IMC!$F$1:$R$5,5,$O364+1)) -> #NAME? | R364: =MATCH(F364,[3]PC!A:A,0) -> #NAME? | S364: =MATCH(K364,INDIRECT("PC!E" & R364 & ":L" &R364),1) -> #NAME? | T364: =CONCATENATE(INDEX([3]PC!$E$1:$M$2,1,$S364) & " e " & INDEX([3]PC!$E$1:$M$2,1,$S364+1)) -> #NAME? | W364: =CONCATENATE(INDEX([3]IMC!$F$1:$R$5,5,$V364) & " e " & INDEX([3]IMC!$F$1:$R$5,5,$V364+1)) -> #VALUE! | X364: =U364*(I364*I364) -> 0 | Y364: =H364-X364 -> 0
F365: =meses(E365,D365) -> #NAME? | G365: =AnosMeses(E365,D365) -> #NAME? | M365: =IF(H365>0,IF(I365>0,H365/I365^2,""),"") | N365: =MATCH(F365,[3]IMC!B:B,0) -> #NAME? | O365: =MATCH(M365,INDIRECT("IMC!F" & N365 & ":R" &N365),1) -> #NAME? | P365: =CONCATENATE(INDEX([3]IMC!$F$1:$R$5,5,$O365) & " e " & INDEX([3]IMC!$F$1:$R$5,5,$O365+1)) -> #NAME? | R365: =MATCH(F365,[3]PC!A:A,0) -> #NAME? | S365: =MATCH(K365,INDIRECT("PC!E" & R365 & ":L" &R365),1) -> #NAME? | T365: =CONCATENATE(INDEX([3]PC!$E$1:$M$2,1,$S365) & " e " & INDEX([3]PC!$E$1:$M$2,1,$S365+1)) -> #NAME? | W365: =CONCATENATE(INDEX([3]IMC!$F$1:$R$5,5,$V365) & " e " & INDEX([3]IMC!$F$1:$R$5,5,$V365+1)) -> #VALUE! | X365: =U365*(I365*I365) -> 0 | Y365: =H365-X365 -> 0
F366: =meses(E366,D366) -> #NAME? | G366: =AnosMeses(E366,D366) -> #NAME? | M366: =IF(H366>0,IF(I366>0,H366/I366^2,""),"") | N366: =MATCH(F366,[3]IMC!B:B,0) -> #NAME? | O366: =MATCH(M366,INDIRECT("IMC!F" & N366 & ":R" &N366),1) -> #NAME? | P366: =CONCATENATE(INDEX([3]IMC!$F$1:$R$5,5,$O366) & " e " & INDEX([3]IMC!$F$1:$R$5,5,$O366+1)) -> #NAME? | R366: =MATCH(F366,[3]PC!A:A,0) -> #NAME? | S366: =MATCH(K366,INDIRECT("PC!E" & R366 & ":L" &R366),1) -> #NAME? | T366: =CONCATENATE(INDEX([3]PC!$E$1:$M$2,1,$S366) & " e " & INDEX([3]PC!$E$1:$M$2,1,$S366+1)) -> #NAME? | W366: =CONCATENATE(INDEX([3]IMC!$F$1:$R$5,5,$V366) & " e " & INDEX([3]IMC!$F$1:$R$5,5,$V366+1)) -> #VALUE! | X366: =U366*(I366*I366) -> 0 | Y366: =H366-X366 -> 0
F367: =meses(E367,D367) -> #NAME? | G367: =AnosMeses(E367,D367) -> #NAME? | M367: =IF(H367>0,IF(I367>0,H367/I367^2,""),"") | N367: =MATCH(F367,[3]IMC!B:B,0) -> #NAME? | O367: =MATCH(M367,INDIRECT("IMC!F" & N367 & ":R" &N367),1) -> #NAME? | P367: =CONCATENATE(INDEX([3]IMC!$F$1:$R$5,5,$O367) & " e " & INDEX([3]IMC!$F$1:$R$5,5,$O367+1)) -> #NAME? | R367: =MATCH(F367,[3]PC!A:A,0) -> #NAME? | S367: =MATCH(K367,INDIRECT("PC!E" & R367 & ":L" &R367),1) -> #NAME? | T367: =CONCATENATE(INDEX([3]PC!$E$1:$M$2,1,$S367) & " e " & INDEX([3]PC!$E$1:$M$2,1,$S367+1)) -> #NAME? | W367: =CONCATENATE(INDEX([3]IMC!$F$1:$R$5,5,$V367) & " e " & INDEX([3]IMC!$F$1:$R$5,5,$V367+1)) -> #VALUE! | X367: =U367*(I367*I367) -> 0 | Y367: =H367-X367 -> 0
F368: =meses(E368,D368) -> #NAME? | G368: =AnosMeses(E368,D368) -> #NAME? | M368: =IF(H368>0,IF(I368>0,H368/I368^2,""),"") | N368: =MATCH(F368,[3]IMC!B:B,0) -> #NAME? | O368: =MATCH(M368,INDIRECT("IMC!F" & N368 & ":R" &N368),1) -> #NAME? | P368: =CONCATENATE(INDEX([3]IMC!$F$1:$R$5,5,$O368) & " e " & INDEX([3]IMC!$F$1:$R$5,5,$O368+1)) -> #NAME? | R368: =MATCH(F368,[3]PC!A:A,0) -> #NAME? | S368: =MATCH(K368,INDIRECT("PC!E" & R368 & ":L" &R368),1) -> #NAME? | T368: =CONCATENATE(INDEX([3]PC!$E$1:$M$2,1,$S368) & " e " & INDEX([3]PC!$E$1:$M$2,1,$S368+1)) -> #NAME? | W368: =CONCATENATE(INDEX([3]IMC!$F$1:$R$5,5,$V368) & " e " & INDEX([3]IMC!$F$1:$R$5,5,$V368+1)) -> #VALUE! | X368: =U368*(I368*I368) -> 0 | Y368: =H368-X368 -> 0
F369: =meses(E369,D369) -> #NAME? | G369: =AnosMeses(E369,D369) -> #NAME? | M369: =IF(H369>0,IF(I369>0,H369/I369^2,""),"") | N369: =MATCH(F369,[3]IMC!B:B,0) -> #NAME? | O369: =MATCH(M369,INDIRECT("IMC!F" & N369 & ":R" &N369),1) -> #NAME? | P369: =CONCATENATE(INDEX([3]IMC!$F$1:$R$5,5,$O369) & " e " & INDEX([3]IMC!$F$1:$R$5,5,$O369+1)) -> #NAME? | R369: =MATCH(F369,[3]PC!A:A,0) -> #NAME? | S369: =MATCH(K369,INDIRECT("PC!E" & R369 & ":L" &R369),1) -> #NAME? | T369: =CONCATENATE(INDEX([3]PC!$E$1:$M$2,1,$S369) & " e " & INDEX([3]PC!$E$1:$M$2,1,$S369+1)) -> #NAME? | W369: =CONCATENATE(INDEX([3]IMC!$F$1:$R$5,5,$V369) & " e " & INDEX([3]IMC!$F$1:$R$5,5,$V369+1)) -> #VALUE! | X369: =U369*(I369*I369) -> 0 | Y369: =H369-X369 -> 0
F370: =meses(E370,D370) -> #NAME? | G370: =AnosMeses(E370,D370) -> #NAME? | M370: =IF(H370>0,IF(I370>0,H370/I370^2,""),"") | N370: =MATCH(F370,[3]IMC!B:B,0) -> #NAME? | O370: =MATCH(M370,INDIRECT("IMC!F" & N370 & ":R" &N370),1) -> #NAME? | P370: =CONCATENATE(INDEX([3]IMC!$F$1:$R$5,5,$O370) & " e " & INDEX([3]IMC!$F$1:$R$5,5,$O370+1)) -> #NAME? | R370: =MATCH(F370,[3]PC!A:A,0) -> #NAME? | S370: =MATCH(K370,INDIRECT("PC!E" & R370 & ":L" &R370),1) -> #NAME? | T370: =CONCATENATE(INDEX([3]PC!$E$1:$M$2,1,$S370) & " e " & INDEX([3]PC!$E$1:$M$2,1,$S370+1)) -> #NAME? | W370: =CONCATENATE(INDEX([3]IMC!$F$1:$R$5,5,$V370) & " e " & INDEX([3]IMC!$F$1:$R$5,5,$V370+1)) -> #VALUE! | X370: =U370*(I370*I370) -> 0 | Y370: =H370-X370 -> 0
F371: =meses(E371,D371) -> #NAME? | G371: =AnosMeses(E371,D371) -> #NAME? | M371: =IF(H371>0,IF(I371>0,H371/I371^2,""),"") | N371: =MATCH(F371,[3]IMC!B:B,0) -> #NAME? | O371: =MATCH(M371,INDIRECT("IMC!F" & N371 & ":R" &N371),1) -> #NAME? | P371: =CONCATENATE(INDEX([3]IMC!$F$1:$R$5,5,$O371) & " e " & INDEX([3]IMC!$F$1:$R$5,5,$O371+1)) -> #NAME? | R371: =MATCH(F371,[3]PC!A:A,0) -> #NAME? | S371: =MATCH(K371,INDIRECT("PC!E" & R371 & ":L" &R371),1) -> #NAME? | T371: =CONCATENATE(INDEX([3]PC!$E$1:$M$2,1,$S371) & " e " & INDEX([3]PC!$E$1:$M$2,1,$S371+1)) -> #NAME? | W371: =CONCATENATE(INDEX([3]IMC!$F$1:$R$5,5,$V371) & " e " & INDEX([3]IMC!$F$1:$R$5,5,$V371+1)) -> #VALUE! | X371: =U371*(I371*I371) -> 0 | Y371: =H371-X371 -> 0
F372: =meses(E372,D372) -> #NAME? | G372: =AnosMeses(E372,D372) -> #NAME? | M372: =IF(H372>0,IF(I372>0,H372/I372^2,""),"") | N372: =MATCH(F372,[3]IMC!B:B,0) -> #NAME? | O372: =MATCH(M372,INDIRECT("IMC!F" & N372 & ":R" &N372),1) -> #NAME? | P372: =CONCATENATE(INDEX([3]IMC!$F$1:$R$5,5,$O372) & " e " & INDEX([3]IMC!$F$1:$R$5,5,$O372+1)) -> #NAME? | R372: =MATCH(F372,[3]PC!A:A,0) -> #NAME? | S372: =MATCH(K372,INDIRECT("PC!E" & R372 & ":L" &R372),1) -> #NAME? | T372: =CONCATENATE(INDEX([3]PC!$E$1:$M$2,1,$S372) & " e " & INDEX([3]PC!$E$1:$M$2,1,$S372+1)) -> #NAME? | W372: =CONCATENATE(INDEX([3]IMC!$F$1:$R$5,5,$V372) & " e " & INDEX([3]IMC!$F$1:$R$5,5,$V372+1)) -> #VALUE! | X372: =U372*(I372*I372) -> 0 | Y372: =H372-X372 -> 0
F373: =meses(E373,D373) -> #NAME? | G373: =AnosMeses(E373,D373) -> #NAME? | M373: =IF(H373>0,IF(I373>0,H373/I373^2,""),"") | N373: =MATCH(F373,[3]IMC!B:B,0) -> #NAME? | O373: =MATCH(M373,INDIRECT("IMC!F" & N373 & ":R" &N373),1) -> #NAME? | P373: =CONCATENATE(INDEX([3]IMC!$F$1:$R$5,5,$O373) & " e " & INDEX([3]IMC!$F$1:$R$5,5,$O373+1)) -> #NAME? | R373: =MATCH(F373,[3]PC!A:A,0) -> #NAME? | S373: =MATCH(K373,INDIRECT("PC!E" & R373 & ":L" &R373),1) -> #NAME? | T373: =CONCATENATE(INDEX([3]PC!$E$1:$M$2,1,$S373) & " e " & INDEX([3]PC!$E$1:$M$2,1,$S373+1)) -> #NAME? | W373: =CONCATENATE(INDEX([3]IMC!$F$1:$R$5,5,$V373) & " e " & INDEX([3]IMC!$F$1:$R$5,5,$V373+1)) -> #VALUE! | X373: =U373*(I373*I373) -> 0 | Y373: =H373-X373 -> 0
F374: =meses(E374,D374) -> #NAME? | G374: =AnosMeses(E374,D374) -> #NAME? | M374: =IF(H374>0,IF(I374>0,H374/I374^2,""),"") | N374: =MATCH(F374,[3]IMC!B:B,0) -> #NAME? | O374: =MATCH(M374,INDIRECT("IMC!F" & N374 & ":R" &N374),1) -> #NAME? | P374: =CONCATENATE(INDEX([3]IMC!$F$1:$R$5,5,$O374) & " e " & INDEX([3]IMC!$F$1:$R$5,5,$O374+1)) -> #NAME? | R374: =MATCH(F374,[3]PC!A:A,0) -> #NAME? | S374: =MATCH(K374,INDIRECT("PC!E" & R374 & ":L" &R374),1) -> #NAME? | T374: =CONCATENATE(INDEX([3]PC!$E$1:$M$2,1,$S374) & " e " & INDEX([3]PC!$E$1:$M$2,1,$S374+1)) -> #NAME? | W374: =CONCATENATE(INDEX([3]IMC!$F$1:$R$5,5,$V374) & " e " & INDEX([3]IMC!$F$1:$R$5,5,$V374+1)) -> #VALUE! | X374: =U374*(I374*I374) -> 0 | Y374: =H374-X374 -> 0
... F904: =meses(E904,D904) -> #NAME? | G904: =AnosMeses(E904,D904) -> #NAME? | M904: =IF(H904>0,IF(I904>0,H904/I904^2,""),"") | N904: =MATCH(F904,[3]IMC!B:B,0) -> #NAME? | O904: =MATCH(M904,INDIRECT("IMC!F" & N904 & ":R" &N904),1) -> #NAME? | P904: =CONCATENATE(INDEX([3]IMC!$F$1:$R$5,5,$O904) & " e " & INDEX([3]IMC!$F$1:$R$5,5,$O904+1)) -> #NAME? | R904: =MATCH(F904,[3]PC!A:A,0) -> #NAME? | S904: =MATCH(K904,INDIRECT("PC!E" & R904 & ":L" &R904),1) -> #NAME? | T904: =CONCATENATE(INDEX([3]PC!$E$1:$M$2,1,$S904) & " e " & INDEX([3]PC!$E$1:$M$2,1,$S904+1)) -> #NAME? | W904: =CONCATENATE(INDEX([3]IMC!$F$1:$R$5,5,$V904) & " e " & INDEX([3]IMC!$F$1:$R$5,5,$V904+1)) -> #VALUE! | X904: =U904*(I904*I904) -> 0 | Y904: =H904-X904 -> 0
F905: =meses(E905,D905) -> #NAME? | G905: =AnosMeses(E905,D905) -> #NAME? | M905: =IF(H905>0,IF(I905>0,H905/I905^2,""),"") | N905: =MATCH(F905,[3]IMC!B:B,0) -> #NAME? | O905: =MATCH(M905,INDIRECT("IMC!F" & N905 & ":R" &N905),1) -> #NAME? | P905: =CONCATENATE(INDEX([3]IMC!$F$1:$R$5,5,$O905) & " e " & INDEX([3]IMC!$F$1:$R$5,5,$O905+1)) -> #NAME? | R905: =MATCH(F905,[3]PC!A:A,0) -> #NAME? | S905: =MATCH(K905,INDIRECT("PC!E" & R905 & ":L" &R905),1) -> #NAME? | T905: =CONCATENATE(INDEX([3]PC!$E$1:$M$2,1,$S905) & " e " & INDEX([3]PC!$E$1:$M$2,1,$S905+1)) -> #NAME?
F906: =meses(E906,D906) -> #NAME? | G906: =AnosMeses(E906,D906) -> #NAME? | M906: =IF(H906>0,IF(I906>0,H906/I906^2,""),"") | N906: =MATCH(F906,[3]IMC!B:B,0) -> #NAME? | O906: =MATCH(M906,INDIRECT("IMC!F" & N906 & ":R" &N906),1) -> #NAME? | P906: =CONCATENATE(INDEX([3]IMC!$F$1:$R$5,5,$O906) & " e " & INDEX([3]IMC!$F$1:$R$5,5,$O906+1)) -> #NAME? | R906: =MATCH(F906,[3]PC!A:A,0) -> #NAME? | S906: =MATCH(K906,INDIRECT("PC!E" & R906 & ":L" &R906),1) -> #NAME? | T906: =CONCATENATE(INDEX([3]PC!$E$1:$M$2,1,$S906) & " e " & INDEX([3]PC!$E$1:$M$2,1,$S906+1)) -> #NAME?
F907: =meses(E907,D907) -> #NAME? | G907: =AnosMeses(E907,D907) -> #NAME? | M907: =IF(H907>0,IF(I907>0,H907/I907^2,""),"") | N907: =MATCH(F907,[3]IMC!B:B,0) -> #NAME? | O907: =MATCH(M907,INDIRECT("IMC!F" & N907 & ":R" &N907),1) -> #NAME? | P907: =CONCATENATE(INDEX([3]IMC!$F$1:$R$5,5,$O907) & " e " & INDEX([3]IMC!$F$1:$R$5,5,$O907+1)) -> #NAME? | R907: =MATCH(F907,[3]PC!A:A,0) -> #NAME? | S907: =MATCH(K907,INDIRECT("PC!E" & R907 & ":L" &R907),1) -> #NAME? | T907: =CONCATENATE(INDEX([3]PC!$E$1:$M$2,1,$S907) & " e " & INDEX([3]PC!$E$1:$M$2,1,$S907+1)) -> #NAME?
F908: =meses(E908,D908) -> #NAME? | G908: =AnosMeses(E908,D908) -> #NAME? | M908: =IF(H908>0,IF(I908>0,H908/I908^2,""),"") | N908: =MATCH(F908,[3]IMC!B:B,0) -> #NAME? | O908: =MATCH(M908,INDIRECT("IMC!F" & N908 & ":R" &N908),1) -> #NAME? | P908: =CONCATENATE(INDEX([3]IMC!$F$1:$R$5,5,$O908) & " e " & INDEX([3]IMC!$F$1:$R$5,5,$O908+1)) -> #NAME? | R908: =MATCH(F908,[3]PC!A:A,0) -> #NAME? | S908: =MATCH(K908,INDIRECT("PC!E" & R908 & ":L" &R908),1) -> #NAME? | T908: =CONCATENATE(INDEX([3]PC!$E$1:$M$2,1,$S908) & " e " & INDEX([3]PC!$E$1:$M$2,1,$S908+1)) -> #NAME?
F909: =meses(E909,D909) -> #NAME? | G909: =AnosMeses(E909,D909) -> #NAME? | M909: =IF(H909>0,IF(I909>0,H909/I909^2,""),"") | N909: =MATCH(F909,[3]IMC!B:B,0) -> #NAME? | O909: =MATCH(M909,INDIRECT("IMC!F" & N909 & ":R" &N909),1) -> #NAME? | P909: =CONCATENATE(INDEX([3]IMC!$F$1:$R$5,5,$O909) & " e " & INDEX([3]IMC!$F$1:$R$5,5,$O909+1)) -> #NAME? | R909: =MATCH(F909,[3]PC!A:A,0) -> #NAME? | S909: =MATCH(K909,INDIRECT("PC!E" & R909 & ":L" &R909),1) -> #NAME? | T909: =CONCATENATE(INDEX([3]PC!$E$1:$M$2,1,$S909) & " e " & INDEX([3]PC!$E$1:$M$2,1,$S909+1)) -> #NAME?
F910: =meses(E910,D910) -> #NAME? | G910: =AnosMeses(E910,D910) -> #NAME? | M910: =IF(H910>0,IF(I910>0,H910/I910^2,""),"") | N910: =MATCH(F910,[3]IMC!B:B,0) -> #NAME? | O910: =MATCH(M910,INDIRECT("IMC!F" & N910 & ":R" &N910),1) -> #NAME? | P910: =CONCATENATE(INDEX([3]IMC!$F$1:$R$5,5,$O910) & " e " & INDEX([3]IMC!$F$1:$R$5,5,$O910+1)) -> #NAME? | R910: =MATCH(F910,[3]PC!A:A,0) -> #NAME? | S910: =MATCH(K910,INDIRECT("PC!E" & R910 & ":L" &R910),1) -> #NAME? | T910: =CONCATENATE(INDEX([3]PC!$E$1:$M$2,1,$S910) & " e " & INDEX([3]PC!$E$1:$M$2,1,$S910+1)) -> #NAME?
F911: =meses(E911,D911) -> #NAME? | G911: =AnosMeses(E911,D911) -> #NAME? | M911: =IF(H911>0,IF(I911>0,H911/I911^2,""),"") | N911: =MATCH(F911,[3]IMC!B:B,0) -> #NAME? | O911: =MATCH(M911,INDIRECT("IMC!F" & N911 & ":R" &N911),1) -> #NAME? | P911: =CONCATENATE(INDEX([3]IMC!$F$1:$R$5,5,$O911) & " e " & INDEX([3]IMC!$F$1:$R$5,5,$O911+1)) -> #NAME? | R911: =MATCH(F911,[3]PC!A:A,0) -> #NAME? | S911: =MATCH(K911,INDIRECT("PC!E" & R911 & ":L" &R911),1) -> #NAME? | T911: =CONCATENATE(INDEX([3]PC!$E$1:$M$2,1,$S911) & " e " & INDEX([3]PC!$E$1:$M$2,1,$S911+1)) -> #NAME?
F912: =meses(E912,D912) -> #NAME? | G912: =AnosMeses(E912,D912) -> #NAME? | M912: =IF(H912>0,IF(I912>0,H912/I912^2,""),"") | N912: =MATCH(F912,[3]IMC!B:B,0) -> #NAME? | O912: =MATCH(M912,INDIRECT("IMC!F" & N912 & ":R" &N912),1) -> #NAME? | P912: =CONCATENATE(INDEX([3]IMC!$F$1:$R$5,5,$O912) & " e " & INDEX([3]IMC!$F$1:$R$5,5,$O912+1)) -> #NAME? | R912: =MATCH(F912,[3]PC!A:A,0) -> #NAME? | S912: =MATCH(K912,INDIRECT("PC!E" & R912 & ":L" &R912),1) -> #NAME? | T912: =CONCATENATE(INDEX([3]PC!$E$1:$M$2,1,$S912) & " e " & INDEX([3]PC!$E$1:$M$2,1,$S912+1)) -> #NAME?

Sheet IMC_
A1: BMI-for-age BOYS
A2: 5 to 19 years (percentiles)
A4: Percentiles (BMI in kg/m2)
A5: Year: Month | B5: Month | C5: L | D5: M | E5: S | F5: <1st | G5: 1st | H5: 3rd | I5: 5th | J5: 15th | K5: 25th | L5: 50th | M5: 75th | N5: 85th | O5: 95th | P5: 97th | Q5: 99th | R5: >99
A6: 2: 0 | B6: 24 | C6: -0.6187 | D6: 16.0189 | E6: 0.07785 | F6: -1 | G6: 13.5 | H6: 13.9 | I6: 14.2 | J6: 14.8 | K6: 15.2 | L6: 16 | M6: 16.9 | N6: 17.4 | O6: 18.3 | P6: 18.7 | Q6: 19.4 | R6: 9999
A7: 2: 1 | B7: 25 | C7: -0.584 | D7: 15.98 | E7: 0.07792 | F7: -1 | G7: 13.5 | H7: 13.9 | I7: 14.1 | J7: 14.8 | K7: 15.2 | L7: 16 | M7: 16.9 | N7: 17.4 | O7: 18.3 | P7: 18.6 | Q7: 19.4 | R7: 9999
A8: 2: 2 | B8: 26 | C8: -0.5497 | D8: 15.9414 | E8: 0.078 | F8: -1 | G8: 13.4 | H8: 13.8 | I8: 14.1 | J8: 14.7 | K8: 15.1 | L8: 15.9 | M8: 16.8 | N8: 17.3 | O8: 18.2 | P8: 18.6 | Q8: 19.3 | R8: 9999
A9: 2: 3 | B9: 27 | C9: -0.5166 | D9: 15.9036 | E9: 0.07808 | F9: -1 | G9: 13.4 | H9: 13.8 | I9: 14 | J9: 14.7 | K9: 15.1 | L9: 15.9 | M9: 16.8 | N9: 17.3 | O9: 18.2 | P9: 18.5 | Q9: 19.2 | R9: 9999
A10: 2: 4 | B10: 28 | C10: -0.485 | D10: 15.8667 | E10: 0.07818 | F10: -1 | G10: 13.3 | H10: 13.8 | I10: 14 | J10: 14.7 | K10: 15.1 | L10: 15.9 | M10: 16.7 | N10: 17.2 | O10: 18.1 | P10: 18.5 | Q10: 19.2 | R10: 9999
A11: 2: 5 | B11: 29 | C11: -0.4552 | D11: 15.8306 | E11: 0.07829 | F11: -1 | G11: 13.3 | H11: 13.7 | I11: 14 | J11: 14.6 | K11: 15 | L11: 15.8 | M11: 16.7 | N11: 17.2 | O11: 18.1 | P11: 18.4 | Q11: 19.1 | R11: 9999
A12: 2: 6 | B12: 30 | C12: -0.4274 | D12: 15.7953 | E12: 0.07841 | F12: -1 | G12: 13.3 | H12: 13.7 | I12: 13.9 | J12: 14.6 | K12: 15 | L12: 15.8 | M12: 16.7 | N12: 17.2 | O12: 18 | P12: 18.4 | Q12: 19.1 | R12: 9999
A13: 2: 7 | B13: 31 | C13: -0.4016 | D13: 15.7606 | E13: 0.07854 | F13: -1 | G13: 13.2 | H13: 13.7 | I13: 13.9 | J13: 14.5 | K13: 15 | L13: 15.8 | M13: 16.6 | N13: 17.1 | O13: 18 | P13: 18.4 | Q13: 19.1 | R13: 9999
A14: 2: 8 | B14: 32 | C14: -0.3782 | D14: 15.7267 | E14: 0.07867 | F14: -1 | G14: 13.2 | H14: 13.6 | I14: 13.9 | J14: 14.5 | K14: 14.9 | L14: 15.7 | M14: 16.6 | N14: 17.1 | O14: 18 | P14: 18.3 | Q14: 19 | R14: 9999
A15: 2: 9 | B15: 33 | C15: -0.3572 | D15: 15.6934 | E15: 0.07882 | F15: -1 | G15: 13.1 | H15: 13.6 | I15: 13.8 | J15: 14.5 | K15: 14.9 | L15: 15.7 | M15: 16.6 | N15: 17 | O15: 17.9 | P15: 18.3 | Q15: 19 | R15: 9999
A16: 2:10 | B16: 34 | C16: -0.3388 | D16: 15.661 | E16: 0.07897 | F16: -1 | G16: 13.1 | H16: 13.5 | I16: 13.8 | J16: 14.4 | K16: 14.9 | L16: 15.7 | M16: 16.5 | N16: 17 | O16: 17.9 | P16: 18.2 | Q16: 18.9 | R16: 9999
A17: 2:11 | B17: 35 | C17: -0.3231 | D17: 15.6294 | E17: 0.07914 | F17: -1 | G17: 13.1 | H17: 13.5 | I17: 13.8 | J17: 14.4 | K17: 14.8 | L17: 15.6 | M17: 16.5 | N17: 17 | O17: 17.9 | P17: 18.2 | Q17: 18.9 | R17: 9999
... A210: 19: 0 | B210: 228 | C210: -0.8419 | D210: 22.1883 | E210: 0.12948 | F210: -1 | G210: 17 | H210: 17.8 | I210: 18.2 | J210: 19.5 | K210: 20.4 | L210: 22.2 | M210: 24.3 | N210: 25.6 | O210: 28.1 | P210: 29.1 | Q210: 31.4 | R210: 9999

Sheet _PEDIATRIA
A1: Turma | B1: Nº | C1: Nome | D1: Data Medição | E1: Data Nascimento | F1: Meses | G1: Anos Meses | H1: Peso | I1: Altura | J1: Altura (cm) | K1: PC | L1: PC/alt | M1: IMC | N1: Linha | O1: Coluna | P1: Perc IMC | Q1: Classificação IMC | R1: Linha | S1: Coluna | T1: Perc cint | U1: IMC ideal | V1: Coluna pretendida | W1: Perc IMC ideal | X1: Peso ideal | Y1: Peso a perder | AA1: <1st | AB1: 1st | AC1: 3rd | AD1: 5th | AE1: 15th | AF1: 25th | AG1: 50th | AH1: 75th | AI1: 85th | AJ1: 95th | AK1: 97th | AL1: 99th | AM1: >99
D2: 44714 | E2: 40568 | F2: =DATEDIF(E2,D2,"M") -> 136 | G2: =YEARFRAC(D2,E2) -> 11.352778 | H2: 35 | I2: 1.36 | L2: =K2/J2 -> #DIV/0! | M2: =IF(H2>0,IF(I2>0,H2/I2^2,""),"") -> 18.92301 | N2: =MATCH(F2,[4]IMC!B:B,0) -> 118 | O2: =MATCH(M2,INDIRECT("IMC!F" & N2 & ":R" &N2),1) -> 7 | P2: =CONCATENATE(INDEX([4]IMC!$F$1:$R$5,5,$O2) & " e " & INDEX([4]IMC!$F$1:$R$5,5,$O2+1)) -> 50th e 75th | R2: =MATCH(F2,[4]PC!A:A,0) -> 24 | S2: =MATCH(K2,INDIRECT("PC!E" & R2 & ":L" &R2),1) -> #REF! | T2: =CONCATENATE(INDEX([4]PC!$E$1:$M$2,1,$S2) & " e " & INDEX([4]PC!$E$1:$M$2,1,$S2+1)) -> #REF! | V2: =MATCH(U2,INDIRECT("IMC!F" & N2 & ":R" &N2),1) -> 1 | W2: =CONCATENATE(INDEX([4]IMC!$F$1:$R$5,5,$V2) & " e " & INDEX([4]IMC!$F$1:$R$5,5,$V2+1)) -> <1st e 1st | X2: =U2*(I2*I2) -> 0 | Y2: =H2-X2 -> 35 | AA2: =VLOOKUP(F2,[4]IMC!$B$6:$R$210,5,FALSE) -> -1 | AB2: =VLOOKUP(F2,[4]IMC!$B$6:$R$210,6,FALSE) -> 13.8 | AC2: =VLOOKUP(F2,[4]IMC!$B$6:$R$210,7,FALSE) -> 14.3 | AD2: =VLOOKUP(F2,[4]IMC!$B$6:$R$210,8,FALSE) -> 14.6 | AE2: =VLOOKUP(F2,[4]IMC!$B$6:$R$210,9,FALSE) -> 15.4 | AF2: =VLOOKUP(F2,[4]IMC!$B$6:$R$210,10,FALSE) -> 16 | AG2: =VLOOKUP(F2,[4]IMC!$B$6:$R$210,11,FALSE) -> 17.1 | AH2: =VLOOKUP(F2,[4]IMC!$B$6:$R$210,12,FALSE) -> 18.6 | AI2: =VLOOKUP(F2,[4]IMC!$B$6:$R$210,13,FALSE) -> 19.5 | AJ2: =VLOOKUP(F2,[4]IMC!$B$6:$R$210,14,FALSE) -> 21.4 | AK2: =VLOOKUP(F2,[4]IMC!$B$6:$R$210,15,FALSE) -> 22.3 | AL2: =VLOOKUP(F2,[4]IMC!$B$6:$R$210,16,FALSE) -> 24.4 | AM2: =VLOOKUP(F2,[4]IMC!$B$6:$R$210,17,FALSE) -> 9999
F3: =DATEDIF(E3,D3,"M") -> 0 | G3: =YEARFRAC(D3,E3) -> 0 | L3: =K3/J3 -> #DIV/0! | M3: =IF(H3>0,IF(I3>0,H3/I3^2,""),"") | N3: =MATCH(F3,[4]IMC!B:B,0) -> #N/A | O3: =MATCH(M3,INDIRECT("IMC!F" & N3 & ":R" &N3),1) -> #N/A | P3: =CONCATENATE(INDEX([4]IMC!$F$1:$R$5,5,$O3) & " e " & INDEX([4]IMC!$F$1:$R$5,5,$O3+1)) -> #N/A | R3: =MATCH(F3,[4]PC!A:A,0) -> #N/A | S3: =MATCH(K3,INDIRECT("PC!E" & R3 & ":L" &R3),1) -> #N/A | T3: =CONCATENATE(INDEX([4]PC!$E$1:$M$2,1,$S3) & " e " & INDEX([4]PC!$E$1:$M$2,1,$S3+1)) -> #N/A | V3: =MATCH(U3,INDIRECT("IMC!F" & N3 & ":R" &N3),1) -> #N/A | W3: =CONCATENATE(INDEX([4]IMC!$F$1:$R$5,5,$V3) & " e " & INDEX([4]IMC!$F$1:$R$5,5,$V3+1)) -> #N/A | X3: =U3*(I3*I3) -> 0 | Y3: =H3-X3 -> 0 | AA3: =VLOOKUP(F3,[4]IMC!$B$6:$R$210,5,FALSE) -> #N/A | AB3: =VLOOKUP(F3,[4]IMC!$B$6:$R$210,6,FALSE) -> #N/A | AC3: =VLOOKUP(F3,[4]IMC!$B$6:$R$210,7,FALSE) -> #N/A | AD3: =VLOOKUP(F3,[4]IMC!$B$6:$R$210,8,FALSE) -> #N/A | AE3: =VLOOKUP(F3,[4]IMC!$B$6:$R$210,9,FALSE) -> #N/A | AF3: =VLOOKUP(F3,[4]IMC!$B$6:$R$210,10,FALSE) -> #N/A | AG3: =VLOOKUP(F3,[4]IMC!$B$6:$R$210,11,FALSE) -> #N/A | AH3: =VLOOKUP(F3,[4]IMC!$B$6:$R$210,12,FALSE) -> #N/A | AI3: =VLOOKUP(F3,[4]IMC!$B$6:$R$210,13,FALSE) -> #N/A | AJ3: =VLOOKUP(F3,[4]IMC!$B$6:$R$210,14,FALSE) -> #N/A | AK3: =VLOOKUP(F3,[4]IMC!$B$6:$R$210,15,FALSE) -> #N/A | AL3: =VLOOKUP(F3,[4]IMC!$B$6:$R$210,16,FALSE) -> #N/A | AM3: =VLOOKUP(F3,[4]IMC!$B$6:$R$210,17,FALSE) -> #N/A
F4: =DATEDIF(E4,D4,"M") -> 0 | G4: =YEARFRAC(D4,E4) -> 0 | L4: =K4/J4 -> #DIV/0! | M4: =IF(H4>0,IF(I4>0,H4/I4^2,""),"") | N4: =MATCH(F4,[4]IMC!B:B,0) -> #N/A | O4: =MATCH(M4,INDIRECT("IMC!F" & N4 & ":R" &N4),1) -> #N/A | P4: =CONCATENATE(INDEX([4]IMC!$F$1:$R$5,5,$O4) & " e " & INDEX([4]IMC!$F$1:$R$5,5,$O4+1)) -> #N/A | R4: =MATCH(F4,[4]PC!A:A,0) -> #N/A | S4: =MATCH(K4,INDIRECT("PC!E" & R4 & ":L" &R4),1) -> #N/A | T4: =CONCATENATE(INDEX([4]PC!$E$1:$M$2,1,$S4) & " e " & INDEX([4]PC!$E$1:$M$2,1,$S4+1)) -> #N/A | V4: =MATCH(U4,INDIRECT("IMC!F" & N4 & ":R" &N4),1) -> #N/A | W4: =CONCATENATE(INDEX([4]IMC!$F$1:$R$5,5,$V4) & " e " & INDEX([4]IMC!$F$1:$R$5,5,$V4+1)) -> #N/A | X4: =U4*(I4*I4) -> 0 | Y4: =H4-X4 -> 0 | AA4: =VLOOKUP(F4,[4]IMC!$B$6:$R$210,5,FALSE) -> #N/A | AB4: =VLOOKUP(F4,[4]IMC!$B$6:$R$210,6,FALSE) -> #N/A | AC4: =VLOOKUP(F4,[4]IMC!$B$6:$R$210,7,FALSE) -> #N/A | AD4: =VLOOKUP(F4,[4]IMC!$B$6:$R$210,8,FALSE) -> #N/A | AE4: =VLOOKUP(F4,[4]IMC!$B$6:$R$210,9,FALSE) -> #N/A | AF4: =VLOOKUP(F4,[4]IMC!$B$6:$R$210,10,FALSE) -> #N/A | AG4: =VLOOKUP(F4,[4]IMC!$B$6:$R$210,11,FALSE) -> #N/A | AH4: =VLOOKUP(F4,[4]IMC!$B$6:$R$210,12,FALSE) -> #N/A | AI4: =VLOOKUP(F4,[4]IMC!$B$6:$R$210,13,FALSE) -> #N/A | AJ4: =VLOOKUP(F4,[4]IMC!$B$6:$R$210,14,FALSE) -> #N/A | AK4: =VLOOKUP(F4,[4]IMC!$B$6:$R$210,15,FALSE) -> #N/A | AL4: =VLOOKUP(F4,[4]IMC!$B$6:$R$210,16,FALSE) -> #N/A | AM4: =VLOOKUP(F4,[4]IMC!$B$6:$R$210,17,FALSE) -> #N/A
F5: =DATEDIF(E5,D5,"M") -> 0 | G5: =YEARFRAC(D5,E5) -> 0 | L5: =K5/J5 -> #DIV/0! | M5: =IF(H5>0,IF(I5>0,H5/I5^2,""),"") | N5: =MATCH(F5,[4]IMC!B:B,0) -> #N/A | O5: =MATCH(M5,INDIRECT("IMC!F" & N5 & ":R" &N5),1) -> #N/A | P5: =CONCATENATE(INDEX([4]IMC!$F$1:$R$5,5,$O5) & " e " & INDEX([4]IMC!$F$1:$R$5,5,$O5+1)) -> #N/A | R5: =MATCH(F5,[4]PC!A:A,0) -> #N/A | S5: =MATCH(K5,INDIRECT("PC!E" & R5 & ":L" &R5),1) -> #N/A | T5: =CONCATENATE(INDEX([4]PC!$E$1:$M$2,1,$S5) & " e " & INDEX([4]PC!$E$1:$M$2,1,$S5+1)) -> #N/A | V5: =MATCH(U5,INDIRECT("IMC!F" & N5 & ":R" &N5),1) -> #N/A | W5: =CONCATENATE(INDEX([4]IMC!$F$1:$R$5,5,$V5) & " e " & INDEX([4]IMC!$F$1:$R$5,5,$V5+1)) -> #N/A | X5: =U5*(I5*I5) -> 0 | Y5: =H5-X5 -> 0 | AA5: =VLOOKUP(F5,[4]IMC!$B$6:$R$210,5,FALSE) -> #N/A | AB5: =VLOOKUP(F5,[4]IMC!$B$6:$R$210,6,FALSE) -> #N/A | AC5: =VLOOKUP(F5,[4]IMC!$B$6:$R$210,7,FALSE) -> #N/A | AD5: =VLOOKUP(F5,[4]IMC!$B$6:$R$210,8,FALSE) -> #N/A | AE5: =VLOOKUP(F5,[4]IMC!$B$6:$R$210,9,FALSE) -> #N/A | AF5: =VLOOKUP(F5,[4]IMC!$B$6:$R$210,10,FALSE) -> #N/A | AG5: =VLOOKUP(F5,[4]IMC!$B$6:$R$210,11,FALSE) -> #N/A | AH5: =VLOOKUP(F5,[4]IMC!$B$6:$R$210,12,FALSE) -> #N/A | AI5: =VLOOKUP(F5,[4]IMC!$B$6:$R$210,13,FALSE) -> #N/A | AJ5: =VLOOKUP(F5,[4]IMC!$B$6:$R$210,14,FALSE) -> #N/A | AK5: =VLOOKUP(F5,[4]IMC!$B$6:$R$210,15,FALSE) -> #N/A | AL5: =VLOOKUP(F5,[4]IMC!$B$6:$R$210,16,FALSE) -> #N/A | AM5: =VLOOKUP(F5,[4]IMC!$B$6:$R$210,17,FALSE) -> #N/A
F6: =DATEDIF(E6,D6,"M") -> 0 | G6: =YEARFRAC(D6,E6) -> 0 | L6: =K6/J6 -> #DIV/0! | M6: =IF(H6>0,IF(I6>0,H6/I6^2,""),"") | N6: =MATCH(F6,[4]IMC!B:B,0) -> #N/A | O6: =MATCH(M6,INDIRECT("IMC!F" & N6 & ":R" &N6),1) -> #N/A | P6: =CONCATENATE(INDEX([4]IMC!$F$1:$R$5,5,$O6) & " e " & INDEX([4]IMC!$F$1:$R$5,5,$O6+1)) -> #N/A | R6: =MATCH(F6,[4]PC!A:A,0) -> #N/A | S6: =MATCH(K6,INDIRECT("PC!E" & R6 & ":L" &R6),1) -> #N/A | T6: =CONCATENATE(INDEX([4]PC!$E$1:$M$2,1,$S6) & " e " & INDEX([4]PC!$E$1:$M$2,1,$S6+1)) -> #N/A | V6: =MATCH(U6,INDIRECT("IMC!F" & N6 & ":R" &N6),1) -> #N/A | W6: =CONCATENATE(INDEX([4]IMC!$F$1:$R$5,5,$V6) & " e " & INDEX([4]IMC!$F$1:$R$5,5,$V6+1)) -> #N/A | X6: =U6*(I6*I6) -> 0 | Y6: =H6-X6 -> 0 | AA6: =VLOOKUP(F6,[4]IMC!$B$6:$R$210,5,FALSE) -> #N/A | AB6: =VLOOKUP(F6,[4]IMC!$B$6:$R$210,6,FALSE) -> #N/A | AC6: =VLOOKUP(F6,[4]IMC!$B$6:$R$210,7,FALSE) -> #N/A | AD6: =VLOOKUP(F6,[4]IMC!$B$6:$R$210,8,FALSE) -> #N/A | AE6: =VLOOKUP(F6,[4]IMC!$B$6:$R$210,9,FALSE) -> #N/A | AF6: =VLOOKUP(F6,[4]IMC!$B$6:$R$210,10,FALSE) -> #N/A | AG6: =VLOOKUP(F6,[4]IMC!$B$6:$R$210,11,FALSE) -> #N/A | AH6: =VLOOKUP(F6,[4]IMC!$B$6:$R$210,12,FALSE) -> #N/A | AI6: =VLOOKUP(F6,[4]IMC!$B$6:$R$210,13,FALSE) -> #N/A | AJ6: =VLOOKUP(F6,[4]IMC!$B$6:$R$210,14,FALSE) -> #N/A | AK6: =VLOOKUP(F6,[4]IMC!$B$6:$R$210,15,FALSE) -> #N/A | AL6: =VLOOKUP(F6,[4]IMC!$B$6:$R$210,16,FALSE) -> #N/A | AM6: =VLOOKUP(F6,[4]IMC!$B$6:$R$210,17,FALSE) -> #N/A
F7: =DATEDIF(E7,D7,"M") -> 0 | G7: =YEARFRAC(D7,E7) -> 0 | L7: =K7/J7 -> #DIV/0! | M7: =IF(H7>0,IF(I7>0,H7/I7^2,""),"") | N7: =MATCH(F7,[4]IMC!B:B,0) -> #N/A | O7: =MATCH(M7,INDIRECT("IMC!F" & N7 & ":R" &N7),1) -> #N/A | P7: =CONCATENATE(INDEX([4]IMC!$F$1:$R$5,5,$O7) & " e " & INDEX([4]IMC!$F$1:$R$5,5,$O7+1)) -> #N/A | R7: =MATCH(F7,[4]PC!A:A,0) -> #N/A | S7: =MATCH(K7,INDIRECT("PC!E" & R7 & ":L" &R7),1) -> #N/A | T7: =CONCATENATE(INDEX([4]PC!$E$1:$M$2,1,$S7) & " e " & INDEX([4]PC!$E$1:$M$2,1,$S7+1)) -> #N/A | V7: =MATCH(U7,INDIRECT("IMC!F" & N7 & ":R" &N7),1) -> #N/A | W7: =CONCATENATE(INDEX([4]IMC!$F$1:$R$5,5,$V7) & " e " & INDEX([4]IMC!$F$1:$R$5,5,$V7+1)) -> #N/A | X7: =U7*(I7*I7) -> 0 | Y7: =H7-X7 -> 0 | AA7: =VLOOKUP(F7,[4]IMC!$B$6:$R$210,5,FALSE) -> #N/A | AB7: =VLOOKUP(F7,[4]IMC!$B$6:$R$210,6,FALSE) -> #N/A | AC7: =VLOOKUP(F7,[4]IMC!$B$6:$R$210,7,FALSE) -> #N/A | AD7: =VLOOKUP(F7,[4]IMC!$B$6:$R$210,8,FALSE) -> #N/A | AE7: =VLOOKUP(F7,[4]IMC!$B$6:$R$210,9,FALSE) -> #N/A | AF7: =VLOOKUP(F7,[4]IMC!$B$6:$R$210,10,FALSE) -> #N/A | AG7: =VLOOKUP(F7,[4]IMC!$B$6:$R$210,11,FALSE) -> #N/A | AH7: =VLOOKUP(F7,[4]IMC!$B$6:$R$210,12,FALSE) -> #N/A | AI7: =VLOOKUP(F7,[4]IMC!$B$6:$R$210,13,FALSE) -> #N/A | AJ7: =VLOOKUP(F7,[4]IMC!$B$6:$R$210,14,FALSE) -> #N/A | AK7: =VLOOKUP(F7,[4]IMC!$B$6:$R$210,15,FALSE) -> #N/A | AL7: =VLOOKUP(F7,[4]IMC!$B$6:$R$210,16,FALSE) -> #N/A | AM7: =VLOOKUP(F7,[4]IMC!$B$6:$R$210,17,FALSE) -> #N/A
F8: =DATEDIF(E8,D8,"M") -> 0 | G8: =YEARFRAC(D8,E8) -> 0 | J8: =I8*100 -> 0 | L8: =K8/J8 -> #DIV/0! | M8: =IF(H8>0,IF(I8>0,H8/I8^2,""),"") | N8: =MATCH(F8,[4]IMC!B:B,0) -> #N/A | O8: =MATCH(M8,INDIRECT("IMC!F" & N8 & ":R" &N8),1) -> #N/A | P8: =CONCATENATE(INDEX([4]IMC!$F$1:$R$5,5,$O8) & " e " & INDEX([4]IMC!$F$1:$R$5,5,$O8+1)) -> #N/A | R8: =MATCH(F8,[4]PC!A:A,0) -> #N/A | S8: =MATCH(K8,INDIRECT("PC!E" & R8 & ":L" &R8),1) -> #N/A | T8: =CONCATENATE(INDEX([4]PC!$E$1:$M$2,1,$S8) & " e " & INDEX([4]PC!$E$1:$M$2,1,$S8+1)) -> #N/A | V8: =MATCH(U8,INDIRECT("IMC!F" & N8 & ":R" &N8),1) -> #N/A | W8: =CONCATENATE(INDEX([4]IMC!$F$1:$R$5,5,$V8) & " e " & INDEX([4]IMC!$F$1:$R$5,5,$V8+1)) -> #N/A | X8: =U8*(I8*I8) -> 0 | Y8: =H8-X8 -> 0 | AA8: =VLOOKUP(F8,[4]IMC!$B$6:$R$210,5,FALSE) -> #N/A | AB8: =VLOOKUP(F8,[4]IMC!$B$6:$R$210,6,FALSE) -> #N/A | AC8: =VLOOKUP(F8,[4]IMC!$B$6:$R$210,7,FALSE) -> #N/A | AD8: =VLOOKUP(F8,[4]IMC!$B$6:$R$210,8,FALSE) -> #N/A | AE8: =VLOOKUP(F8,[4]IMC!$B$6:$R$210,9,FALSE) -> #N/A | AF8: =VLOOKUP(F8,[4]IMC!$B$6:$R$210,10,FALSE) -> #N/A | AG8: =VLOOKUP(F8,[4]IMC!$B$6:$R$210,11,FALSE) -> #N/A | AH8: =VLOOKUP(F8,[4]IMC!$B$6:$R$210,12,FALSE) -> #N/A | AI8: =VLOOKUP(F8,[4]IMC!$B$6:$R$210,13,FALSE) -> #N/A | AJ8: =VLOOKUP(F8,[4]IMC!$B$6:$R$210,14,FALSE) -> #N/A | AK8: =VLOOKUP(F8,[4]IMC!$B$6:$R$210,15,FALSE) -> #N/A | AL8: =VLOOKUP(F8,[4]IMC!$B$6:$R$210,16,FALSE) -> #N/A | AM8: =VLOOKUP(F8,[4]IMC!$B$6:$R$210,17,FALSE) -> #N/A
F9: =DATEDIF(E9,D9,"M") -> 0 | G9: =YEARFRAC(D9,E9) -> 0 | J9: =I9*100 -> 0 | L9: =K9/J9 -> #DIV/0! | M9: =IF(H9>0,IF(I9>0,H9/I9^2,""),"") | N9: =MATCH(F9,[4]IMC!B:B,0) -> #N/A | O9: =MATCH(M9,INDIRECT("IMC!F" & N9 & ":R" &N9),1) -> #N/A | P9: =CONCATENATE(INDEX([4]IMC!$F$1:$R$5,5,$O9) & " e " & INDEX([4]IMC!$F$1:$R$5,5,$O9+1)) -> #N/A | R9: =MATCH(F9,[4]PC!A:A,0) -> #N/A | S9: =MATCH(K9,INDIRECT("PC!E" & R9 & ":L" &R9),1) -> #N/A | T9: =CONCATENATE(INDEX([4]PC!$E$1:$M$2,1,$S9) & " e " & INDEX([4]PC!$E$1:$M$2,1,$S9+1)) -> #N/A | V9: =MATCH(U9,INDIRECT("IMC!F" & N9 & ":R" &N9),1) -> #N/A | W9: =CONCATENATE(INDEX([4]IMC!$F$1:$R$5,5,$V9) & " e " & INDEX([4]IMC!$F$1:$R$5,5,$V9+1)) -> #N/A | X9: =U9*(I9*I9) -> 0 | Y9: =H9-X9 -> 0 | AA9: =VLOOKUP(F9,[4]IMC!$B$6:$R$210,5,FALSE) -> #N/A | AB9: =VLOOKUP(F9,[4]IMC!$B$6:$R$210,6,FALSE) -> #N/A | AC9: =VLOOKUP(F9,[4]IMC!$B$6:$R$210,7,FALSE) -> #N/A | AD9: =VLOOKUP(F9,[4]IMC!$B$6:$R$210,8,FALSE) -> #N/A | AE9: =VLOOKUP(F9,[4]IMC!$B$6:$R$210,9,FALSE) -> #N/A | AF9: =VLOOKUP(F9,[4]IMC!$B$6:$R$210,10,FALSE) -> #N/A | AG9: =VLOOKUP(F9,[4]IMC!$B$6:$R$210,11,FALSE) -> #N/A | AH9: =VLOOKUP(F9,[4]IMC!$B$6:$R$210,12,FALSE) -> #N/A | AI9: =VLOOKUP(F9,[4]IMC!$B$6:$R$210,13,FALSE) -> #N/A | AJ9: =VLOOKUP(F9,[4]IMC!$B$6:$R$210,14,FALSE) -> #N/A | AK9: =VLOOKUP(F9,[4]IMC!$B$6:$R$210,15,FALSE) -> #N/A | AL9: =VLOOKUP(F9,[4]IMC!$B$6:$R$210,16,FALSE) -> #N/A | AM9: =VLOOKUP(F9,[4]IMC!$B$6:$R$210,17,FALSE) -> #N/A
F10: =DATEDIF(E10,D10,"M") -> 0 | G10: =YEARFRAC(D10,E10) -> 0 | J10: =I10*100 -> 0 | L10: =K10/J10 -> #DIV/0! | M10: =IF(H10>0,IF(I10>0,H10/I10^2,""),"") | N10: =MATCH(F10,[4]IMC!B:B,0) -> #N/A | O10: =MATCH(M10,INDIRECT("IMC!F" & N10 & ":R" &N10),1) -> #N/A | P10: =CONCATENATE(INDEX([4]IMC!$F$1:$R$5,5,$O10) & " e " & INDEX([4]IMC!$F$1:$R$5,5,$O10+1)) -> #N/A | R10: =MATCH(F10,[4]PC!A:A,0) -> #N/A | S10: =MATCH(K10,INDIRECT("PC!E" & R10 & ":L" &R10),1) -> #N/A | T10: =CONCATENATE(INDEX([4]PC!$E$1:$M$2,1,$S10) & " e " & INDEX([4]PC!$E$1:$M$2,1,$S10+1)) -> #N/A | V10: =MATCH(U10,INDIRECT("IMC!F" & N10 & ":R" &N10),1) -> #N/A | W10: =CONCATENATE(INDEX([4]IMC!$F$1:$R$5,5,$V10) & " e " & INDEX([4]IMC!$F$1:$R$5,5,$V10+1)) -> #N/A | X10: =U10*(I10*I10) -> 0 | Y10: =H10-X10 -> 0 | AA10: =VLOOKUP(F10,[4]IMC!$B$6:$R$210,5,FALSE) -> #N/A | AB10: =VLOOKUP(F10,[4]IMC!$B$6:$R$210,6,FALSE) -> #N/A | AC10: =VLOOKUP(F10,[4]IMC!$B$6:$R$210,7,FALSE) -> #N/A | AD10: =VLOOKUP(F10,[4]IMC!$B$6:$R$210,8,FALSE) -> #N/A | AE10: =VLOOKUP(F10,[4]IMC!$B$6:$R$210,9,FALSE) -> #N/A | AF10: =VLOOKUP(F10,[4]IMC!$B$6:$R$210,10,FALSE) -> #N/A | AG10: =VLOOKUP(F10,[4]IMC!$B$6:$R$210,11,FALSE) -> #N/A | AH10: =VLOOKUP(F10,[4]IMC!$B$6:$R$210,12,FALSE) -> #N/A | AI10: =VLOOKUP(F10,[4]IMC!$B$6:$R$210,13,FALSE) -> #N/A | AJ10: =VLOOKUP(F10,[4]IMC!$B$6:$R$210,14,FALSE) -> #N/A | AK10: =VLOOKUP(F10,[4]IMC!$B$6:$R$210,15,FALSE) -> #N/A | AL10: =VLOOKUP(F10,[4]IMC!$B$6:$R$210,16,FALSE) -> #N/A | AM10: =VLOOKUP(F10,[4]IMC!$B$6:$R$210,17,FALSE) -> #N/A
F11: =DATEDIF(E11,D11,"M") -> 0 | G11: =YEARFRAC(D11,E11) -> 0 | J11: =I11*100 -> 0 | L11: =K11/J11 -> #DIV/0! | M11: =IF(H11>0,IF(I11>0,H11/I11^2,""),"") | N11: =MATCH(F11,[4]IMC!B:B,0) -> #N/A | O11: =MATCH(M11,INDIRECT("IMC!F" & N11 & ":R" &N11),1) -> #N/A | P11: =CONCATENATE(INDEX([4]IMC!$F$1:$R$5,5,$O11) & " e " & INDEX([4]IMC!$F$1:$R$5,5,$O11+1)) -> #N/A | R11: =MATCH(F11,[4]PC!A:A,0) -> #N/A | S11: =MATCH(K11,INDIRECT("PC!E" & R11 & ":L" &R11),1) -> #N/A | T11: =CONCATENATE(INDEX([4]PC!$E$1:$M$2,1,$S11) & " e " & INDEX([4]PC!$E$1:$M$2,1,$S11+1)) -> #N/A | V11: =MATCH(U11,INDIRECT("IMC!F" & N11 & ":R" &N11),1) -> #N/A | W11: =CONCATENATE(INDEX([4]IMC!$F$1:$R$5,5,$V11) & " e " & INDEX([4]IMC!$F$1:$R$5,5,$V11+1)) -> #N/A | X11: =U11*(I11*I11) -> 0 | Y11: =H11-X11 -> 0 | AA11: =VLOOKUP(F11,[4]IMC!$B$6:$R$210,5,FALSE) -> #N/A | AB11: =VLOOKUP(F11,[4]IMC!$B$6:$R$210,6,FALSE) -> #N/A | AC11: =VLOOKUP(F11,[4]IMC!$B$6:$R$210,7,FALSE) -> #N/A | AD11: =VLOOKUP(F11,[4]IMC!$B$6:$R$210,8,FALSE) -> #N/A | AE11: =VLOOKUP(F11,[4]IMC!$B$6:$R$210,9,FALSE) -> #N/A | AF11: =VLOOKUP(F11,[4]IMC!$B$6:$R$210,10,FALSE) -> #N/A | AG11: =VLOOKUP(F11,[4]IMC!$B$6:$R$210,11,FALSE) -> #N/A | AH11: =VLOOKUP(F11,[4]IMC!$B$6:$R$210,12,FALSE) -> #N/A | AI11: =VLOOKUP(F11,[4]IMC!$B$6:$R$210,13,FALSE) -> #N/A | AJ11: =VLOOKUP(F11,[4]IMC!$B$6:$R$210,14,FALSE) -> #N/A | AK11: =VLOOKUP(F11,[4]IMC!$B$6:$R$210,15,FALSE) -> #N/A | AL11: =VLOOKUP(F11,[4]IMC!$B$6:$R$210,16,FALSE) -> #N/A | AM11: =VLOOKUP(F11,[4]IMC!$B$6:$R$210,17,FALSE) -> #N/A
F12: =DATEDIF(E12,D12,"M") -> 0 | G12: =YEARFRAC(D12,E12) -> 0 | J12: =I12*100 -> 0 | L12: =K12/J12 -> #DIV/0! | M12: =IF(H12>0,IF(I12>0,H12/I12^2,""),"") | N12: =MATCH(F12,[4]IMC!B:B,0) -> #N/A | O12: =MATCH(M12,INDIRECT("IMC!F" & N12 & ":R" &N12),1) -> #N/A | P12: =CONCATENATE(INDEX([4]IMC!$F$1:$R$5,5,$O12) & " e " & INDEX([4]IMC!$F$1:$R$5,5,$O12+1)) -> #N/A | R12: =MATCH(F12,[4]PC!A:A,0) -> #N/A | S12: =MATCH(K12,INDIRECT("PC!E" & R12 & ":L" &R12),1) -> #N/A | T12: =CONCATENATE(INDEX([4]PC!$E$1:$M$2,1,$S12) & " e " & INDEX([4]PC!$E$1:$M$2,1,$S12+1)) -> #N/A | V12: =MATCH(U12,INDIRECT("IMC!F" & N12 & ":R" &N12),1) -> #N/A | W12: =CONCATENATE(INDEX([4]IMC!$F$1:$R$5,5,$V12) & " e " & INDEX([4]IMC!$F$1:$R$5,5,$V12+1)) -> #N/A | X12: =U12*(I12*I12) -> 0 | Y12: =H12-X12 -> 0 | AA12: =VLOOKUP(F12,[4]IMC!$B$6:$R$210,5,FALSE) -> #N/A | AB12: =VLOOKUP(F12,[4]IMC!$B$6:$R$210,6,FALSE) -> #N/A | AC12: =VLOOKUP(F12,[4]IMC!$B$6:$R$210,7,FALSE) -> #N/A | AD12: =VLOOKUP(F12,[4]IMC!$B$6:$R$210,8,FALSE) -> #N/A | AE12: =VLOOKUP(F12,[4]IMC!$B$6:$R$210,9,FALSE) -> #N/A | AF12: =VLOOKUP(F12,[4]IMC!$B$6:$R$210,10,FALSE) -> #N/A | AG12: =VLOOKUP(F12,[4]IMC!$B$6:$R$210,11,FALSE) -> #N/A | AH12: =VLOOKUP(F12,[4]IMC!$B$6:$R$210,12,FALSE) -> #N/A | AI12: =VLOOKUP(F12,[4]IMC!$B$6:$R$210,13,FALSE) -> #N/A | AJ12: =VLOOKUP(F12,[4]IMC!$B$6:$R$210,14,FALSE) -> #N/A | AK12: =VLOOKUP(F12,[4]IMC!$B$6:$R$210,15,FALSE) -> #N/A | AL12: =VLOOKUP(F12,[4]IMC!$B$6:$R$210,16,FALSE) -> #N/A | AM12: =VLOOKUP(F12,[4]IMC!$B$6:$R$210,17,FALSE) -> #N/A
F13: =DATEDIF(E13,D13,"M") -> 0 | G13: =YEARFRAC(D13,E13) -> 0 | J13: =I13*100 -> 0 | L13: =K13/J13 -> #DIV/0! | M13: =IF(H13>0,IF(I13>0,H13/I13^2,""),"") | N13: =MATCH(F13,[4]IMC!B:B,0) -> #N/A | O13: =MATCH(M13,INDIRECT("IMC!F" & N13 & ":R" &N13),1) -> #N/A | P13: =CONCATENATE(INDEX([4]IMC!$F$1:$R$5,5,$O13) & " e " & INDEX([4]IMC!$F$1:$R$5,5,$O13+1)) -> #N/A | R13: =MATCH(F13,[4]PC!A:A,0) -> #N/A | S13: =MATCH(K13,INDIRECT("PC!E" & R13 & ":L" &R13),1) -> #N/A | T13: =CONCATENATE(INDEX([4]PC!$E$1:$M$2,1,$S13) & " e " & INDEX([4]PC!$E$1:$M$2,1,$S13+1)) -> #N/A | V13: =MATCH(U13,INDIRECT("IMC!F" & N13 & ":R" &N13),1) -> #N/A | W13: =CONCATENATE(INDEX([4]IMC!$F$1:$R$5,5,$V13) & " e " & INDEX([4]IMC!$F$1:$R$5,5,$V13+1)) -> #N/A | X13: =U13*(I13*I13) -> 0 | Y13: =H13-X13 -> 0 | AA13: =VLOOKUP(F13,[4]IMC!$B$6:$R$210,5,FALSE) -> #N/A | AB13: =VLOOKUP(F13,[4]IMC!$B$6:$R$210,6,FALSE) -> #N/A | AC13: =VLOOKUP(F13,[4]IMC!$B$6:$R$210,7,FALSE) -> #N/A | AD13: =VLOOKUP(F13,[4]IMC!$B$6:$R$210,8,FALSE) -> #N/A | AE13: =VLOOKUP(F13,[4]IMC!$B$6:$R$210,9,FALSE) -> #N/A | AF13: =VLOOKUP(F13,[4]IMC!$B$6:$R$210,10,FALSE) -> #N/A | AG13: =VLOOKUP(F13,[4]IMC!$B$6:$R$210,11,FALSE) -> #N/A | AH13: =VLOOKUP(F13,[4]IMC!$B$6:$R$210,12,FALSE) -> #N/A | AI13: =VLOOKUP(F13,[4]IMC!$B$6:$R$210,13,FALSE) -> #N/A | AJ13: =VLOOKUP(F13,[4]IMC!$B$6:$R$210,14,FALSE) -> #N/A | AK13: =VLOOKUP(F13,[4]IMC!$B$6:$R$210,15,FALSE) -> #N/A | AL13: =VLOOKUP(F13,[4]IMC!$B$6:$R$210,16,FALSE) -> #N/A | AM13: =VLOOKUP(F13,[4]IMC!$B$6:$R$210,17,FALSE) -> #N/A
F14: =DATEDIF(E14,D14,"M") -> 0 | G14: =YEARFRAC(D14,E14) -> 0 | J14: =I14*100 -> 0 | L14: =K14/J14 -> #DIV/0! | M14: =IF(H14>0,IF(I14>0,H14/I14^2,""),"") | N14: =MATCH(F14,[4]IMC!B:B,0) -> #N/A | O14: =MATCH(M14,INDIRECT("IMC!F" & N14 & ":R" &N14),1) -> #N/A | P14: =CONCATENATE(INDEX([4]IMC!$F$1:$R$5,5,$O14) & " e " & INDEX([4]IMC!$F$1:$R$5,5,$O14+1)) -> #N/A | R14: =MATCH(F14,[4]PC!A:A,0) -> #N/A | S14: =MATCH(K14,INDIRECT("PC!E" & R14 & ":L" &R14),1) -> #N/A | T14: =CONCATENATE(INDEX([4]PC!$E$1:$M$2,1,$S14) & " e " & INDEX([4]PC!$E$1:$M$2,1,$S14+1)) -> #N/A | V14: =MATCH(U14,INDIRECT("IMC!F" & N14 & ":R" &N14),1) -> #N/A | W14: =CONCATENATE(INDEX([4]IMC!$F$1:$R$5,5,$V14) & " e " & INDEX([4]IMC!$F$1:$R$5,5,$V14+1)) -> #N/A | X14: =U14*(I14*I14) -> 0 | Y14: =H14-X14 -> 0 | AA14: =VLOOKUP(F14,[4]IMC!$B$6:$R$210,5,FALSE) -> #N/A | AB14: =VLOOKUP(F14,[4]IMC!$B$6:$R$210,6,FALSE) -> #N/A | AC14: =VLOOKUP(F14,[4]IMC!$B$6:$R$210,7,FALSE) -> #N/A | AD14: =VLOOKUP(F14,[4]IMC!$B$6:$R$210,8,FALSE) -> #N/A | AE14: =VLOOKUP(F14,[4]IMC!$B$6:$R$210,9,FALSE) -> #N/A | AF14: =VLOOKUP(F14,[4]IMC!$B$6:$R$210,10,FALSE) -> #N/A | AG14: =VLOOKUP(F14,[4]IMC!$B$6:$R$210,11,FALSE) -> #N/A | AH14: =VLOOKUP(F14,[4]IMC!$B$6:$R$210,12,FALSE) -> #N/A | AI14: =VLOOKUP(F14,[4]IMC!$B$6:$R$210,13,FALSE) -> #N/A | AJ14: =VLOOKUP(F14,[4]IMC!$B$6:$R$210,14,FALSE) -> #N/A | AK14: =VLOOKUP(F14,[4]IMC!$B$6:$R$210,15,FALSE) -> #N/A | AL14: =VLOOKUP(F14,[4]IMC!$B$6:$R$210,16,FALSE) -> #N/A | AM14: =VLOOKUP(F14,[4]IMC!$B$6:$R$210,17,FALSE) -> #N/A
F15: =DATEDIF(E15,D15,"M") -> 0 | G15: =YEARFRAC(D15,E15) -> 0 | J15: =I15*100 -> 0 | L15: =K15/J15 -> #DIV/0! | M15: =IF(H15>0,IF(I15>0,H15/I15^2,""),"") | N15: =MATCH(F15,[4]IMC!B:B,0) -> #N/A | O15: =MATCH(M15,INDIRECT("IMC!F" & N15 & ":R" &N15),1) -> #N/A | P15: =CONCATENATE(INDEX([4]IMC!$F$1:$R$5,5,$O15) & " e " & INDEX([4]IMC!$F$1:$R$5,5,$O15+1)) -> #N/A | R15: =MATCH(F15,[4]PC!A:A,0) -> #N/A | S15: =MATCH(K15,INDIRECT("PC!E" & R15 & ":L" &R15),1) -> #N/A | T15: =CONCATENATE(INDEX([4]PC!$E$1:$M$2,1,$S15) & " e " & INDEX([4]PC!$E$1:$M$2,1,$S15+1)) -> #N/A | V15: =MATCH(U15,INDIRECT("IMC!F" & N15 & ":R" &N15),1) -> #N/A | W15: =CONCATENATE(INDEX([4]IMC!$F$1:$R$5,5,$V15) & " e " & INDEX([4]IMC!$F$1:$R$5,5,$V15+1)) -> #N/A | X15: =U15*(I15*I15) -> 0 | Y15: =H15-X15 -> 0 | AA15: =VLOOKUP(F15,[4]IMC!$B$6:$R$210,5,FALSE) -> #N/A | AB15: =VLOOKUP(F15,[4]IMC!$B$6:$R$210,6,FALSE) -> #N/A | AC15: =VLOOKUP(F15,[4]IMC!$B$6:$R$210,7,FALSE) -> #N/A | AD15: =VLOOKUP(F15,[4]IMC!$B$6:$R$210,8,FALSE) -> #N/A | AE15: =VLOOKUP(F15,[4]IMC!$B$6:$R$210,9,FALSE) -> #N/A | AF15: =VLOOKUP(F15,[4]IMC!$B$6:$R$210,10,FALSE) -> #N/A | AG15: =VLOOKUP(F15,[4]IMC!$B$6:$R$210,11,FALSE) -> #N/A | AH15: =VLOOKUP(F15,[4]IMC!$B$6:$R$210,12,FALSE) -> #N/A | AI15: =VLOOKUP(F15,[4]IMC!$B$6:$R$210,13,FALSE) -> #N/A | AJ15: =VLOOKUP(F15,[4]IMC!$B$6:$R$210,14,FALSE) -> #N/A | AK15: =VLOOKUP(F15,[4]IMC!$B$6:$R$210,15,FALSE) -> #N/A | AL15: =VLOOKUP(F15,[4]IMC!$B$6:$R$210,16,FALSE) -> #N/A | AM15: =VLOOKUP(F15,[4]IMC!$B$6:$R$210,17,FALSE) -> #N/A
F16: =DATEDIF(E16,D16,"M") -> 0 | G16: =YEARFRAC(D16,E16) -> 0 | J16: =I16*100 -> 0 | L16: =K16/J16 -> #DIV/0! | M16: =IF(H16>0,IF(I16>0,H16/I16^2,""),"") | N16: =MATCH(F16,[4]IMC!B:B,0) -> #N/A | O16: =MATCH(M16,INDIRECT("IMC!F" & N16 & ":R" &N16),1) -> #N/A | P16: =CONCATENATE(INDEX([4]IMC!$F$1:$R$5,5,$O16) & " e " & INDEX([4]IMC!$F$1:$R$5,5,$O16+1)) -> #N/A | R16: =MATCH(F16,[4]PC!A:A,0) -> #N/A | S16: =MATCH(K16,INDIRECT("PC!E" & R16 & ":L" &R16),1) -> #N/A | T16: =CONCATENATE(INDEX([4]PC!$E$1:$M$2,1,$S16) & " e " & INDEX([4]PC!$E$1:$M$2,1,$S16+1)) -> #N/A | V16: =MATCH(U16,INDIRECT("IMC!F" & N16 & ":R" &N16),1) -> #N/A | W16: =CONCATENATE(INDEX([4]IMC!$F$1:$R$5,5,$V16) & " e " & INDEX([4]IMC!$F$1:$R$5,5,$V16+1)) -> #N/A | X16: =U16*(I16*I16) -> 0 | Y16: =H16-X16 -> 0 | AA16: =VLOOKUP(F16,[4]IMC!$B$6:$R$210,5,FALSE) -> #N/A | AB16: =VLOOKUP(F16,[4]IMC!$B$6:$R$210,6,FALSE) -> #N/A | AC16: =VLOOKUP(F16,[4]IMC!$B$6:$R$210,7,FALSE) -> #N/A | AD16: =VLOOKUP(F16,[4]IMC!$B$6:$R$210,8,FALSE) -> #N/A | AE16: =VLOOKUP(F16,[4]IMC!$B$6:$R$210,9,FALSE) -> #N/A | AF16: =VLOOKUP(F16,[4]IMC!$B$6:$R$210,10,FALSE) -> #N/A | AG16: =VLOOKUP(F16,[4]IMC!$B$6:$R$210,11,FALSE) -> #N/A | AH16: =VLOOKUP(F16,[4]IMC!$B$6:$R$210,12,FALSE) -> #N/A | AI16: =VLOOKUP(F16,[4]IMC!$B$6:$R$210,13,FALSE) -> #N/A | AJ16: =VLOOKUP(F16,[4]IMC!$B$6:$R$210,14,FALSE) -> #N/A | AK16: =VLOOKUP(F16,[4]IMC!$B$6:$R$210,15,FALSE) -> #N/A | AL16: =VLOOKUP(F16,[4]IMC!$B$6:$R$210,16,FALSE) -> #N/A | AM16: =VLOOKUP(F16,[4]IMC!$B$6:$R$210,17,FALSE) -> #N/A
F17: =DATEDIF(E17,D17,"M") -> 0 | G17: =YEARFRAC(D17,E17) -> 0 | J17: =I17*100 -> 0 | L17: =K17/J17 -> #DIV/0! | M17: =IF(H17>0,IF(I17>0,H17/I17^2,""),"") | N17: =MATCH(F17,[4]IMC!B:B,0) -> #N/A | O17: =MATCH(M17,INDIRECT("IMC!F" & N17 & ":R" &N17),1) -> #N/A | P17: =CONCATENATE(INDEX([4]IMC!$F$1:$R$5,5,$O17) & " e " & INDEX([4]IMC!$F$1:$R$5,5,$O17+1)) -> #N/A | R17: =MATCH(F17,[4]PC!A:A,0) -> #N/A | S17: =MATCH(K17,INDIRECT("PC!E" & R17 & ":L" &R17),1) -> #N/A | T17: =CONCATENATE(INDEX([4]PC!$E$1:$M$2,1,$S17) & " e " & INDEX([4]PC!$E$1:$M$2,1,$S17+1)) -> #N/A | V17: =MATCH(U17,INDIRECT("IMC!F" & N17 & ":R" &N17),1) -> #N/A | W17: =CONCATENATE(INDEX([4]IMC!$F$1:$R$5,5,$V17) & " e " & INDEX([4]IMC!$F$1:$R$5,5,$V17+1)) -> #N/A | X17: =U17*(I17*I17) -> 0 | Y17: =H17-X17 -> 0 | AA17: =VLOOKUP(F17,[4]IMC!$B$6:$R$210,5,FALSE) -> #N/A | AB17: =VLOOKUP(F17,[4]IMC!$B$6:$R$210,6,FALSE) -> #N/A | AC17: =VLOOKUP(F17,[4]IMC!$B$6:$R$210,7,FALSE) -> #N/A | AD17: =VLOOKUP(F17,[4]IMC!$B$6:$R$210,8,FALSE) -> #N/A | AE17: =VLOOKUP(F17,[4]IMC!$B$6:$R$210,9,FALSE) -> #N/A | AF17: =VLOOKUP(F17,[4]IMC!$B$6:$R$210,10,FALSE) -> #N/A | AG17: =VLOOKUP(F17,[4]IMC!$B$6:$R$210,11,FALSE) -> #N/A | AH17: =VLOOKUP(F17,[4]IMC!$B$6:$R$210,12,FALSE) -> #N/A | AI17: =VLOOKUP(F17,[4]IMC!$B$6:$R$210,13,FALSE) -> #N/A | AJ17: =VLOOKUP(F17,[4]IMC!$B$6:$R$210,14,FALSE) -> #N/A | AK17: =VLOOKUP(F17,[4]IMC!$B$6:$R$210,15,FALSE) -> #N/A | AL17: =VLOOKUP(F17,[4]IMC!$B$6:$R$210,16,FALSE) -> #N/A | AM17: =VLOOKUP(F17,[4]IMC!$B$6:$R$210,17,FALSE) -> #N/A
F18: =DATEDIF(E18,D18,"M") -> 0 | G18: =YEARFRAC(D18,E18) -> 0 | J18: =I18*100 -> 0 | L18: =K18/J18 -> #DIV/0! | M18: =IF(H18>0,IF(I18>0,H18/I18^2,""),"") | N18: =MATCH(F18,[4]IMC!B:B,0) -> #N/A | O18: =MATCH(M18,INDIRECT("IMC!F" & N18 & ":R" &N18),1) -> #N/A | P18: =CONCATENATE(INDEX([4]IMC!$F$1:$R$5,5,$O18) & " e " & INDEX([4]IMC!$F$1:$R$5,5,$O18+1)) -> #N/A | R18: =MATCH(F18,[4]PC!A:A,0) -> #N/A | S18: =MATCH(K18,INDIRECT("PC!E" & R18 & ":L" &R18),1) -> #N/A | T18: =CONCATENATE(INDEX([4]PC!$E$1:$M$2,1,$S18) & " e " & INDEX([4]PC!$E$1:$M$2,1,$S18+1)) -> #N/A | V18: =MATCH(U18,INDIRECT("IMC!F" & N18 & ":R" &N18),1) -> #N/A | W18: =CONCATENATE(INDEX([4]IMC!$F$1:$R$5,5,$V18) & " e " & INDEX([4]IMC!$F$1:$R$5,5,$V18+1)) -> #N/A | X18: =U18*(I18*I18) -> 0 | Y18: =H18-X18 -> 0 | AA18: =VLOOKUP(F18,[4]IMC!$B$6:$R$210,5,FALSE) -> #N/A | AB18: =VLOOKUP(F18,[4]IMC!$B$6:$R$210,6,FALSE) -> #N/A | AC18: =VLOOKUP(F18,[4]IMC!$B$6:$R$210,7,FALSE) -> #N/A | AD18: =VLOOKUP(F18,[4]IMC!$B$6:$R$210,8,FALSE) -> #N/A | AE18: =VLOOKUP(F18,[4]IMC!$B$6:$R$210,9,FALSE) -> #N/A | AF18: =VLOOKUP(F18,[4]IMC!$B$6:$R$210,10,FALSE) -> #N/A | AG18: =VLOOKUP(F18,[4]IMC!$B$6:$R$210,11,FALSE) -> #N/A | AH18: =VLOOKUP(F18,[4]IMC!$B$6:$R$210,12,FALSE) -> #N/A | AI18: =VLOOKUP(F18,[4]IMC!$B$6:$R$210,13,FALSE) -> #N/A | AJ18: =VLOOKUP(F18,[4]IMC!$B$6:$R$210,14,FALSE) -> #N/A | AK18: =VLOOKUP(F18,[4]IMC!$B$6:$R$210,15,FALSE) -> #N/A | AL18: =VLOOKUP(F18,[4]IMC!$B$6:$R$210,16,FALSE) -> #N/A | AM18: =VLOOKUP(F18,[4]IMC!$B$6:$R$210,17,FALSE) -> #N/A
F19: =DATEDIF(E19,D19,"M") -> 0 | G19: =YEARFRAC(D19,E19) -> 0 | J19: =I19*100 -> 0 | L19: =K19/J19 -> #DIV/0! | M19: =IF(H19>0,IF(I19>0,H19/I19^2,""),"") | N19: =MATCH(F19,[4]IMC!B:B,0) -> #N/A | O19: =MATCH(M19,INDIRECT("IMC!F" & N19 & ":R" &N19),1) -> #N/A | P19: =CONCATENATE(INDEX([4]IMC!$F$1:$R$5,5,$O19) & " e " & INDEX([4]IMC!$F$1:$R$5,5,$O19+1)) -> #N/A | R19: =MATCH(F19,[4]PC!A:A,0) -> #N/A | S19: =MATCH(K19,INDIRECT("PC!E" & R19 & ":L" &R19),1) -> #N/A | T19: =CONCATENATE(INDEX([4]PC!$E$1:$M$2,1,$S19) & " e " & INDEX([4]PC!$E$1:$M$2,1,$S19+1)) -> #N/A | V19: =MATCH(U19,INDIRECT("IMC!F" & N19 & ":R" &N19),1) -> #N/A | W19: =CONCATENATE(INDEX([4]IMC!$F$1:$R$5,5,$V19) & " e " & INDEX([4]IMC!$F$1:$R$5,5,$V19+1)) -> #N/A | X19: =U19*(I19*I19) -> 0 | Y19: =H19-X19 -> 0 | AA19: =VLOOKUP(F19,[4]IMC!$B$6:$R$210,5,FALSE) -> #N/A | AB19: =VLOOKUP(F19,[4]IMC!$B$6:$R$210,6,FALSE) -> #N/A | AC19: =VLOOKUP(F19,[4]IMC!$B$6:$R$210,7,FALSE) -> #N/A | AD19: =VLOOKUP(F19,[4]IMC!$B$6:$R$210,8,FALSE) -> #N/A | AE19: =VLOOKUP(F19,[4]IMC!$B$6:$R$210,9,FALSE) -> #N/A | AF19: =VLOOKUP(F19,[4]IMC!$B$6:$R$210,10,FALSE) -> #N/A | AG19: =VLOOKUP(F19,[4]IMC!$B$6:$R$210,11,FALSE) -> #N/A | AH19: =VLOOKUP(F19,[4]IMC!$B$6:$R$210,12,FALSE) -> #N/A | AI19: =VLOOKUP(F19,[4]IMC!$B$6:$R$210,13,FALSE) -> #N/A | AJ19: =VLOOKUP(F19,[4]IMC!$B$6:$R$210,14,FALSE) -> #N/A | AK19: =VLOOKUP(F19,[4]IMC!$B$6:$R$210,15,FALSE) -> #N/A | AL19: =VLOOKUP(F19,[4]IMC!$B$6:$R$210,16,FALSE) -> #N/A | AM19: =VLOOKUP(F19,[4]IMC!$B$6:$R$210,17,FALSE) -> #N/A
... F99: =DATEDIF(E99,D99,"M") -> 0 | G99: =YEARFRAC(D99,E99) -> 0 | J99: =I99*100 -> 0 | L99: =K99/J99 -> #DIV/0! | M99: =IF(H99>0,IF(I99>0,H99/I99^2,""),"") | N99: =MATCH(F99,[4]IMC!B:B,0) -> #N/A | O99: =MATCH(M99,INDIRECT("IMC!F" & N99 & ":R" &N99),1) -> #N/A | P99: =CONCATENATE(INDEX([4]IMC!$F$1:$R$5,5,$O99) & " e " & INDEX([4]IMC!$F$1:$R$5,5,$O99+1)) -> #N/A | R99: =MATCH(F99,[4]PC!A:A,0) -> #N/A | S99: =MATCH(K99,INDIRECT("PC!E" & R99 & ":L" &R99),1) -> #N/A | T99: =CONCATENATE(INDEX([4]PC!$E$1:$M$2,1,$S99) & " e " & INDEX([4]PC!$E$1:$M$2,1,$S99+1)) -> #N/A | V99: =MATCH(U99,INDIRECT("IMC!F" & N99 & ":R" &N99),1) -> #N/A | W99: =CONCATENATE(INDEX([4]IMC!$F$1:$R$5,5,$V99) & " e " & INDEX([4]IMC!$F$1:$R$5,5,$V99+1)) -> #N/A | X99: =U99*(I99*I99) -> 0 | Y99: =H99-X99 -> 0 | AA99: =VLOOKUP(F99,[4]IMC!$B$6:$R$210,5,FALSE) -> #N/A | AB99: =VLOOKUP(F99,[4]IMC!$B$6:$R$210,6,FALSE) -> #N/A | AC99: =VLOOKUP(F99,[4]IMC!$B$6:$R$210,7,FALSE) -> #N/A | AD99: =VLOOKUP(F99,[4]IMC!$B$6:$R$210,8,FALSE) -> #N/A | AE99: =VLOOKUP(F99,[4]IMC!$B$6:$R$210,9,FALSE) -> #N/A | AF99: =VLOOKUP(F99,[4]IMC!$B$6:$R$210,10,FALSE) -> #N/A | AG99: =VLOOKUP(F99,[4]IMC!$B$6:$R$210,11,FALSE) -> #N/A | AH99: =VLOOKUP(F99,[4]IMC!$B$6:$R$210,12,FALSE) -> #N/A | AI99: =VLOOKUP(F99,[4]IMC!$B$6:$R$210,13,FALSE) -> #N/A | AJ99: =VLOOKUP(F99,[4]IMC!$B$6:$R$210,14,FALSE) -> #N/A | AK99: =VLOOKUP(F99,[4]IMC!$B$6:$R$210,15,FALSE) -> #N/A | AL99: =VLOOKUP(F99,[4]IMC!$B$6:$R$210,16,FALSE) -> #N/A | AM99: =VLOOKUP(F99,[4]IMC!$B$6:$R$210,17,FALSE) -> #N/A
D100: 44717 | E100: 38797 | F100: =DATEDIF(E100,D100,"M") -> 194 | G100: =YEARFRAC(D100,E100) -> 16.205556 | H100: 52 | I100: 1.65 | J100: =I100*100 -> 165 | L100: =K100/J100 -> 0 | M100: =IF(H100>0,IF(I100>0,H100/I100^2,""),"") -> 19.100092 | N100: =MATCH(F100,[4]IMC!B:B,0) -> 176 | O100: =MATCH(M100,INDIRECT("IMC!F" & N100 & ":R" &N100),1) -> 6 | P100: =CONCATENATE(INDEX([4]IMC!$F$1:$R$5,5,$O100) & " e " & INDEX([4]IMC!$F$1:$R$5,5,$O100+1)) -> 25th e 50th | R100: =MATCH(F100,[4]PC!A:A,0) -> 82 | S100: =MATCH(K100,INDIRECT("PC!E" & R100 & ":L" &R100),1) -> #REF! | T100: =CONCATENATE(INDEX([4]PC!$E$1:$M$2,1,$S100) & " e " & INDEX([4]PC!$E$1:$M$2,1,$S100+1)) -> #REF! | V100: =MATCH(U100,INDIRECT("IMC!F" & N100 & ":R" &N100),1) -> 1 | W100: =CONCATENATE(INDEX([4]IMC!$F$1:$R$5,5,$V100) & " e " & INDEX([4]IMC!$F$1:$R$5,5,$V100+1)) -> <1st e 1st | X100: =U100*(I100*I100) -> 0 | Y100: =H100-X100 -> 52 | AA100: =VLOOKUP(F100,[4]IMC!$B$6:$R$210,5,FALSE) -> -1 | AB100: =VLOOKUP(F100,[4]IMC!$B$6:$R$210,6,FALSE) -> 16.1 | AC100: =VLOOKUP(F100,[4]IMC!$B$6:$R$210,7,FALSE) -> 16.8 | AD100: =VLOOKUP(F100,[4]IMC!$B$6:$R$210,8,FALSE) -> 17.2 | AE100: =VLOOKUP(F100,[4]IMC!$B$6:$R$210,9,FALSE) -> 18.3 | AF100: =VLOOKUP(F100,[4]IMC!$B$6:$R$210,10,FALSE) -> 19 | AG100: =VLOOKUP(F100,[4]IMC!$B$6:$R$210,11,FALSE) -> 20.6 | AH100: =VLOOKUP(F100,[4]IMC!$B$6:$R$210,12,FALSE) -> 22.6 | AI100: =VLOOKUP(F100,[4]IMC!$B$6:$R$210,13,FALSE) -> 23.8 | AJ100: =VLOOKUP(F100,[4]IMC!$B$6:$R$210,14,FALSE) -> 26.3 | AK100: =VLOOKUP(F100,[4]IMC!$B$6:$R$210,15,FALSE) -> 27.4 | AL100: =VLOOKUP(F100,[4]IMC!$B$6:$R$210,16,FALSE) -> 29.9 | AM100: =VLOOKUP(F100,[4]IMC!$B$6:$R$210,17,FALSE) -> 9999
F101: =DATEDIF(E101,D101,"M") -> 0 | G101: =YEARFRAC(D101,E101) -> 0 | J101: =I101*100 -> 0 | L101: =K101/J101 -> #DIV/0! | M101: =IF(H101>0,IF(I101>0,H101/I101^2,""),"") | N101: =MATCH(F101,[4]IMC!B:B,0) -> #N/A | O101: =MATCH(M101,INDIRECT("IMC!F" & N101 & ":R" &N101),1) -> #N/A | P101: =CONCATENATE(INDEX([4]IMC!$F$1:$R$5,5,$O101) & " e " & INDEX([4]IMC!$F$1:$R$5,5,$O101+1)) -> #N/A | R101: =MATCH(F101,[4]PC!A:A,0) -> #N/A | S101: =MATCH(K101,INDIRECT("PC!E" & R101 & ":L" &R101),1) -> #N/A | T101: =CONCATENATE(INDEX([4]PC!$E$1:$M$2,1,$S101) & " e " & INDEX([4]PC!$E$1:$M$2,1,$S101+1)) -> #N/A | V101: =MATCH(U101,INDIRECT("IMC!F" & N101 & ":R" &N101),1) -> #N/A | W101: =CONCATENATE(INDEX([4]IMC!$F$1:$R$5,5,$V101) & " e " & INDEX([4]IMC!$F$1:$R$5,5,$V101+1)) -> #N/A | X101: =U101*(I101*I101) -> 0 | Y101: =H101-X101 -> 0 | AA101: =VLOOKUP(F101,[4]IMC!$B$6:$R$210,5,FALSE) -> #N/A | AB101: =VLOOKUP(F101,[4]IMC!$B$6:$R$210,6,FALSE) -> #N/A | AC101: =VLOOKUP(F101,[4]IMC!$B$6:$R$210,7,FALSE) -> #N/A | AD101: =VLOOKUP(F101,[4]IMC!$B$6:$R$210,8,FALSE) -> #N/A | AE101: =VLOOKUP(F101,[4]IMC!$B$6:$R$210,9,FALSE) -> #N/A | AF101: =VLOOKUP(F101,[4]IMC!$B$6:$R$210,10,FALSE) -> #N/A | AG101: =VLOOKUP(F101,[4]IMC!$B$6:$R$210,11,FALSE) -> #N/A | AH101: =VLOOKUP(F101,[4]IMC!$B$6:$R$210,12,FALSE) -> #N/A | AI101: =VLOOKUP(F101,[4]IMC!$B$6:$R$210,13,FALSE) -> #N/A | AJ101: =VLOOKUP(F101,[4]IMC!$B$6:$R$210,14,FALSE) -> #N/A | AK101: =VLOOKUP(F101,[4]IMC!$B$6:$R$210,15,FALSE) -> #N/A | AL101: =VLOOKUP(F101,[4]IMC!$B$6:$R$210,16,FALSE) -> #N/A | AM101: =VLOOKUP(F101,[4]IMC!$B$6:$R$210,17,FALSE) -> #N/A
F102: =DATEDIF(E102,D102,"M") -> 0 | G102: =YEARFRAC(D102,E102) -> 0 | J102: =I102*100 -> 0 | L102: =K102/J102 -> #DIV/0! | M102: =IF(H102>0,IF(I102>0,H102/I102^2,""),"") | N102: =MATCH(F102,[4]IMC!B:B,0) -> #N/A | O102: =MATCH(M102,INDIRECT("IMC!F" & N102 & ":R" &N102),1) -> #N/A | P102: =CONCATENATE(INDEX([4]IMC!$F$1:$R$5,5,$O102) & " e " & INDEX([4]IMC!$F$1:$R$5,5,$O102+1)) -> #N/A | R102: =MATCH(F102,[4]PC!A:A,0) -> #N/A | S102: =MATCH(K102,INDIRECT("PC!E" & R102 & ":L" &R102),1) -> #N/A | T102: =CONCATENATE(INDEX([4]PC!$E$1:$M$2,1,$S102) & " e " & INDEX([4]PC!$E$1:$M$2,1,$S102+1)) -> #N/A | V102: =MATCH(U102,INDIRECT("IMC!F" & N102 & ":R" &N102),1) -> #N/A | W102: =CONCATENATE(INDEX([4]IMC!$F$1:$R$5,5,$V102) & " e " & INDEX([4]IMC!$F$1:$R$5,5,$V102+1)) -> #N/A | X102: =U102*(I102*I102) -> 0 | Y102: =H102-X102 -> 0 | AA102: =VLOOKUP(F102,[4]IMC!$B$6:$R$210,5,FALSE) -> #N/A | AB102: =VLOOKUP(F102,[4]IMC!$B$6:$R$210,6,FALSE) -> #N/A | AC102: =VLOOKUP(F102,[4]IMC!$B$6:$R$210,7,FALSE) -> #N/A | AD102: =VLOOKUP(F102,[4]IMC!$B$6:$R$210,8,FALSE) -> #N/A | AE102: =VLOOKUP(F102,[4]IMC!$B$6:$R$210,9,FALSE) -> #N/A | AF102: =VLOOKUP(F102,[4]IMC!$B$6:$R$210,10,FALSE) -> #N/A | AG102: =VLOOKUP(F102,[4]IMC!$B$6:$R$210,11,FALSE) -> #N/A | AH102: =VLOOKUP(F102,[4]IMC!$B$6:$R$210,12,FALSE) -> #N/A | AI102: =VLOOKUP(F102,[4]IMC!$B$6:$R$210,13,FALSE) -> #N/A | AJ102: =VLOOKUP(F102,[4]IMC!$B$6:$R$210,14,FALSE) -> #N/A | AK102: =VLOOKUP(F102,[4]IMC!$B$6:$R$210,15,FALSE) -> #N/A | AL102: =VLOOKUP(F102,[4]IMC!$B$6:$R$210,16,FALSE) -> #N/A | AM102: =VLOOKUP(F102,[4]IMC!$B$6:$R$210,17,FALSE) -> #N/A
F103: =DATEDIF(E103,D103,"M") -> 0 | G103: =YEARFRAC(D103,E103) -> 0 | J103: =I103*100 -> 0 | L103: =K103/J103 -> #DIV/0! | M103: =IF(H103>0,IF(I103>0,H103/I103^2,""),"") | N103: =MATCH(F103,[4]IMC!B:B,0) -> #N/A | O103: =MATCH(M103,INDIRECT("IMC!F" & N103 & ":R" &N103),1) -> #N/A | P103: =CONCATENATE(INDEX([4]IMC!$F$1:$R$5,5,$O103) & " e " & INDEX([4]IMC!$F$1:$R$5,5,$O103+1)) -> #N/A | R103: =MATCH(F103,[4]PC!A:A,0) -> #N/A | S103: =MATCH(K103,INDIRECT("PC!E" & R103 & ":L" &R103),1) -> #N/A | T103: =CONCATENATE(INDEX([4]PC!$E$1:$M$2,1,$S103) & " e " & INDEX([4]PC!$E$1:$M$2,1,$S103+1)) -> #N/A | V103: =MATCH(U103,INDIRECT("IMC!F" & N103 & ":R" &N103),1) -> #N/A | W103: =CONCATENATE(INDEX([4]IMC!$F$1:$R$5,5,$V103) & " e " & INDEX([4]IMC!$F$1:$R$5,5,$V103+1)) -> #N/A | X103: =U103*(I103*I103) -> 0 | Y103: =H103-X103 -> 0 | AA103: =VLOOKUP(F103,[4]IMC!$B$6:$R$210,5,FALSE) -> #N/A | AB103: =VLOOKUP(F103,[4]IMC!$B$6:$R$210,6,FALSE) -> #N/A | AC103: =VLOOKUP(F103,[4]IMC!$B$6:$R$210,7,FALSE) -> #N/A | AD103: =VLOOKUP(F103,[4]IMC!$B$6:$R$210,8,FALSE) -> #N/A | AE103: =VLOOKUP(F103,[4]IMC!$B$6:$R$210,9,FALSE) -> #N/A | AF103: =VLOOKUP(F103,[4]IMC!$B$6:$R$210,10,FALSE) -> #N/A | AG103: =VLOOKUP(F103,[4]IMC!$B$6:$R$210,11,FALSE) -> #N/A | AH103: =VLOOKUP(F103,[4]IMC!$B$6:$R$210,12,FALSE) -> #N/A | AI103: =VLOOKUP(F103,[4]IMC!$B$6:$R$210,13,FALSE) -> #N/A | AJ103: =VLOOKUP(F103,[4]IMC!$B$6:$R$210,14,FALSE) -> #N/A | AK103: =VLOOKUP(F103,[4]IMC!$B$6:$R$210,15,FALSE) -> #N/A | AL103: =VLOOKUP(F103,[4]IMC!$B$6:$R$210,16,FALSE) -> #N/A | AM103: =VLOOKUP(F103,[4]IMC!$B$6:$R$210,17,FALSE) -> #N/A
F104: =DATEDIF(E104,D104,"M") -> 0 | G104: =YEARFRAC(D104,E104) -> 0 | J104: =I104*100 -> 0 | L104: =K104/J104 -> #DIV/0! | M104: =IF(H104>0,IF(I104>0,H104/I104^2,""),"") | N104: =MATCH(F104,[4]IMC!B:B,0) -> #N/A | O104: =MATCH(M104,INDIRECT("IMC!F" & N104 & ":R" &N104),1) -> #N/A | P104: =CONCATENATE(INDEX([4]IMC!$F$1:$R$5,5,$O104) & " e " & INDEX([4]IMC!$F$1:$R$5,5,$O104+1)) -> #N/A | R104: =MATCH(F104,[4]PC!A:A,0) -> #N/A | S104: =MATCH(K104,INDIRECT("PC!E" & R104 & ":L" &R104),1) -> #N/A | T104: =CONCATENATE(INDEX([4]PC!$E$1:$M$2,1,$S104) & " e " & INDEX([4]PC!$E$1:$M$2,1,$S104+1)) -> #N/A | V104: =MATCH(U104,INDIRECT("IMC!F" & N104 & ":R" &N104),1) -> #N/A | W104: =CONCATENATE(INDEX([4]IMC!$F$1:$R$5,5,$V104) & " e " & INDEX([4]IMC!$F$1:$R$5,5,$V104+1)) -> #N/A | X104: =U104*(I104*I104) -> 0 | Y104: =H104-X104 -> 0 | AA104: =VLOOKUP(F104,[4]IMC!$B$6:$R$210,5,FALSE) -> #N/A | AB104: =VLOOKUP(F104,[4]IMC!$B$6:$R$210,6,FALSE) -> #N/A | AC104: =VLOOKUP(F104,[4]IMC!$B$6:$R$210,7,FALSE) -> #N/A | AD104: =VLOOKUP(F104,[4]IMC!$B$6:$R$210,8,FALSE) -> #N/A | AE104: =VLOOKUP(F104,[4]IMC!$B$6:$R$210,9,FALSE) -> #N/A | AF104: =VLOOKUP(F104,[4]IMC!$B$6:$R$210,10,FALSE) -> #N/A | AG104: =VLOOKUP(F104,[4]IMC!$B$6:$R$210,11,FALSE) -> #N/A | AH104: =VLOOKUP(F104,[4]IMC!$B$6:$R$210,12,FALSE) -> #N/A | AI104: =VLOOKUP(F104,[4]IMC!$B$6:$R$210,13,FALSE) -> #N/A | AJ104: =VLOOKUP(F104,[4]IMC!$B$6:$R$210,14,FALSE) -> #N/A | AK104: =VLOOKUP(F104,[4]IMC!$B$6:$R$210,15,FALSE) -> #N/A | AL104: =VLOOKUP(F104,[4]IMC!$B$6:$R$210,16,FALSE) -> #N/A | AM104: =VLOOKUP(F104,[4]IMC!$B$6:$R$210,17,FALSE) -> #N/A
F105: =DATEDIF(E105,D105,"M") -> 0 | G105: =YEARFRAC(D105,E105) -> 0 | J105: =I105*100 -> 0 | L105: =K105/J105 -> #DIV/0! | M105: =IF(H105>0,IF(I105>0,H105/I105^2,""),"") | N105: =MATCH(F105,[4]IMC!B:B,0) -> #N/A | O105: =MATCH(M105,INDIRECT("IMC!F" & N105 & ":R" &N105),1) -> #N/A | P105: =CONCATENATE(INDEX([4]IMC!$F$1:$R$5,5,$O105) & " e " & INDEX([4]IMC!$F$1:$R$5,5,$O105+1)) -> #N/A | R105: =MATCH(F105,[4]PC!A:A,0) -> #N/A | S105: =MATCH(K105,INDIRECT("PC!E" & R105 & ":L" &R105),1) -> #N/A | T105: =CONCATENATE(INDEX([4]PC!$E$1:$M$2,1,$S105) & " e " & INDEX([4]PC!$E$1:$M$2,1,$S105+1)) -> #N/A | V105: =MATCH(U105,INDIRECT("IMC!F" & N105 & ":R" &N105),1) -> #N/A | W105: =CONCATENATE(INDEX([4]IMC!$F$1:$R$5,5,$V105) & " e " & INDEX([4]IMC!$F$1:$R$5,5,$V105+1)) -> #N/A | X105: =U105*(I105*I105) -> 0 | Y105: =H105-X105 -> 0 | AA105: =VLOOKUP(F105,[4]IMC!$B$6:$R$210,5,FALSE) -> #N/A | AB105: =VLOOKUP(F105,[4]IMC!$B$6:$R$210,6,FALSE) -> #N/A | AC105: =VLOOKUP(F105,[4]IMC!$B$6:$R$210,7,FALSE) -> #N/A | AD105: =VLOOKUP(F105,[4]IMC!$B$6:$R$210,8,FALSE) -> #N/A | AE105: =VLOOKUP(F105,[4]IMC!$B$6:$R$210,9,FALSE) -> #N/A | AF105: =VLOOKUP(F105,[4]IMC!$B$6:$R$210,10,FALSE) -> #N/A | AG105: =VLOOKUP(F105,[4]IMC!$B$6:$R$210,11,FALSE) -> #N/A | AH105: =VLOOKUP(F105,[4]IMC!$B$6:$R$210,12,FALSE) -> #N/A | AI105: =VLOOKUP(F105,[4]IMC!$B$6:$R$210,13,FALSE) -> #N/A | AJ105: =VLOOKUP(F105,[4]IMC!$B$6:$R$210,14,FALSE) -> #N/A | AK105: =VLOOKUP(F105,[4]IMC!$B$6:$R$210,15,FALSE) -> #N/A | AL105: =VLOOKUP(F105,[4]IMC!$B$6:$R$210,16,FALSE) -> #N/A | AM105: =VLOOKUP(F105,[4]IMC!$B$6:$R$210,17,FALSE) -> #N/A
F106: =DATEDIF(E106,D106,"M") -> 0 | G106: =YEARFRAC(D106,E106) -> 0 | J106: =I106*100 -> 0 | L106: =K106/J106 -> #DIV/0! | M106: =IF(H106>0,IF(I106>0,H106/I106^2,""),"") | N106: =MATCH(F106,[4]IMC!B:B,0) -> #N/A | O106: =MATCH(M106,INDIRECT("IMC!F" & N106 & ":R" &N106),1) -> #N/A | P106: =CONCATENATE(INDEX([4]IMC!$F$1:$R$5,5,$O106) & " e " & INDEX([4]IMC!$F$1:$R$5,5,$O106+1)) -> #N/A | R106: =MATCH(F106,[4]PC!A:A,0) -> #N/A | S106: =MATCH(K106,INDIRECT("PC!E" & R106 & ":L" &R106),1) -> #N/A | T106: =CONCATENATE(INDEX([4]PC!$E$1:$M$2,1,$S106) & " e " & INDEX([4]PC!$E$1:$M$2,1,$S106+1)) -> #N/A | V106: =MATCH(U106,INDIRECT("IMC!F" & N106 & ":R" &N106),1) -> #N/A | W106: =CONCATENATE(INDEX([4]IMC!$F$1:$R$5,5,$V106) & " e " & INDEX([4]IMC!$F$1:$R$5,5,$V106+1)) -> #N/A | X106: =U106*(I106*I106) -> 0 | Y106: =H106-X106 -> 0 | AA106: =VLOOKUP(F106,[4]IMC!$B$6:$R$210,5,FALSE) -> #N/A | AB106: =VLOOKUP(F106,[4]IMC!$B$6:$R$210,6,FALSE) -> #N/A | AC106: =VLOOKUP(F106,[4]IMC!$B$6:$R$210,7,FALSE) -> #N/A | AD106: =VLOOKUP(F106,[4]IMC!$B$6:$R$210,8,FALSE) -> #N/A | AE106: =VLOOKUP(F106,[4]IMC!$B$6:$R$210,9,FALSE) -> #N/A | AF106: =VLOOKUP(F106,[4]IMC!$B$6:$R$210,10,FALSE) -> #N/A | AG106: =VLOOKUP(F106,[4]IMC!$B$6:$R$210,11,FALSE) -> #N/A | AH106: =VLOOKUP(F106,[4]IMC!$B$6:$R$210,12,FALSE) -> #N/A | AI106: =VLOOKUP(F106,[4]IMC!$B$6:$R$210,13,FALSE) -> #N/A | AJ106: =VLOOKUP(F106,[4]IMC!$B$6:$R$210,14,FALSE) -> #N/A | AK106: =VLOOKUP(F106,[4]IMC!$B$6:$R$210,15,FALSE) -> #N/A | AL106: =VLOOKUP(F106,[4]IMC!$B$6:$R$210,16,FALSE) -> #N/A | AM106: =VLOOKUP(F106,[4]IMC!$B$6:$R$210,17,FALSE) -> #N/A
F107: =DATEDIF(E107,D107,"M") -> 0 | G107: =YEARFRAC(D107,E107) -> 0 | J107: =I107*100 -> 0 | L107: =K107/J107 -> #DIV/0! | M107: =IF(H107>0,IF(I107>0,H107/I107^2,""),"") | N107: =MATCH(F107,[4]IMC!B:B,0) -> #N/A | O107: =MATCH(M107,INDIRECT("IMC!F" & N107 & ":R" &N107),1) -> #N/A | P107: =CONCATENATE(INDEX([4]IMC!$F$1:$R$5,5,$O107) & " e " & INDEX([4]IMC!$F$1:$R$5,5,$O107+1)) -> #N/A | R107: =MATCH(F107,[4]PC!A:A,0) -> #N/A | S107: =MATCH(K107,INDIRECT("PC!E" & R107 & ":L" &R107),1) -> #N/A | T107: =CONCATENATE(INDEX([4]PC!$E$1:$M$2,1,$S107) & " e " & INDEX([4]PC!$E$1:$M$2,1,$S107+1)) -> #N/A | V107: =MATCH(U107,INDIRECT("IMC!F" & N107 & ":R" &N107),1) -> #N/A | W107: =CONCATENATE(INDEX([4]IMC!$F$1:$R$5,5,$V107) & " e " & INDEX([4]IMC!$F$1:$R$5,5,$V107+1)) -> #N/A | X107: =U107*(I107*I107) -> 0 | Y107: =H107-X107 -> 0 | AA107: =VLOOKUP(F107,[4]IMC!$B$6:$R$210,5,FALSE) -> #N/A | AB107: =VLOOKUP(F107,[4]IMC!$B$6:$R$210,6,FALSE) -> #N/A | AC107: =VLOOKUP(F107,[4]IMC!$B$6:$R$210,7,FALSE) -> #N/A | AD107: =VLOOKUP(F107,[4]IMC!$B$6:$R$210,8,FALSE) -> #N/A | AE107: =VLOOKUP(F107,[4]IMC!$B$6:$R$210,9,FALSE) -> #N/A | AF107: =VLOOKUP(F107,[4]IMC!$B$6:$R$210,10,FALSE) -> #N/A | AG107: =VLOOKUP(F107,[4]IMC!$B$6:$R$210,11,FALSE) -> #N/A | AH107: =VLOOKUP(F107,[4]IMC!$B$6:$R$210,12,FALSE) -> #N/A | AI107: =VLOOKUP(F107,[4]IMC!$B$6:$R$210,13,FALSE) -> #N/A | AJ107: =VLOOKUP(F107,[4]IMC!$B$6:$R$210,14,FALSE) -> #N/A | AK107: =VLOOKUP(F107,[4]IMC!$B$6:$R$210,15,FALSE) -> #N/A | AL107: =VLOOKUP(F107,[4]IMC!$B$6:$R$210,16,FALSE) -> #N/A | AM107: =VLOOKUP(F107,[4]IMC!$B$6:$R$210,17,FALSE) -> #N/A
F108: =DATEDIF(E108,D108,"M") -> 0 | G108: =YEARFRAC(D108,E108) -> 0 | J108: =I108*100 -> 0 | L108: =K108/J108 -> #DIV/0! | M108: =IF(H108>0,IF(I108>0,H108/I108^2,""),"") | N108: =MATCH(F108,[4]IMC!B:B,0) -> #N/A | O108: =MATCH(M108,INDIRECT("IMC!F" & N108 & ":R" &N108),1) -> #N/A | P108: =CONCATENATE(INDEX([4]IMC!$F$1:$R$5,5,$O108) & " e " & INDEX([4]IMC!$F$1:$R$5,5,$O108+1)) -> #N/A | R108: =MATCH(F108,[4]PC!A:A,0) -> #N/A | S108: =MATCH(K108,INDIRECT("PC!E" & R108 & ":L" &R108),1) -> #N/A | T108: =CONCATENATE(INDEX([4]PC!$E$1:$M$2,1,$S108) & " e " & INDEX([4]PC!$E$1:$M$2,1,$S108+1)) -> #N/A | V108: =MATCH(U108,INDIRECT("IMC!F" & N108 & ":R" &N108),1) -> #N/A | W108: =CONCATENATE(INDEX([4]IMC!$F$1:$R$5,5,$V108) & " e " & INDEX([4]IMC!$F$1:$R$5,5,$V108+1)) -> #N/A | X108: =U108*(I108*I108) -> 0 | Y108: =H108-X108 -> 0 | AA108: =VLOOKUP(F108,[4]IMC!$B$6:$R$210,5,FALSE) -> #N/A | AB108: =VLOOKUP(F108,[4]IMC!$B$6:$R$210,6,FALSE) -> #N/A | AC108: =VLOOKUP(F108,[4]IMC!$B$6:$R$210,7,FALSE) -> #N/A | AD108: =VLOOKUP(F108,[4]IMC!$B$6:$R$210,8,FALSE) -> #N/A | AE108: =VLOOKUP(F108,[4]IMC!$B$6:$R$210,9,FALSE) -> #N/A | AF108: =VLOOKUP(F108,[4]IMC!$B$6:$R$210,10,FALSE) -> #N/A | AG108: =VLOOKUP(F108,[4]IMC!$B$6:$R$210,11,FALSE) -> #N/A | AH108: =VLOOKUP(F108,[4]IMC!$B$6:$R$210,12,FALSE) -> #N/A | AI108: =VLOOKUP(F108,[4]IMC!$B$6:$R$210,13,FALSE) -> #N/A | AJ108: =VLOOKUP(F108,[4]IMC!$B$6:$R$210,14,FALSE) -> #N/A | AK108: =VLOOKUP(F108,[4]IMC!$B$6:$R$210,15,FALSE) -> #N/A | AL108: =VLOOKUP(F108,[4]IMC!$B$6:$R$210,16,FALSE) -> #N/A | AM108: =VLOOKUP(F108,[4]IMC!$B$6:$R$210,17,FALSE) -> #N/A
F109: =DATEDIF(E109,D109,"M") -> 0 | G109: =YEARFRAC(D109,E109) -> 0 | J109: =I109*100 -> 0 | L109: =K109/J109 -> #DIV/0! | M109: =IF(H109>0,IF(I109>0,H109/I109^2,""),"") | N109: =MATCH(F109,[4]IMC!B:B,0) -> #N/A | O109: =MATCH(M109,INDIRECT("IMC!F" & N109 & ":R" &N109),1) -> #N/A | P109: =CONCATENATE(INDEX([4]IMC!$F$1:$R$5,5,$O109) & " e " & INDEX([4]IMC!$F$1:$R$5,5,$O109+1)) -> #N/A | R109: =MATCH(F109,[4]PC!A:A,0) -> #N/A | S109: =MATCH(K109,INDIRECT("PC!E" & R109 & ":L" &R109),1) -> #N/A | T109: =CONCATENATE(INDEX([4]PC!$E$1:$M$2,1,$S109) & " e " & INDEX([4]PC!$E$1:$M$2,1,$S109+1)) -> #N/A | V109: =MATCH(U109,INDIRECT("IMC!F" & N109 & ":R" &N109),1) -> #N/A | W109: =CONCATENATE(INDEX([4]IMC!$F$1:$R$5,5,$V109) & " e " & INDEX([4]IMC!$F$1:$R$5,5,$V109+1)) -> #N/A | X109: =U109*(I109*I109) -> 0 | Y109: =H109-X109 -> 0 | AA109: =VLOOKUP(F109,[4]IMC!$B$6:$R$210,5,FALSE) -> #N/A | AB109: =VLOOKUP(F109,[4]IMC!$B$6:$R$210,6,FALSE) -> #N/A | AC109: =VLOOKUP(F109,[4]IMC!$B$6:$R$210,7,FALSE) -> #N/A | AD109: =VLOOKUP(F109,[4]IMC!$B$6:$R$210,8,FALSE) -> #N/A | AE109: =VLOOKUP(F109,[4]IMC!$B$6:$R$210,9,FALSE) -> #N/A | AF109: =VLOOKUP(F109,[4]IMC!$B$6:$R$210,10,FALSE) -> #N/A | AG109: =VLOOKUP(F109,[4]IMC!$B$6:$R$210,11,FALSE) -> #N/A | AH109: =VLOOKUP(F109,[4]IMC!$B$6:$R$210,12,FALSE) -> #N/A | AI109: =VLOOKUP(F109,[4]IMC!$B$6:$R$210,13,FALSE) -> #N/A | AJ109: =VLOOKUP(F109,[4]IMC!$B$6:$R$210,14,FALSE) -> #N/A | AK109: =VLOOKUP(F109,[4]IMC!$B$6:$R$210,15,FALSE) -> #N/A | AL109: =VLOOKUP(F109,[4]IMC!$B$6:$R$210,16,FALSE) -> #N/A | AM109: =VLOOKUP(F109,[4]IMC!$B$6:$R$210,17,FALSE) -> #N/A
F110: =DATEDIF(E110,D110,"M") -> 0 | G110: =YEARFRAC(D110,E110) -> 0 | J110: =I110*100 -> 0 | L110: =K110/J110 -> #DIV/0! | M110: =IF(H110>0,IF(I110>0,H110/I110^2,""),"") | N110: =MATCH(F110,[4]IMC!B:B,0) -> #N/A | O110: =MATCH(M110,INDIRECT("IMC!F" & N110 & ":R" &N110),1) -> #N/A | P110: =CONCATENATE(INDEX([4]IMC!$F$1:$R$5,5,$O110) & " e " & INDEX([4]IMC!$F$1:$R$5,5,$O110+1)) -> #N/A | R110: =MATCH(F110,[4]PC!A:A,0) -> #N/A | S110: =MATCH(K110,INDIRECT("PC!E" & R110 & ":L" &R110),1) -> #N/A | T110: =CONCATENATE(INDEX([4]PC!$E$1:$M$2,1,$S110) & " e " & INDEX([4]PC!$E$1:$M$2,1,$S110+1)) -> #N/A | V110: =MATCH(U110,INDIRECT("IMC!F" & N110 & ":R" &N110),1) -> #N/A | W110: =CONCATENATE(INDEX([4]IMC!$F$1:$R$5,5,$V110) & " e " & INDEX([4]IMC!$F$1:$R$5,5,$V110+1)) -> #N/A | X110: =U110*(I110*I110) -> 0 | Y110: =H110-X110 -> 0 | AA110: =VLOOKUP(F110,[4]IMC!$B$6:$R$210,5,FALSE) -> #N/A | AB110: =VLOOKUP(F110,[4]IMC!$B$6:$R$210,6,FALSE) -> #N/A | AC110: =VLOOKUP(F110,[4]IMC!$B$6:$R$210,7,FALSE) -> #N/A | AD110: =VLOOKUP(F110,[4]IMC!$B$6:$R$210,8,FALSE) -> #N/A | AE110: =VLOOKUP(F110,[4]IMC!$B$6:$R$210,9,FALSE) -> #N/A | AF110: =VLOOKUP(F110,[4]IMC!$B$6:$R$210,10,FALSE) -> #N/A | AG110: =VLOOKUP(F110,[4]IMC!$B$6:$R$210,11,FALSE) -> #N/A | AH110: =VLOOKUP(F110,[4]IMC!$B$6:$R$210,12,FALSE) -> #N/A | AI110: =VLOOKUP(F110,[4]IMC!$B$6:$R$210,13,FALSE) -> #N/A | AJ110: =VLOOKUP(F110,[4]IMC!$B$6:$R$210,14,FALSE) -> #N/A | AK110: =VLOOKUP(F110,[4]IMC!$B$6:$R$210,15,FALSE) -> #N/A | AL110: =VLOOKUP(F110,[4]IMC!$B$6:$R$210,16,FALSE) -> #N/A | AM110: =VLOOKUP(F110,[4]IMC!$B$6:$R$210,17,FALSE) -> #N/A
F111: =DATEDIF(E111,D111,"M") -> 0 | G111: =YEARFRAC(D111,E111) -> 0 | J111: =I111*100 -> 0 | L111: =K111/J111 -> #DIV/0! | M111: =IF(H111>0,IF(I111>0,H111/I111^2,""),"") | N111: =MATCH(F111,[4]IMC!B:B,0) -> #N/A | O111: =MATCH(M111,INDIRECT("IMC!F" & N111 & ":R" &N111),1) -> #N/A | P111: =CONCATENATE(INDEX([4]IMC!$F$1:$R$5,5,$O111) & " e " & INDEX([4]IMC!$F$1:$R$5,5,$O111+1)) -> #N/A | R111: =MATCH(F111,[4]PC!A:A,0) -> #N/A | S111: =MATCH(K111,INDIRECT("PC!E" & R111 & ":L" &R111),1) -> #N/A | T111: =CONCATENATE(INDEX([4]PC!$E$1:$M$2,1,$S111) & " e " & INDEX([4]PC!$E$1:$M$2,1,$S111+1)) -> #N/A | V111: =MATCH(U111,INDIRECT("IMC!F" & N111 & ":R" &N111),1) -> #N/A | W111: =CONCATENATE(INDEX([4]IMC!$F$1:$R$5,5,$V111) & " e " & INDEX([4]IMC!$F$1:$R$5,5,$V111+1)) -> #N/A | X111: =U111*(I111*I111) -> 0 | Y111: =H111-X111 -> 0 | AA111: =VLOOKUP(F111,[4]IMC!$B$6:$R$210,5,FALSE) -> #N/A | AB111: =VLOOKUP(F111,[4]IMC!$B$6:$R$210,6,FALSE) -> #N/A | AC111: =VLOOKUP(F111,[4]IMC!$B$6:$R$210,7,FALSE) -> #N/A | AD111: =VLOOKUP(F111,[4]IMC!$B$6:$R$210,8,FALSE) -> #N/A | AE111: =VLOOKUP(F111,[4]IMC!$B$6:$R$210,9,FALSE) -> #N/A | AF111: =VLOOKUP(F111,[4]IMC!$B$6:$R$210,10,FALSE) -> #N/A | AG111: =VLOOKUP(F111,[4]IMC!$B$6:$R$210,11,FALSE) -> #N/A | AH111: =VLOOKUP(F111,[4]IMC!$B$6:$R$210,12,FALSE) -> #N/A | AI111: =VLOOKUP(F111,[4]IMC!$B$6:$R$210,13,FALSE) -> #N/A | AJ111: =VLOOKUP(F111,[4]IMC!$B$6:$R$210,14,FALSE) -> #N/A | AK111: =VLOOKUP(F111,[4]IMC!$B$6:$R$210,15,FALSE) -> #N/A | AL111: =VLOOKUP(F111,[4]IMC!$B$6:$R$210,16,FALSE) -> #N/A | AM111: =VLOOKUP(F111,[4]IMC!$B$6:$R$210,17,FALSE) -> #N/A
F112: =DATEDIF(E112,D112,"M") -> 0 | G112: =YEARFRAC(D112,E112) -> 0 | J112: =I112*100 -> 0 | L112: =K112/J112 -> #DIV/0! | M112: =IF(H112>0,IF(I112>0,H112/I112^2,""),"") | N112: =MATCH(F112,[4]IMC!B:B,0) -> #N/A | O112: =MATCH(M112,INDIRECT("IMC!F" & N112 & ":R" &N112),1) -> #N/A | P112: =CONCATENATE(INDEX([4]IMC!$F$1:$R$5,5,$O112) & " e " & INDEX([4]IMC!$F$1:$R$5,5,$O112+1)) -> #N/A | R112: =MATCH(F112,[4]PC!A:A,0) -> #N/A | S112: =MATCH(K112,INDIRECT("PC!E" & R112 & ":L" &R112),1) -> #N/A | T112: =CONCATENATE(INDEX([4]PC!$E$1:$M$2,1,$S112) & " e " & INDEX([4]PC!$E$1:$M$2,1,$S112+1)) -> #N/A | V112: =MATCH(U112,INDIRECT("IMC!F" & N112 & ":R" &N112),1) -> #N/A | W112: =CONCATENATE(INDEX([4]IMC!$F$1:$R$5,5,$V112) & " e " & INDEX([4]IMC!$F$1:$R$5,5,$V112+1)) -> #N/A | X112: =U112*(I112*I112) -> 0 | Y112: =H112-X112 -> 0 | AA112: =VLOOKUP(F112,[4]IMC!$B$6:$R$210,5,FALSE) -> #N/A | AB112: =VLOOKUP(F112,[4]IMC!$B$6:$R$210,6,FALSE) -> #N/A | AC112: =VLOOKUP(F112,[4]IMC!$B$6:$R$210,7,FALSE) -> #N/A | AD112: =VLOOKUP(F112,[4]IMC!$B$6:$R$210,8,FALSE) -> #N/A | AE112: =VLOOKUP(F112,[4]IMC!$B$6:$R$210,9,FALSE) -> #N/A | AF112: =VLOOKUP(F112,[4]IMC!$B$6:$R$210,10,FALSE) -> #N/A | AG112: =VLOOKUP(F112,[4]IMC!$B$6:$R$210,11,FALSE) -> #N/A | AH112: =VLOOKUP(F112,[4]IMC!$B$6:$R$210,12,FALSE) -> #N/A | AI112: =VLOOKUP(F112,[4]IMC!$B$6:$R$210,13,FALSE) -> #N/A | AJ112: =VLOOKUP(F112,[4]IMC!$B$6:$R$210,14,FALSE) -> #N/A | AK112: =VLOOKUP(F112,[4]IMC!$B$6:$R$210,15,FALSE) -> #N/A | AL112: =VLOOKUP(F112,[4]IMC!$B$6:$R$210,16,FALSE) -> #N/A | AM112: =VLOOKUP(F112,[4]IMC!$B$6:$R$210,17,FALSE) -> #N/A
